Workbook

Sheet Sheet8
A1: Years | B1: Planterware Profit % | C1: Forecast(Planterware Profit %) | D1: Lower Confidence Bound(Planterware Profit %) | E1: Upper Confidence Bound(Planterware Profit %)
A2: 2006 | B2: 0
A3: 2007 | B3: 0
A4: 2008 | B4: 0
A5: 2009 | B5: 0
A6: 2010 | B6: 0.015657436
A7: 2011 | B7: -0.011998599
A8: 2012 | B8: -0.0086839589 | C8: -0.0086839589 | D8: -0.0086839589 | E8: -0.0086839589
A9: 2013 | C9: =_xlfn.FORECAST.ETS(A9,$B$2:$B$8,$A$2:$A$8,1,1) -> -0.0084742344 | D9: =C9-_xlfn.FORECAST.ETS.CONFINT(A9,$B$2:$B$8,$A$2:$A$8,0.95,1,1) -> -0.024712869 | E9: =C9+_xlfn.FORECAST.ETS.CONFINT(A9,$B$2:$B$8,$A$2:$A$8,0.95,1,1) -> 0.0077644
A10: 2014 | C10: =_xlfn.FORECAST.ETS(A10,$B$2:$B$8,$A$2:$A$8,1,1) -> -0.0096819835 | D10: =C10-_xlfn.FORECAST.ETS.CONFINT(A10,$B$2:$B$8,$A$2:$A$8,0.95,1,1) -> -0.025920691 | E10: =C10+_xlfn.FORECAST.ETS.CONFINT(A10,$B$2:$B$8,$A$2:$A$8,0.95,1,1) -> 0.006556724
A11: 2015 | C11: =_xlfn.FORECAST.ETS(A11,$B$2:$B$8,$A$2:$A$8,1,1) -> -0.010889733 | D11: =C11-_xlfn.FORECAST.ETS.CONFINT(A11,$B$2:$B$8,$A$2:$A$8,0.95,1,1) -> -0.02712857 | E11: =C11+_xlfn.FORECAST.ETS.CONFINT(A11,$B$2:$B$8,$A$2:$A$8,0.95,1,1) -> 0.0053491047
A12: 2016 | C12: =_xlfn.FORECAST.ETS(A12,$B$2:$B$8,$A$2:$A$8,1,1) -> -0.012097482 | D12: =C12-_xlfn.FORECAST.ETS.CONFINT(A12,$B$2:$B$8,$A$2:$A$8,0.95,1,1) -> -0.028336522 | E12: =C12+_xlfn.FORECAST.ETS.CONFINT(A12,$B$2:$B$8,$A$2:$A$8,0.95,1,1) -> 0.0041415586
A13: 2017 | C13: =_xlfn.FORECAST.ETS(A13,$B$2:$B$8,$A$2:$A$8,1,1) -> -0.013305231 | D13: =C13-_xlfn.FORECAST.ETS.CONFINT(A13,$B$2:$B$8,$A$2:$A$8,0.95,1,1) -> -0.029544563 | E13: =C13+_xlfn.FORECAST.ETS.CONFINT(A13,$B$2:$B$8,$A$2:$A$8,0.95,1,1) -> 0.0029341018

Sheet Sheet9
A1: Years | B1: Self Watering Profit % | C1: Forecast(Self Watering Profit %) | D1: Lower Confidence Bound(Self Watering Profit %) | E1: Upper Confidence Bound(Self Watering Profit %)
A2: 2006 | B2: 0.84680475
A3: 2007 | B3: 0.87116813
A4: 2008 | B4: 0.85565081
A5: 2009 | B5: 0.8943359
A6: 2010 | B6: 0.64545676
A7: 2011 | B7: 0.75770816
A8: 2012 | B8: 0.74140511 | C8: 0.74140511 | D8: 0.74140511 | E8: 0.74140511
A9: 2013 | C9: =_xlfn.FORECAST.ETS(A9,$B$2:$B$8,$A$2:$A$8,1,1) -> 0.67772982 | D9: =C9-_xlfn.FORECAST.ETS.CONFINT(A9,$B$2:$B$8,$A$2:$A$8,0.95,1,1) -> 0.53691202 | E9: =C9+_xlfn.FORECAST.ETS.CONFINT(A9,$B$2:$B$8,$A$2:$A$8,0.95,1,1) -> 0.81854763
A10: 2014 | C10: =_xlfn.FORECAST.ETS(A10,$B$2:$B$8,$A$2:$A$8,1,1) -> 0.6510101 | D10: =C10-_xlfn.FORECAST.ETS.CONFINT(A10,$B$2:$B$8,$A$2:$A$8,0.95,1,1) -> 0.50947587 | E10: =C10+_xlfn.FORECAST.ETS.CONFINT(A10,$B$2:$B$8,$A$2:$A$8,0.95,1,1) -> 0.79254432
A11: 2015 | C11: =_xlfn.FORECAST.ETS(A11,$B$2:$B$8,$A$2:$A$8,1,1) -> 0.62429037 | D11: =C11-_xlfn.FORECAST.ETS.CONFINT(A11,$B$2:$B$8,$A$2:$A$8,0.95,1,1) -> 0.48202918 | E11: =C11+_xlfn.FORECAST.ETS.CONFINT(A11,$B$2:$B$8,$A$2:$A$8,0.95,1,1) -> 0.76655155
A12: 2016 | C12: =_xlfn.FORECAST.ETS(A12,$B$2:$B$8,$A$2:$A$8,1,1) -> 0.59757064 | D12: =C12-_xlfn.FORECAST.ETS.CONFINT(A12,$B$2:$B$8,$A$2:$A$8,0.95,1,1) -> 0.45457198 | E12: =C12+_xlfn.FORECAST.ETS.CONFINT(A12,$B$2:$B$8,$A$2:$A$8,0.95,1,1) -> 0.7405693
A13: 2017 | C13: =_xlfn.FORECAST.ETS(A13,$B$2:$B$8,$A$2:$A$8,1,1) -> 0.57085091 | D13: =C13-_xlfn.FORECAST.ETS.CONFINT(A13,$B$2:$B$8,$A$2:$A$8,0.95,1,1) -> 0.42710428 | E13: =C13+_xlfn.FORECAST.ETS.CONFINT(A13,$B$2:$B$8,$A$2:$A$8,0.95,1,1) -> 0.71459755

Sheet Profit Data
A1: Profitin_2012 | B1: Profitin_2011 | C1: Profitin_2010 | D1: Profitin_2009 | E1: Profitin_2008 | F1: Profitin_2007 | G1: Profitin_2006 | H1: Product Family
A2: -938 | B2: -5593 | C2: 0 | D2: 0 | E2: 0 | F2: 0 | G2: 0 | H2: Planterware
A3: -660 | B3: -2860 | C3: -11 | D3: 0 | E3: 0 | F3: 0 | G3: 0 | H3: Planterware
A4: 0 | B4: 16020 | C4: 0 | D4: 0 | E4: 0 | F4: 0 | G4: 0 | H4: Self-Watering
A5: 0 | B5: 3500 | C5: 0 | D5: 0 | E5: 0 | F5: 0 | G5: 0 | H5: Self-Watering
A6: 0 | B6: 1500 | C6: 0 | D6: 0 | E6: 0 | F6: 0 | G6: 0 | H6: Self-Watering
A7: 0 | B7: 1500 | C7: 0 | D7: 0 | E7: 0 | F7: 0 | G7: 0 | H7: Self-Watering
A8: 0 | B8: 1250 | C8: 0 | D8: 0 | E8: 0 | F8: 0 | G8: 0 | H8: Self-Watering
A9: 0 | B9: 1250 | C9: 0 | D9: 0 | E9: 0 | F9: 0 | G9: 0 | H9: Self-Watering
A10: 0 | B10: 500 | C10: 0 | D10: 0 | E10: 0 | F10: 0 | G10: 0 | H10: Self-Watering
A11: 0 | B11: 455 | C11: 0 | D11: 0 | E11: 0 | F11: 0 | G11: 0 | H11: Self-Watering
A12: 0 | B12: 400 | C12: 0 | D12: 0 | E12: 0 | F12: 0 | G12: 0 | H12: Self-Watering
A13: 0 | B13: 370 | C13: 0 | D13: 0 | E13: 0 | F13: 0 | G13: 0 | H13: Self-Watering
... A203: 164606 | B203: 147956 | C203: 322452 | D203: 8450 | E203: 0 | F203: 0 | G203: 0 | H203: Bins
D208: Years | E208: Bins | F208: Planterware | G208: Self Watering | H208: Total Profit | K208: Years | L208: Bins Profit % | M208: Planterware Profit % | N208: Self Watering Profit %
D209: 2006 | E209: =SUM(G2:G20) -> 0 | F209: =SUM(G22:G58) -> 0 | G209: =SUM(G59:G203) -> 943793.2 | H209: 943793 | K209: 2006 | L209: =E209/H209 -> 0 | M209: =F209/H209 -> 0 | N209: =G209/H209 -> 1.0000002
D210: 2007 | E210: =SUM(F2:F21) -> 0 | F210: =SUM(F22:F58) -> 1468.8 | G210: =SUM(F59:F203) -> 1026848 | H210: 1028317 | K210: 2007 | L210: =E210/H210 -> 0 | M210: =F210/H210 -> 0.0014283533 | N210: =G210/H210 -> 0.99857145
D211: 2008 | E211: =SUM(E2:E21) -> 4104 | F211: =SUM(E22:E58) -> 6487.2 | G211: =SUM(E59:E203) -> 971913.4 | H211: 982505 | K211: 2008 | L211: =E211/H211 -> 0.004177078 | M211: =F211/H211 -> 0.0066027145 | N211: =G211/H211 -> 0.9892198
D212: 2009 | E212: =SUM(D2:D21) -> 108 | F212: =SUM(D22:D58) -> 1849.8 | G212: =SUM(D59:D203) -> 834856.2 | H212: 836814 | K212: 2009 | L212: =E212/H212 -> 0.00012906094 | M212: =F212/H212 -> 0.0022105271 | N212: =G212/H212 -> 0.99766041
D213: 2010 | E213: =SUM(C2:C21) -> -11 | F213: =SUM(C22:C58) -> 9228.8 | G213: =SUM(C59:C203) -> 1236995.1 | H213: 1246213 | K213: 2010 | L213: =E213/H213 -> -8.8267415e-06 | M213: =F213/H213 -> 0.0074054756 | N213: =G213/H213 -> 0.99260327
D214: 2011 | E214: =SUM(B2:B21) -> 20129 | F214: =SUM(B22:B58) -> 8157.3 | G214: =SUM(B59:B203) -> 1039797 | H214: 1068083 | K214: 2011 | L214: =E214/H214 -> 0.018845914 | M214: =F214/H214 -> 0.0076373278 | N214: =G214/H214 -> 0.97351704
D215: 2012 | E215: =SUM(A2:A21) -> -1598 | F215: =SUM(B22:B58) -> 8157.3 | G215: =SUM(A59:A203) -> 1470701 | H215: 1475767 | K215: 2012 | L215: =E215/H215 -> -0.0010828268 | M215: =F215/H215 -> 0.0055274986 | N215: =G215/H215 -> 0.99656721
I220: Year | J220: Total Profit | K220: Total Sales
I221: 2006 | J221: 943793 | K221: 24122
I222: 2007 | J222: 1028317 | K222: 25891
I223: 2008 | J223: 982505 | K223: 24809
I224: 2009 | J224: 836814 | K224: 23226
I225: 2010 | J225: 1246213 | K225: 22470
I226: 2011 | J226: 1068083 | K226: 24843
I227: 2012 | J227: 1475767 | K227: 29941
H255: Sales_in2012 | I255: Profit_in2012 | J255: Sales_in2011 | K255: Profit_in2011 | L255: Sales_in2010 | M255: Profit_in2010 | N255: Sales_in2009 | O255: Profit_in2009 | P255: Sales_in2008 | Q255: Profit_in2008 | R255: Sales_in2007 | S255: Profit_in2007 | T255: Sales_in_2006 | U255: Profit_in2006 | V255: Total_of_Sales | W255: Product Family | X255: Due Date Performance
H256: 0 | I256: 0 | J256: 1 | K256: 220 | L256: 0 | M256: 0 | N256: 1 | O256: 108 | P256: 38 | Q256: 4104 | R256: 0 | S256: 0 | T256: 0 | U256: 0 | V256: 40 | W256: Self-Watering | X256: 98
H257: 0 | I257: 0 | J257: 0 | K257: 0 | L257: 0 | M257: 0 | N257: 0 | O257: 0 | P257: 12 | Q257: 4932 | R257: 0 | S257: 0 | T257: 0 | U257: 0 | V257: 12 | W257: Self-Watering | X257: 96
H258: 0 | I258: 0 | J258: 0 | K258: 0 | L258: 0 | M258: 0 | N258: 1 | O258: 183.4 | P258: 0 | Q258: 0 | R258: 0 | S258: 0 | T258: 0 | U258: 0 | V258: 1 | W258: Self-Watering | X258: 93
H259: 0 | I259: 0 | J259: 0 | K259: 0 | L259: 0 | M259: 0 | N259: 0 | O259: 0 | P259: 0 | Q259: 0 | R259: 0 | S259: 0 | T259: 0 | U259: 0 | V259: 0 | W259: Planterware | X259: 93
H260: 0 | I260: 0 | J260: 0 | K260: 0 | L260: 0 | M260: 0 | N260: 0 | O260: 0 | P260: 0 | Q260: 0 | R260: 0 | S260: 0 | T260: 0 | U260: 0 | V260: 0 | W260: Planterware | X260: 99
H261: 2 | I261: 416.8 | J261: 34 | K261: 11296.8 | L261: 36 | M261: 7502.4 | N261: 2 | O261: 416.8 | P261: 0 | Q261: 0 | R261: 0 | S261: 0 | T261: 0 | U261: 0 | V261: 74 | W261: Self-Watering | X261: 92
H262: 5 | I262: 690 | J262: 0 | K262: -560 | L262: 0 | M262: 0 | N262: 2 | O262: 276 | P262: 52 | Q262: 7176 | R262: 0 | S262: 0 | T262: 0 | U262: 0 | V262: 59 | W262: Self-Watering | X262: 95
H263: 5 | I263: 430 | J263: 7 | K263: 630 | L263: 3 | M263: 258 | N263: 8 | O263: 688 | P263: 0 | Q263: 0 | R263: 0 | S263: 0 | T263: 0 | U263: 0 | V263: 23 | W263: Bins | X263: 91
H264: 7 | I264: 2072 | J264: 2 | K264: -178 | L264: 3 | M264: 888 | N264: 1 | O264: 296 | P264: 8 | Q264: 2368 | R264: 0 | S264: 0 | T264: 0 | U264: 0 | V264: 21 | W264: Self-Watering | X264: 95
H265: 10 | I265: 432 | J265: 10 | K265: 432 | L265: 12 | M265: 518.4 | N265: 13 | O265: 561.6 | P265: 36 | Q265: 1555.2 | R265: 34 | S265: 1468.8 | T265: 0 | U265: 0 | V265: 115 | W265: Self-Watering | X265: 98
H266: 10 | I266: 1004 | J266: 0 | K266: -196 | L266: 0 | M266: 0 | N266: 0 | O266: 0 | P266: 0 | Q266: 0 | R266: 0 | S266: 0 | T266: 0 | U266: 0 | V266: 10 | W266: Bins | X266: 98
H267: 12 | I267: 2352 | J267: 12 | K267: 2352 | L267: 9 | M267: 1764 | N267: 10 | O267: 1960 | P267: 13 | Q267: 2548 | R267: 13 | S267: 2548 | T267: 15 | U267: 2940 | V267: 69 | W267: Bins | X267: 93
... H351: 1578 | I351: 53652 | J351: 1450 | K351: 46612 | L351: 1135 | M351: 38590 | N351: 957 | O351: 32538 | P351: 2300 | Q351: 78200 | R351: 2780 | S351: 94520 | T351: 2800 | U351: 95200 | V351: 10200 | W351: Self-Watering | X351: 95
S406: Bins | T406: Planterware | U406: Self_Watering
R407: 2006 | S407: 1230
R408: 2007 | S408: 1453
R409: 2008 | S409: 1674
R410: 2009 | S410: 1328
R411: 2010 | S411: 2543
R412: 2011 | S412: 2081
R413: 2012 | S413: 2048
A426: Salesin_2012 | C426: Salesin_2011 | E426: Salesin_2010 | G426: Salesin_2009 | I426: Salesin_2008 | K426: Salesin_2007 | L426: Profitin_2007 | M426: Salesin_2006 | N426: Profitin_2006 | O426: Total Nr of Sales | P426: Product Family | Q426: Due Date Performance/%
A427: 0 | C427: 1 | E427: 0 | G427: 1 | I427: 38 | K427: 0 | L427: 0 | M427: 0 | N427: 0 | O427: 40 | P427: Self-Watering | Q427: 98
A428: 0 | C428: 0 | E428: 0 | G428: 0 | I428: 12 | K428: 0 | L428: 0 | M428: 0 | N428: 0 | O428: 12 | P428: Self-Watering | Q428: 96
A429: 0 | C429: 0 | E429: 0 | G429: 1 | I429: 0 | K429: 0 | L429: 0 | M429: 0 | N429: 0 | O429: 1 | P429: Self-Watering | Q429: 93
A430: 0 | C430: 0 | E430: 0 | G430: 0 | I430: 0 | K430: 0 | L430: 0 | M430: 0 | N430: 0 | O430: 0 | P430: Planterware | Q430: 93
A431: 0 | C431: 0 | E431: 0 | G431: 0 | I431: 0 | K431: 0 | L431: 0 | M431: 0 | N431: 0 | O431: 0 | P431: Planterware | Q431: 99
A432: 2 | C432: 34 | E432: 36 | G432: 2 | I432: 0 | K432: 0 | L432: 0 | M432: 0 | N432: 0 | O432: 74 | P432: Self-Watering | Q432: 92
A433: 5 | C433: 0 | E433: 0 | G433: 2 | I433: 52 | K433: 0 | L433: 0 | M433: 0 | N433: 0 | O433: 59 | P433: Self-Watering | Q433: 95
A434: 5 | C434: 7 | E434: 3 | G434: 8 | I434: 0 | K434: 0 | L434: 0 | M434: 0 | N434: 0 | O434: 23 | P434: Bins | Q434: 91
A435: 7 | C435: 2 | E435: 3 | G435: 1 | I435: 8 | K435: 0 | L435: 0 | M435: 0 | N435: 0 | O435: 21 | P435: Self-Watering | Q435: 95
A436: 10 | C436: 10 | E436: 12 | G436: 13 | I436: 36 | K436: 34 | L436: 1468.8 | M436: 0 | N436: 0 | O436: 115 | P436: Self-Watering | Q436: 98
A437: 10 | C437: 0 | E437: 0 | G437: 0 | I437: 0 | K437: 0 | L437: 0 | M437: 0 | N437: 0 | O437: 10 | P437: Bins | Q437: 98
A438: 12 | C438: 12 | E438: 9 | G438: 10 | I438: 13 | K438: 13 | L438: 2548 | M438: 15 | N438: 2940 | O438: 69 | P438: Bins | Q438: 93
... A628: 5 | C628: 0 | E628: 0 | G628: 0 | I628: 0 | K628: 0 | L628: 0 | M628: 0 | N628: 0 | O628: 5 | P628: Self-Watering | Q628: 97
E643: Salesin_2012 | F643: Salesin_2011 | G643: Salesin_2010 | H643: Salesin_2009 | I643: Salesin_2008 | J643: Salesin_2007 | K643: Salesin_2006 | L643: Product Family
E644: 0 | F644: 1 | G644: 0 | H644: 1 | I644: 38 | J644: 0 | K644: 0 | L644: Self-Watering
E645: 0 | F645: 0 | G645: 0 | H645: 0 | I645: 12 | J645: 0 | K645: 0 | L645: Self-Watering
E646: 0 | F646: 0 | G646: 0 | H646: 1 | I646: 0 | J646: 0 | K646: 0 | L646: Self-Watering
E647: 0 | F647: 0 | G647: 0 | H647: 0 | I647: 0 | J647: 0 | K647: 0 | L647: Planterware
E648: 0 | F648: 0 | G648: 0 | H648: 0 | I648: 0 | J648: 0 | K648: 0 | L648: Planterware
E649: 2 | F649: 34 | G649: 36 | H649: 2 | I649: 0 | J649: 0 | K649: 0 | L649: Self-Watering
E650: 5 | F650: 0 | G650: 0 | H650: 2 | I650: 52 | J650: 0 | K650: 0 | L650: Self-Watering
E651: 5 | F651: 7 | G651: 3 | H651: 8 | I651: 0 | J651: 0 | K651: 0 | L651: Bins
E652: 7 | F652: 2 | G652: 3 | H652: 1 | I652: 8 | J652: 0 | K652: 0 | L652: Self-Watering
E653: 10 | F653: 10 | G653: 12 | H653: 13 | I653: 36 | J653: 34 | K653: 0 | L653: Self-Watering
E654: 10 | F654: 0 | G654: 0 | H654: 0 | I654: 0 | J654: 0 | K654: 0 | L654: Bins
E655: 12 | F655: 12 | G655: 9 | H655: 10 | I655: 13 | J655: 13 | K655: 15 | L655: Bins
... E845: 5 | F845: 0 | G845: 0 | H845: 0 | I845: 0 | J845: 0 | K845: 0 | L845: Self-Watering

Sheet DraftDataset (2)
A1: Product | B1: Description | C1: Colour | D1: Powder_weight_kg | E1: Powder_Cost | F1: Selling_Price_Pound | G1: Profit | H1: Sales_in2012 | I1: Profit_in2012 | J1: Sales_in2011 | K1: Profit_in2011 | L1: Sales_in2010 | M1: Profit_in2010 | N1: Sales_in2009 | O1: Profit_in2009 | P1: Sales_in2008 | Q1: Profit_in2008 | R1: Sales_in2007 | S1: Profit_in2007 | T1: Sales_in_2006 | U1: Profit_in2006 | V1: Total_of_Sales | W1: Product Family | X1: Due Date Performance
A2: MSP 1P | B2: Meter sq planter (1) | C2: Black | D2: 40 | E2: 112 | F2: 220 | G2: 108 | H2: 0 | I2: 0 | J2: 1 | K2: 220 | L2: 0 | M2: 0 | N2: 1 | O2: 108 | P2: 38 | Q2: 4104 | R2: 0 | S2: 0 | T2: 0 | U2: 0 | V2: 40 | W2: Self-Watering | X2: 98
A3: MSP 4P | B3: Meter sq planter (4) | C3: Black | D3: 60 | E3: 168 | F3: 579 | G3: 411 | H3: 0 | I3: 0 | J3: 0 | K3: 0 | L3: 0 | M3: 0 | N3: 0 | O3: 0 | P3: 12 | Q3: 4932 | R3: 0 | S3: 0 | T3: 0 | U3: 0 | V3: 12 | W3: Self-Watering | X3: 96
A4: OCT 2P | B4: Octagonal fountain (2) | C4: Black | D4: 47 | E4: 131.6 | F4: 315 | G4: 183.4 | H4: 0 | I4: 0 | J4: 0 | K4: 0 | L4: 0 | M4: 0 | N4: 1 | O4: 183.4 | P4: 0 | Q4: 0 | R4: 0 | S4: 0 | T4: 0 | U4: 0 | V4: 1 | W4: Self-Watering | X4: 93
A5: J-C41 | B5: Cylinder | C5: Black | D5: 14 | E5: 39.2 | F5: 30 | G5: -9.2 | H5: 0 | I5: 0 | J5: 0 | K5: 0 | L5: 0 | M5: 0 | N5: 0 | O5: 0 | P5: 0 | Q5: 0 | R5: 0 | S5: 0 | T5: 0 | U5: 0 | V5: 0 | W5: Planterware | X5: 93
A6: J-C45-T3 | B6: Cylinder | C6: Black | D6: 17 | E6: 47.6 | F6: 38 | G6: -9.6 | H6: 0 | I6: 0 | J6: 0 | K6: 0 | L6: 0 | M6: 0 | N6: 0 | O6: 0 | P6: 0 | Q6: 0 | R6: 0 | S6: 0 | T6: 0 | U6: 0 | V6: 0 | W6: Planterware | X6: 99
A7: MSP 2P | B7: Meter sq planter (2) | C7: Black | D7: 47 | E7: 131.6 | F7: 340 | G7: 208.4 | H7: 2 | I7: 416.8 | J7: 34 | K7: 11296.8 | L7: 36 | M7: 7502.4 | N7: 2 | O7: 416.8 | P7: 0 | Q7: 0 | R7: 0 | S7: 0 | T7: 0 | U7: 0 | V7: 74 | W7: Self-Watering | X7: 92
A8: OCT 1P | B8: Octagonal fountain (1) | C8: Black | D8: 40 | E8: 112 | F8: 250 | G8: 138 | H8: 5 | I8: 690 | J8: 0 | K8: -560 | L8: 0 | M8: 0 | N8: 2 | O8: 276 | P8: 52 | Q8: 7176 | R8: 0 | S8: 0 | T8: 0 | U8: 0 | V8: 59 | W8: Self-Watering | X8: 95
A9: SCW 0P | B9: Screwball post bin | C9: Black | D9: 5 | E9: 14 | F9: 100 | G9: 86 | H9: 5 | I9: 430 | J9: 7 | K9: 630 | L9: 3 | M9: 258 | N9: 8 | O9: 688 | P9: 0 | Q9: 0 | R9: 0 | S9: 0 | T9: 0 | U9: 0 | V9: 23 | W9: Bins | X9: 91
A10: OCT 3P | B10: Octagonal fountain (3) | C10: Black | D10: 55 | E10: 154 | F10: 450 | G10: 296 | H10: 7 | I10: 2072 | J10: 2 | K10: -178 | L10: 3 | M10: 888 | N10: 1 | O10: 296 | P10: 8 | Q10: 2368 | R10: 0 | S10: 0 | T10: 0 | U10: 0 | V10: 21 | W10: Self-Watering | X10: 95
A11: WBX 0P | B11: Wall and window box | C11: Black | D11: 6 | E11: 16.8 | F11: 60 | G11: 43.2 | H11: 10 | I11: 432 | J11: 10 | K11: 432 | L11: 12 | M11: 518.4 | N11: 13 | O11: 561.6 | P11: 36 | Q11: 1555.2 | R11: 34 | S11: 1468.8 | T11: 0 | U11: 0 | V11: 115 | W11: Self-Watering | X11: 98
A12: POOP 0P | B12: Poo bin | C12: Black | D12: 7 | E12: 19.6 | F12: 120 | G12: 100.4 | H12: 10 | I12: 1004 | J12: 0 | K12: -196 | L12: 0 | M12: 0 | N12: 0 | O12: 0 | P12: 0 | Q12: 0 | R12: 0 | S12: 0 | T12: 0 | U12: 0 | V12: 10 | W12: Bins | X12: 98
A13: PAR 1P | B13: Parot bin | C13: Black | D13: 30 | E13: 84 | F13: 280 | G13: 196 | H13: 12 | I13: 2352 | J13: 12 | K13: 2352 | L13: 9 | M13: 1764 | N13: 10 | O13: 1960 | P13: 13 | Q13: 2548 | R13: 13 | S13: 2548 | T13: 15 | U13: 2940 | V13: 69 | W13: Bins | X13: 93
... A97: CNS 1P | B97: Cup and Saucer on pole | C97: Standard Green | D97: 7 | E97: 21 | F97: 55 | G97: 34 | H97: 1578 | I97: 53652 | J97: 1450 | K97: 46612 | L97: 1135 | M97: 38590 | N97: 957 | O97: 32538 | P97: 2300 | Q97: 78200 | R97: 2780 | S97: 94520 | T97: 2800 | U97: 95200 | V97: 10200 | W97: Self-Watering | X97: 95

Sheet CleanedDataset
A1: Product | B1: Description | C1: Colour | D1: Powder_weight_kg | E1: Powder_Cost | F1: Selling_Price_Pound | G1: Profit | H1: Profit_Margin | I1: Salesin_2012 | J1: Profitin_2012 | K1: Salesin_2011 | L1: Profitin_2011 | M1: Salesin_2010 | N1: Profitin_2010 | O1: Salesin_2009 | P1: Profitin_2009 | Q1: Salesin_2008 | R1: Profitin_2008 | S1: Salesin_2007 | T1: Profitin_2007 | U1: Salesin_2006 | V1: Profitin_2006 | W1: Total Nr of Sales | X1: Product__Family | Y1: Due Date Performance/% | Z1: Total_Powder_Weight_kg
A2: ACT 1P | B2: Enviro can recycle - post | C2: Black | D2: 8 | E2: =D2*2.8 -> 22.4 | F2: 125 | G2: =F2-E2 -> 102.6 | H2: =(CleanedDataset!$F31-CleanedDataset!$E31)/CleanedDataset!$F31 -> 0.66666667 | I2: 45 | J2: =I2*F2-I2*E2 -> 4617 | K2: 50 | L2: =K2*F2-I2*E2 -> 5242 | M2: 80 | N2: =M2*F2-M2*E2 -> 8208 | O2: 50 | P2: =O2*F2-O2*E2 -> 5130 | Q2: 120 | R2: =Q2*F2-Q2*E2 -> 12312 | S2: 103 | T2: =S2*F2-S2*E2 -> 10567.8 | U2: 69 | V2: =U2*F2-U2*E2 -> 7079.4 | W2: =SUM(S2,Q2,O2,M2,K2,I2) -> 448 | X2: Bins | Y2: 100 | Z2: =D2*I2 -> 360
A3: AMB 1P | B3: Bear bin | C3: Black | D3: 45 | E3: =D3*2.8 -> 126 | F3: 300 | G3: =F3-E3 -> 174 | H3: =(CleanedDataset!$F20-CleanedDataset!$E20)/CleanedDataset!$F20 -> 0.7 | I3: 23 | J3: =I3*F3-I3*E3 -> 4002 | K3: 20 | L3: =K3*F3-I3*E3 -> 3102 | M3: 15 | N3: =M3*F3-M3*E3 -> 2610 | O3: 10 | P3: =O3*F3-O3*E3 -> 1740 | Q3: 13 | R3: =Q3*F3-Q3*E3 -> 2262 | S3: 20 | T3: =S3*F3-S3*E3 -> 3480 | U3: 15 | V3: =U3*F3-U3*E3 -> 2610 | W3: =SUM(S3,Q3,O3,M3,K3,I3) -> 101 | X3: Bins | Y3: 98 | Z3: =D3*I3 -> 1035
A4: AMP 1P | B4: Ample bin | C4: Black | D4: 20 | E4: =D4*2.8 -> 56 | F4: 150 | G4: =F4-E4 -> 94 | H4: =(CleanedDataset!$F47-CleanedDataset!$E47)/CleanedDataset!$F47 -> 0.64102564 | I4: 230 | J4: =I4*F4-I4*E4 -> 21620 | K4: 215 | L4: =K4*F4-I4*E4 -> 19370 | M4: 150 | N4: =M4*F4-M4*E4 -> 14100 | O4: 20 | P4: =O4*F4-O4*E4 -> 1880 | Q4: 80 | R4: =Q4*F4-Q4*E4 -> 7520 | S4: 40 | T4: =S4*F4-S4*E4 -> 3760 | U4: 50 | V4: =U4*F4-U4*E4 -> 4700 | W4: =SUM(S4,Q4,O4,M4,K4,I4) -> 735 | X4: Bins | Y4: 97 | Z4: =D4*I4 -> 4600
A5: BBU 0P | B5: Full barrier basket | C5: Cherry | D5: 7.5 | E5: =D5*3 -> 22.5 | F5: 70 | G5: =F5-E5 -> 47.5 | H5: =(CleanedDataset!$F73-CleanedDataset!$E73)/CleanedDataset!$F73 -> 0.82222222 | I5: 5 | J5: =I5*F5-I5*E5 -> 237.5 | K5: 0 | L5: =K5*F5-I5*E5 -> -112.5 | M5: 0 | N5: =M5*F5-M5*E5 -> 0 | O5: 0 | P5: =O5*F5-O5*E5 -> 0 | Q5: 0 | R5: =Q5*F5-Q5*E5 -> 0 | S5: 0 | T5: =S5*F5-S5*E5 -> 0 | U5: 0 | V5: =U5*F5-U5*E5 -> 0 | W5: =SUM(S5,Q5,O5,M5,K5,I5) -> 5 | X5: Self-Watering | Y5: 96 | Z5: =D5*I5 -> 37.5
A6: BBU 0P | B6: Full barrier basket | C6: Standard Green | D6: 7.5 | E6: =D6*3 -> 22.5 | F6: 70 | G6: =F6-E6 -> 47.5 | H6: =(CleanedDataset!$F159-CleanedDataset!$E159)/CleanedDataset!$F159 -> 0.25 | I6: 360 | J6: =I6*F6-I6*E6 -> 17100 | K6: 245 | L6: =K6*F6-I6*E6 -> 9050 | M6: 133 | N6: =M6*F6-M6*E6 -> 6317.5 | O6: 88 | P6: =O6*F6-O6*E6 -> 4180 | Q6: 10 | R6: =Q6*F6-Q6*E6 -> 475 | S6: 0 | T6: =S6*F6-S6*E6 -> 0 | U6: 0 | V6: =U6*F6-U6*E6 -> 0 | W6: =SUM(S6,Q6,O6,M6,K6,I6) -> 836 | X6: Self-Watering | Y6: 99 | Z6: =D6*I6 -> 2700
A7: BBU 0P | B7: Full barrier basket | C7: Black | D7: 7.5 | E7: =D7*2.8 -> 21 | F7: 58 | G7: =F7-E7 -> 37 | H7: =(CleanedDataset!$F41-CleanedDataset!$E41)/CleanedDataset!$F41 -> 0.56444444 | I7: 94 | J7: =I7*F7-I7*E7 -> 3478 | K7: 138 | L7: =K7*F7-I7*E7 -> 6030 | M7: 124 | N7: =M7*F7-M7*E7 -> 4588 | O7: 72 | P7: =O7*F7-O7*E7 -> 2664 | Q7: 10 | R7: =Q7*F7-Q7*E7 -> 370 | S7: 0 | T7: =S7*F7-S7*E7 -> 0 | U7: 0 | V7: =U7*F7-U7*E7 -> 0 | W7: =SUM(S7,Q7,O7,M7,K7,I7) -> 438 | X7: Self-Watering | Y7: 99 | Z7: =D7*I7 -> 705
A8: BBU 1P | B8: Barrier Basket | C8: Pink Granite | D8: 6 | E8: =D8*3.2 -> 19.2 | F8: 55 | G8: =F8-E8 -> 35.8 | H8: =(CleanedDataset!$F126-CleanedDataset!$E126)/CleanedDataset!$F126 -> 0.61891892 | I8: 530 | J8: =I8*F8-I8*E8 -> 18974 | K8: 135 | L8: =K8*F8-I8*E8 -> -2751 | M8: 0 | N8: =M8*F8-M8*E8 -> 0 | O8: 0 | P8: =O8*F8-O8*E8 -> 0 | Q8: 0 | R8: =Q8*F8-Q8*E8 -> 0 | S8: 0 | T8: =S8*F8-S8*E8 -> 0 | U8: 0 | V8: =U8*F8-U8*E8 -> 0 | W8: =SUM(S8,Q8,O8,M8,K8,I8) -> 665 | X8: Self-Watering | Y8: 90 | Z8: =D8*I8 -> 3180
A9: BBU 1P | B9: Barrier Basket | C9: Standard Green | D9: 6 | E9: =D9*3 -> 18 | F9: 50 | G9: =F9-E9 -> 32 | H9: =(CleanedDataset!$F162-CleanedDataset!$E162)/CleanedDataset!$F162 -> 0.83666667 | I9: 450 | J9: =I9*F9-I9*E9 -> 14400 | K9: 300 | L9: =K9*F9-I9*E9 -> 6900 | M9: 230 | N9: =M9*F9-M9*E9 -> 7360 | O9: 200 | P9: =O9*F9-O9*E9 -> 6400 | Q9: 225 | R9: =Q9*F9-Q9*E9 -> 7200 | S9: 705 | T9: =S9*F9-S9*E9 -> 22560 | U9: 680 | V9: =U9*F9-U9*E9 -> 21760 | W9: =SUM(S9,Q9,O9,M9,K9,I9) -> 2110 | X9: Self-Watering | Y9: 92 | Z9: =D9*I9 -> 2700
A10: BBU 1P | B10: Barrier Basket | C10: Black | D10: 6 | E10: =D10*2.8 -> 16.8 | F10: 40 | G10: =F10-E10 -> 23.2 | H10: =(CleanedDataset!$F53-CleanedDataset!$E53)/CleanedDataset!$F53 -> 0.7 | I10: 405 | J10: =I10*F10-I10*E10 -> 9396 | K10: 534 | L10: =K10*F10-I10*E10 -> 14556 | M10: 987 | N10: =M10*F10-M10*E10 -> 22898.4 | O10: 1917 | P10: =O10*F10-O10*E10 -> 44474.4 | Q10: 1047 | R10: =Q10*F10-Q10*E10 -> 24290.4 | S10: 326 | T10: =S10*F10-S10*E10 -> 7563.2 | U10: 857 | V10: =U10*F10-U10*E10 -> 19882.4 | W10: =SUM(S10,Q10,O10,M10,K10,I10) -> 5216 | X10: Self-Watering | Y10: 92 | Z10: =D10*I10 -> 2430
A11: BBU 1PL | B11: Barrier Basket Liner | C11: Standard Green | D11: 3.5 | E11: =D11*3 -> 10.5 | F11: 35 | G11: =F11-E11 -> 24.5 | H11: =(CleanedDataset!$F167-CleanedDataset!$E167)/CleanedDataset!$F167 -> 0.29292929 | I11: 1350 | J11: =I11*F11-I11*E11 -> 33075 | K11: 1200 | L11: =K11*F11-I11*E11 -> 27825 | M11: 567 | N11: =M11*F11-M11*E11 -> 13891.5 | O11: 200 | P11: =O11*F11-O11*E11 -> 4900 | Q11: 540 | R11: =Q11*F11-Q11*E11 -> 13230 | S11: 1250 | T11: =S11*F11-S11*E11 -> 30625 | U11: 890 | V11: =U11*F11-U11*E11 -> 21805 | W11: =SUM(S11,Q11,O11,M11,K11,I11) -> 5107 | X11: Self-Watering | Y11: 91 | Z11: =D11*I11 -> 4725
A12: BBU 1PL | B12: Barrier Basket Liner | C12: Black | D12: 3.5 | E12: =D12*2.8 -> 9.8 | F12: 25 | G12: =F12-E12 -> 15.2 | H12: =(CleanedDataset!$F56-CleanedDataset!$E56)/CleanedDataset!$F56 -> 0.68802228 | I12: 604 | J12: =I12*F12-I12*E12 -> 9180.8 | K12: 339 | L12: =K12*F12-I12*E12 -> 2555.8 | M12: 853 | N12: =M12*F12-M12*E12 -> 12965.6 | O12: 2331 | P12: =O12*F12-O12*E12 -> 35431.2 | Q12: 1049 | R12: =Q12*F12-Q12*E12 -> 15944.8 | S12: 326 | T12: =S12*F12-S12*E12 -> 4955.2 | U12: 708 | V12: =U12*F12-U12*E12 -> 10761.6 | W12: =SUM(S12,Q12,O12,M12,K12,I12) -> 5502 | X12: Self-Watering | Y12: 99 | Z12: =D12*I12 -> 2114
A13: BHV 5P | B13: Bee hive fountain (5) | C13: Guerney Granite | D13: 55 | E13: =D13*3.2 -> 176 | F13: 615 | G13: =F13-E13 -> 439 | H13: =(CleanedDataset!$F82-CleanedDataset!$E82)/CleanedDataset!$F82 -> 0.58588235 | I13: 57 | J13: =I13*F13-I13*E13 -> 25023 | K13: 35 | L13: =K13*F13-I13*E13 -> 11493 | M13: 0 | N13: =M13*F13-M13*E13 -> 0 | O13: 0 | P13: =O13*F13-O13*E13 -> 0 | Q13: 0 | R13: =Q13*F13-Q13*E13 -> 0 | S13: 0 | T13: =S13*F13-S13*E13 -> 0 | U13: 0 | V13: =U13*F13-U13*E13 -> 0 | W13: =SUM(S13,Q13,O13,M13,K13,I13) -> 92 | X13: Self-Watering | Y13: 93 | Z13: =D13*I13 -> 3135
A14: BHV 5P | B14: Bee hive fountain (5) | C14: Pink Granite | D14: 55 | E14: =D14*3.2 -> 176 | F14: 600 | G14: =F14-E14 -> 424 | H14: =(CleanedDataset!$F117-CleanedDataset!$E117)/CleanedDataset!$F117 -> 0.57333333 | I14: 35 | J14: =I14*F14-I14*E14 -> 14840 | K14: 14 | L14: =K14*F14-I14*E14 -> 2240 | M14: 0 | N14: =M14*F14-M14*E14 -> 0 | O14: 0 | P14: =O14*F14-O14*E14 -> 0 | Q14: 0 | R14: =Q14*F14-Q14*E14 -> 0 | S14: 0 | T14: =S14*F14-S14*E14 -> 0 | U14: 0 | V14: =U14*F14-U14*E14 -> 0 | W14: =SUM(S14,Q14,O14,M14,K14,I14) -> 49 | X14: Self-Watering | Y14: 90 | Z14: =D14*I14 -> 1925
A15: BHV 5P | B15: Bee hive fountain (5) | C15: Standard Green | D15: 55 | E15: =D15*3 -> 165 | F15: 600 | G15: =F15-E15 -> 435 | H15: =(CleanedDataset!$F148-CleanedDataset!$E148)/CleanedDataset!$F148 -> 0.59351351 | I15: 66 | J15: =I15*F15-I15*E15 -> 28710 | K15: 35 | L15: =K15*F15-I15*E15 -> 10110 | M15: 12 | N15: =M15*F15-M15*E15 -> 5220 | O15: 15 | P15: =O15*F15-O15*E15 -> 6525 | Q15: 33 | R15: =Q15*F15-Q15*E15 -> 14355 | S15: 50 | T15: =S15*F15-S15*E15 -> 21750 | U15: 45 | V15: =U15*F15-U15*E15 -> 19575 | W15: =SUM(S15,Q15,O15,M15,K15,I15) -> 211 | X15: Self-Watering | Y15: 94 | Z15: =D15*I15 -> 3630
A16: BHV 5P | B16: Bee hive fountain (5) | C16: Black | D16: 55 | E16: =D16*2.8 -> 154 | F16: 530 | G16: =F16-E16 -> 376 | H16: =(CleanedDataset!$F33-CleanedDataset!$E33)/CleanedDataset!$F33 -> 0.6 | I16: 58 | J16: =I16*F16-I16*E16 -> 21808 | K16: 75 | L16: =K16*F16-I16*E16 -> 30818 | M16: 39 | N16: =M16*F16-M16*E16 -> 14664 | O16: 16 | P16: =O16*F16-O16*E16 -> 6016 | Q16: 21 | R16: =Q16*F16-Q16*E16 -> 7896 | S16: 60 | T16: =S16*F16-S16*E16 -> 22560 | U16: 64 | V16: =U16*F16-U16*E16 -> 24064 | W16: =SUM(S16,Q16,O16,M16,K16,I16) -> 269 | X16: Self-Watering | Y16: 100 | Z16: =D16*I16 -> 3190
A17: BHV 6P | B17: Bee hive fountain (6) | C17: Guerney Granite | D17: 65 | E17: =D17*3.2 -> 208 | F17: 700 | G17: =F17-E17 -> 492 | H17: =(CleanedDataset!$F78-CleanedDataset!$E78)/CleanedDataset!$F78 -> -0.275 | I17: 5 | J17: =I17*F17-I17*E17 -> 2460 | K17: 0 | L17: =K17*F17-I17*E17 -> -1040 | M17: 0 | N17: =M17*F17-M17*E17 -> 0 | O17: 0 | P17: =O17*F17-O17*E17 -> 0 | Q17: 0 | R17: =Q17*F17-Q17*E17 -> 0 | S17: 0 | T17: =S17*F17-S17*E17 -> 0 | U17: 0 | V17: =U17*F17-U17*E17 -> 0 | W17: =SUM(S17,Q17,O17,M17,K17,I17) -> 5 | X17: Self-Watering | Y17: 99 | Z17: =D17*I17 -> 325
A18: BHV 6P | B18: Bee hive fountain (6) | C18: Moss Stone | D18: 65 | E18: =D18*3.2 -> 208 | F18: 700 | G18: =F18-E18 -> 492 | H18: =(CleanedDataset!$F99-CleanedDataset!$E99)/CleanedDataset!$F99 -> 0.0625 | I18: 0 | J18: =I18*F18-I18*E18 -> 0 | K18: 5 | L18: =K18*F18-I18*E18 -> 3500 | M18: 0 | N18: =M18*F18-M18*E18 -> 0 | O18: 0 | P18: =O18*F18-O18*E18 -> 0 | Q18: 0 | R18: =Q18*F18-Q18*E18 -> 0 | S18: 0 | T18: =S18*F18-S18*E18 -> 0 | U18: 0 | V18: =U18*F18-U18*E18 -> 0 | W18: =SUM(S18,Q18,O18,M18,K18,I18) -> 5 | X18: Self-Watering | Y18: 98 | Z18: =D18*I18 -> 0
A19: BHV 6P | B19: Bee hive fountain (6) | C19: Pink Granite | D19: 65 | E19: =D19*3.2 -> 208 | F19: 700 | G19: =F19-E19 -> 492 | H19: =(CleanedDataset!$F122-CleanedDataset!$E122)/CleanedDataset!$F122 -> 0.49090909 | I19: 53 | J19: =I19*F19-I19*E19 -> 26076 | K19: 28 | L19: =K19*F19-I19*E19 -> 8576 | M19: 0 | N19: =M19*F19-M19*E19 -> 0 | O19: 0 | P19: =O19*F19-O19*E19 -> 0 | Q19: 0 | R19: =Q19*F19-Q19*E19 -> 0 | S19: 0 | T19: =S19*F19-S19*E19 -> 0 | U19: 0 | V19: =U19*F19-U19*E19 -> 0 | W19: =SUM(S19,Q19,O19,M19,K19,I19) -> 81 | X19: Self-Watering | Y19: 93 | Z19: =D19*I19 -> 3445
A20: BHV 6P | B20: Bee hive fountain (6) | C20: Light Green | D20: 65 | E20: =D20*3 -> 195 | F20: 650 | G20: =F20-E20 -> 455 | H20: =(CleanedDataset!$F84-CleanedDataset!$E84)/CleanedDataset!$F84 -> 0.25 | I20: 3 | J20: =I20*F20-I20*E20 -> 1365 | K20: 0 | L20: =K20*F20-I20*E20 -> -585 | M20: 0 | N20: =M20*F20-M20*E20 -> 0 | O20: 0 | P20: =O20*F20-O20*E20 -> 0 | Q20: 0 | R20: =Q20*F20-Q20*E20 -> 0 | S20: 0 | T20: =S20*F20-S20*E20 -> 0 | U20: 0 | V20: =U20*F20-U20*E20 -> 0 | W20: =SUM(S20,Q20,O20,M20,K20,I20) -> 3 | X20: Self-Watering | Y20: 98 | Z20: =D20*I20 -> 195
A21: BHV 6P | B21: Bee hive fountain (6) | C21: Standard Green | D21: 65 | E21: =D21*3 -> 195 | F21: 650 | G21: =F21-E21 -> 455 | H21: =(CleanedDataset!$F152-CleanedDataset!$E152)/CleanedDataset!$F152 -> 0.648 | I21: 158 | J21: =I21*F21-I21*E21 -> 71890 | K21: 113 | L21: =K21*F21-I21*E21 -> 42640 | M21: 250 | N21: =M21*F21-M21*E21 -> 113750 | O21: 0 | P21: =O21*F21-O21*E21 -> 0 | Q21: 0 | R21: =Q21*F21-Q21*E21 -> 0 | S21: 0 | T21: =S21*F21-S21*E21 -> 0 | U21: 0 | V21: =U21*F21-U21*E21 -> 0 | W21: =SUM(S21,Q21,O21,M21,K21,I21) -> 521 | X21: Self-Watering | Y21: 97 | Z21: =D21*I21 -> 10270
A22: BHV 6P | B22: Bee hive fountain (6) | C22: Black | D22: 65 | E22: =D22*2.8 -> 182 | F22: 584 | G22: =F22-E22 -> 402 | H22: =(CleanedDataset!$F32-CleanedDataset!$E32)/CleanedDataset!$F32 -> 0.66666667 | I22: 51 | J22: =I22*F22-I22*E22 -> 20502 | K22: 78 | L22: =K22*F22-I22*E22 -> 36270 | M22: 193 | N22: =M22*F22-M22*E22 -> 77586 | O22: 0 | P22: =O22*F22-O22*E22 -> 0 | Q22: 0 | R22: =Q22*F22-Q22*E22 -> 0 | S22: 0 | T22: =S22*F22-S22*E22 -> 0 | U22: 0 | V22: =U22*F22-U22*E22 -> 0 | W22: =SUM(S22,Q22,O22,M22,K22,I22) -> 322 | X22: Self-Watering | Y22: 94 | Z22: =D22*I22 -> 3315
A23: BRL 0P | B23: Barrel | C23: Brown | D23: 15 | E23: =D23*3 -> 45 | F23: 75 | G23: =F23-E23 -> 30 | H23: =(CleanedDataset!$F62-CleanedDataset!$E62)/CleanedDataset!$F62 -> 0.72 | I23: 496 | J23: =I23*F23-I23*E23 -> 14880 | K23: 557 | L23: =K23*F23-I23*E23 -> 19455 | M23: 0 | N23: =M23*F23-M23*E23 -> 0 | O23: 0 | P23: =O23*F23-O23*E23 -> 0 | Q23: 0 | R23: =Q23*F23-Q23*E23 -> 0 | S23: 0 | T23: =S23*F23-S23*E23 -> 0 | U23: 0 | V23: =U23*F23-U23*E23 -> 0 | W23: =SUM(S23,Q23,O23,M23,K23,I23) -> 1053 | X23: Self-Watering | Y23: 91 | Z23: =D23*I23 -> 7440
A24: CAS 0P | B24: Cup and Saucer | C24: Orange | D24: 7 | E24: =D24*3 -> 21 | F24: 40 | G24: =F24-E24 -> 19 | H24: =(CleanedDataset!$F102-CleanedDataset!$E102)/CleanedDataset!$F102 -> 0.5890411 | I24: 6 | J24: =I24*F24-I24*E24 -> 114 | K24: 15 | L24: =K24*F24-I24*E24 -> 474 | M24: 0 | N24: =M24*F24-M24*E24 -> 0 | O24: 0 | P24: =O24*F24-O24*E24 -> 0 | Q24: 0 | R24: =Q24*F24-Q24*E24 -> 0 | S24: 0 | T24: =S24*F24-S24*E24 -> 0 | U24: 0 | V24: =U24*F24-U24*E24 -> 0 | W24: =SUM(S24,Q24,O24,M24,K24,I24) -> 21 | X24: Self-Watering | Y24: 94 | Z24: =D24*I24 -> 42
A25: CAS 0P | B25: Cup and Saucer | C25: Sky Blue | D25: 7 | E25: =D25*3 -> 21 | F25: 40 | G25: =F25-E25 -> 19 | H25: =(CleanedDataset!$F133-CleanedDataset!$E133)/CleanedDataset!$F133 -> 0.70461538 | I25: 135 | J25: =I25*F25-I25*E25 -> 2565 | K25: 46 | L25: =K25*F25-I25*E25 -> -995 | M25: 0 | N25: =M25*F25-M25*E25 -> 0 | O25: 0 | P25: =O25*F25-O25*E25 -> 0 | Q25: 0 | R25: =Q25*F25-Q25*E25 -> 0 | S25: 0 | T25: =S25*F25-S25*E25 -> 0 | U25: 0 | V25: =U25*F25-U25*E25 -> 0 | W25: =SUM(S25,Q25,O25,M25,K25,I25) -> 181 | X25: Self-Watering | Y25: 95 | Z25: =D25*I25 -> 945
A26: CAS 0P | B26: Cup and Saucer | C26: Standard Green | D26: 7 | E26: =D26*3 -> 21 | F26: 40 | G26: =F26-E26 -> 19 | H26: =(CleanedDataset!$F166-CleanedDataset!$E166)/CleanedDataset!$F166 -> 0.87076923 | I26: 1300 | J26: =I26*F26-I26*E26 -> 24700 | K26: 1250 | L26: =K26*F26-I26*E26 -> 22700 | M26: 800 | N26: =M26*F26-M26*E26 -> 15200 | O26: 750 | P26: =O26*F26-O26*E26 -> 14250 | Q26: 1200 | R26: =Q26*F26-Q26*E26 -> 22800 | S26: 2050 | T26: =S26*F26-S26*E26 -> 38950 | U26: 1980 | V26: =U26*F26-U26*E26 -> 37620 | W26: =SUM(S26,Q26,O26,M26,K26,I26) -> 7350 | X26: Self-Watering | Y26: 97 | Z26: =D26*I26 -> 9100
A27: CAS 0P | B27: Cup and Saucer | C27: Black | D27: 7 | E27: =D27*2.8 -> 19.6 | F27: 30 | G27: =F27-E27 -> 10.4 | H27: =(CleanedDataset!$F61-CleanedDataset!$E61)/CleanedDataset!$F61 -> 0.76666667 | I27: 2132 | J27: =I27*F27-I27*E27 -> 22172.8 | K27: 2648 | L27: =K27*F27-I27*E27 -> 37652.8 | M27: 2712 | N27: =M27*F27-M27*E27 -> 28204.8 | O27: 1775 | P27: =O27*F27-O27*E27 -> 18460 | Q27: 2302 | R27: =Q27*F27-Q27*E27 -> 23940.8 | S27: 2250 | T27: =S27*F27-S27*E27 -> 23400 | U27: 2532 | V27: =U27*F27-U27*E27 -> 26332.8 | W27: =SUM(S27,Q27,O27,M27,K27,I27) -> 13819 | X27: Self-Watering | Y27: 91 | Z27: =D27*I27 -> 14924
A28: CAS 1P | B28: Cup and Saucer (HB) | C28: Light Sandstone | D28: 5 | E28: =D28*3.2 -> 16 | F28: 60 | G28: =F28-E28 -> 44 | H28: =(CleanedDataset!$F97-CleanedDataset!$E97)/CleanedDataset!$F97 -> 0.45 | I28: 23 | J28: =I28*F28-I28*E28 -> 1012 | K28: 35 | L28: =K28*F28-I28*E28 -> 1732 | M28: 0 | N28: =M28*F28-M28*E28 -> 0 | O28: 0 | P28: =O28*F28-O28*E28 -> 0 | Q28: 0 | R28: =Q28*F28-Q28*E28 -> 0 | S28: 0 | T28: =S28*F28-S28*E28 -> 0 | U28: 0 | V28: =U28*F28-U28*E28 -> 0 | W28: =SUM(S28,Q28,O28,M28,K28,I28) -> 58 | X28: Self-Watering | Y28: 95 | Z28: =D28*I28 -> 115
A29: CAS 1P | B29: Cup and Saucer (HB) | C29: Standard Green | D29: 5 | E29: =D29*3 -> 15 | F29: 50 | G29: =F29-E29 -> 35 | H29: =(CleanedDataset!$F164-CleanedDataset!$E164)/CleanedDataset!$F164 -> 0.664 | I29: 860 | J29: =I29*F29-I29*E29 -> 30100 | K29: 744 | L29: =K29*F29-I29*E29 -> 24300 | M29: 343 | N29: =M29*F29-M29*E29 -> 12005 | O29: 320 | P29: =O29*F29-O29*E29 -> 11200 | Q29: 287 | R29: =Q29*F29-Q29*E29 -> 10045 | S29: 680 | T29: =S29*F29-S29*E29 -> 23800 | U29: 623 | V29: =U29*F29-U29*E29 -> 21805 | W29: =SUM(S29,Q29,O29,M29,K29,I29) -> 3234 | X29: Self-Watering | Y29: 96 | Z29: =D29*I29 -> 4300
A30: CAS 1P | B30: Cup and Saucer (HB) | C30: Black | D30: 5 | E30: =D30*2.8 -> 14 | F30: 45 | G30: =F30-E30 -> 31 | H30: =(CleanedDataset!$F58-CleanedDataset!$E58)/CleanedDataset!$F58 -> 0.68 | I30: 787 | J30: =I30*F30-I30*E30 -> 24397 | K30: 478 | L30: =K30*F30-I30*E30 -> 10492 | M30: 1235 | N30: =M30*F30-M30*E30 -> 38285 | O30: 1450 | P30: =O30*F30-O30*E30 -> 44950 | Q30: 1728 | R30: =Q30*F30-Q30*E30 -> 53568 | S30: 1182 | T30: =S30*F30-S30*E30 -> 36642 | U30: 999 | V30: =U30*F30-U30*E30 -> 30969 | W30: =SUM(S30,Q30,O30,M30,K30,I30) -> 6860 | X30: Self-Watering | Y30: 97 | Z30: =D30*I30 -> 3935
A31: CHB 1P | B31: Conventional Hanging Basket | C31: Cherry | D31: 5 | E31: =D31*3 -> 15 | F31: 45 | G31: =F31-E31 -> 30 | H31: =(CleanedDataset!$F75-CleanedDataset!$E75)/CleanedDataset!$F75 -> 0.79466667 | I31: 28 | J31: =I31*F31-I31*E31 -> 840 | K31: 5 | L31: =K31*F31-I31*E31 -> -195 | M31: 0 | N31: =M31*F31-M31*E31 -> 0 | O31: 0 | P31: =O31*F31-O31*E31 -> 0 | Q31: 0 | R31: =Q31*F31-Q31*E31 -> 0 | S31: 0 | T31: =S31*F31-S31*E31 -> 0 | U31: 0 | V31: =U31*F31-U31*E31 -> 0 | W31: =SUM(S31,Q31,O31,M31,K31,I31) -> 33 | X31: Self-Watering | Y31: 90 | Z31: =D31*I31 -> 140
A32: CHB 1P | B32: Conventional Hanging Basket | C32: Standard Green | D32: 5 | E32: =D32*3 -> 15 | F32: 45 | G32: =F32-E32 -> 30 | H32: =(CleanedDataset!$F158-CleanedDataset!$E158)/CleanedDataset!$F158 -> 0.2 | I32: 342 | J32: =I32*F32-I32*E32 -> 10260 | K32: 280 | L32: =K32*F32-I32*E32 -> 7470 | M32: 133 | N32: =M32*F32-M32*E32 -> 3990 | O32: 200 | P32: =O32*F32-O32*E32 -> 6000 | Q32: 187 | R32: =Q32*F32-Q32*E32 -> 5610 | S32: 850 | T32: =S32*F32-S32*E32 -> 25500 | U32: 345 | V32: =U32*F32-U32*E32 -> 10350 | W32: =SUM(S32,Q32,O32,M32,K32,I32) -> 1992 | X32: Self-Watering | Y32: 94 | Z32: =D32*I32 -> 1710
A33: CHB 1P | B33: Conventional Hanging Basket | C33: Black | D33: 5 | E33: =D33*2.8 -> 14 | F33: 35 | G33: =F33-E33 -> 21 | H33: =(CleanedDataset!$F55-CleanedDataset!$E55)/CleanedDataset!$F55 -> 0.67919799 | I33: 527 | J33: =I33*F33-I33*E33 -> 11067 | K33: 203 | L33: =K33*F33-I33*E33 -> -273 | M33: 395 | N33: =M33*F33-M33*E33 -> 8295 | O33: 499 | P33: =O33*F33-O33*E33 -> 10479 | Q33: 915 | R33: =Q33*F33-Q33*E33 -> 19215 | S33: 230 | T33: =S33*F33-S33*E33 -> 4830 | U33: 532 | V33: =U33*F33-U33*E33 -> 11172 | W33: =SUM(S33,Q33,O33,M33,K33,I33) -> 2769 | X33: Self-Watering | Y33: 91 | Z33: =D33*I33 -> 2635
A34: CHB 2P | B34: Conventional Hanging Basket | C34: Cherry | D34: 5 | E34: =D34*3 -> 15 | F34: 66 | G34: =F34-E34 -> 51 | H34: =(CleanedDataset!$F65-CleanedDataset!$E65)/CleanedDataset!$F65 -> 0.77846154 | I34: 0 | J34: =I34*F34-I34*E34 -> 0 | K34: 5 | L34: =K34*F34-I34*E34 -> 330 | M34: 0 | N34: =M34*F34-M34*E34 -> 0 | O34: 0 | P34: =O34*F34-O34*E34 -> 0 | Q34: 0 | R34: =Q34*F34-Q34*E34 -> 0 | S34: 0 | T34: =S34*F34-S34*E34 -> 0 | U34: 0 | V34: =U34*F34-U34*E34 -> 0 | W34: =SUM(S34,Q34,O34,M34,K34,I34) -> 5 | X34: Self-Watering | Y34: 91 | Z34: =D34*I34 -> 0
A35: CHB 2P | B35: Conventional Hanging Basket | C35: Orange | D35: 5 | E35: =D35*3 -> 15 | F35: 66 | G35: =F35-E35 -> 51 | H35: =(CleanedDataset!$F101-CleanedDataset!$E101)/CleanedDataset!$F101 -> 0.1 | I35: 1 | J35: =I35*F35-I35*E35 -> 51 | K35: 0 | L35: =K35*F35-I35*E35 -> -15 | M35: 0 | N35: =M35*F35-M35*E35 -> 0 | O35: 0 | P35: =O35*F35-O35*E35 -> 0 | Q35: 0 | R35: =Q35*F35-Q35*E35 -> 0 | S35: 0 | T35: =S35*F35-S35*E35 -> 0 | U35: 0 | V35: =U35*F35-U35*E35 -> 0 | W35: =SUM(S35,Q35,O35,M35,K35,I35) -> 1 | X35: Self-Watering | Y35: 98 | Z35: =D35*I35 -> 5
A36: CHB 2P | B36: Conventional Hanging Basket | C36: Standard Green | D36: 5 | E36: =D36*3 -> 15 | F36: 66 | G36: =F36-E36 -> 51 | H36: =(CleanedDataset!$F150-CleanedDataset!$E150)/CleanedDataset!$F150 -> 0.58222222 | I36: 87 | J36: =I36*F36-I36*E36 -> 4437 | K36: 65 | L36: =K36*F36-I36*E36 -> 2985 | M36: 50 | N36: =M36*F36-M36*E36 -> 2550 | O36: 67 | P36: =O36*F36-O36*E36 -> 3417 | Q36: 50 | R36: =Q36*F36-Q36*E36 -> 2550 | S36: 35 | T36: =S36*F36-S36*E36 -> 1785 | U36: 55 | V36: =U36*F36-U36*E36 -> 2805 | W36: =SUM(S36,Q36,O36,M36,K36,I36) -> 354 | X36: Self-Watering | Y36: 91 | Z36: =D36*I36 -> 435
A37: CHB 2P | B37: Conventional Hanging Basket | C37: Black | D37: 5 | E37: =D37*2.8 -> 14 | F37: 56 | G37: =F37-E37 -> 42 | H37: =(CleanedDataset!$F35-CleanedDataset!$E35)/CleanedDataset!$F35 -> 0.77272727 | I37: 61 | J37: =I37*F37-I37*E37 -> 2562 | K37: 97 | L37: =K37*F37-I37*E37 -> 4578 | M37: 29 | N37: =M37*F37-M37*E37 -> 1218 | O37: 91 | P37: =O37*F37-O37*E37 -> 3822 | Q37: 62 | R37: =Q37*F37-Q37*E37 -> 2604 | S37: 419 | T37: =S37*F37-S37*E37 -> 17598 | U37: 37 | V37: =U37*F37-U37*E37 -> 1554 | W37: =SUM(S37,Q37,O37,M37,K37,I37) -> 759 | X37: Self-Watering | Y37: 96 | Z37: =D37*I37 -> 305
A38: CHK 1P | B38: Chick bin | C38: Black | D38: 30 | E38: =D38*2.8 -> 84 | F38: 250 | G38: =F38-E38 -> 166 | H38: =(CleanedDataset!$F17-CleanedDataset!$E17)/CleanedDataset!$F17 -> 0.70285714 | I38: 15 | J38: =I38*F38-I38*E38 -> 2490 | K38: 17 | L38: =K38*F38-I38*E38 -> 2990 | M38: 15 | N38: =M38*F38-M38*E38 -> 2490 | O38: 20 | P38: =O38*F38-O38*E38 -> 3320 | Q38: 35 | R38: =Q38*F38-Q38*E38 -> 5810 | S38: 24 | T38: =S38*F38-S38*E38 -> 3984 | U38: 15 | V38: =U38*F38-U38*E38 -> 2490 | W38: =SUM(S38,Q38,O38,M38,K38,I38) -> 126 | X38: Bins | Y38: 90 | Z38: =D38*I38 -> 450
A39: CNS 1P | B39: Cup and Saucer on pole | C39: Light Green | D39: 7 | E39: =D39*3 -> 21 | F39: 55 | G39: =F39-E39 -> 34 | H39: =(CleanedDataset!$F87-CleanedDataset!$E87)/CleanedDataset!$F87 -> 0.49152542 | I39: 23 | J39: =I39*F39-I39*E39 -> 782 | K39: 15 | L39: =K39*F39-I39*E39 -> 342 | M39: 0 | N39: =M39*F39-M39*E39 -> 0 | O39: 0 | P39: =O39*F39-O39*E39 -> 0 | Q39: 0 | R39: =Q39*F39-Q39*E39 -> 0 | S39: 0 | T39: =S39*F39-S39*E39 -> 0 | U39: 0 | V39: =U39*F39-U39*E39 -> 0 | W39: =SUM(S39,Q39,O39,M39,K39,I39) -> 38 | X39: Self-Watering | Y39: 90 | Z39: =D39*I39 -> 161
A40: CNS 1P | B40: Cup and Saucer on pole | C40: Standard Green | D40: 7 | E40: =D40*3 -> 21 | F40: 55 | G40: =F40-E40 -> 34 | H40: =(CleanedDataset!$F169-CleanedDataset!$E169)/CleanedDataset!$F169 -> 0.49090909 | I40: 1578 | J40: =I40*F40-I40*E40 -> 53652 | K40: 1450 | L40: =K40*F40-I40*E40 -> 46612 | M40: 1135 | N40: =M40*F40-M40*E40 -> 38590 | O40: 957 | P40: =O40*F40-O40*E40 -> 32538 | Q40: 2300 | R40: =Q40*F40-Q40*E40 -> 78200 | S40: 2780 | T40: =S40*F40-S40*E40 -> 94520 | U40: 2800 | V40: =U40*F40-U40*E40 -> 95200 | W40: =SUM(S40,Q40,O40,M40,K40,I40) -> 10200 | X40: Self-Watering | Y40: 95 | Z40: =D40*I40 -> 11046
A41: CNS 1P | B41: Cup and Saucer on pole | C41: Black | D41: 7 | E41: =D41*2.8 -> 19.6 | F41: 45 | G41: =F41-E41 -> 25.4 | H41: =(CleanedDataset!$F60-CleanedDataset!$E60)/CleanedDataset!$F60 -> 0.81333333 | I41: 1064 | J41: =I41*F41-I41*E41 -> 27025.6 | K41: 1153 | L41: =K41*F41-I41*E41 -> 31030.6 | M41: 1979 | N41: =M41*F41-M41*E41 -> 50266.6 | O41: 2901 | P41: =O41*F41-O41*E41 -> 73685.4 | Q41: 2434 | R41: =Q41*F41-Q41*E41 -> 61823.6 | S41: 1693 | T41: =S41*F41-S41*E41 -> 43002.2 | U41: 1311 | V41: =U41*F41-U41*E41 -> 33299.4 | W41: =SUM(S41,Q41,O41,M41,K41,I41) -> 11224 | X41: Self-Watering | Y41: 94 | Z41: =D41*I41 -> 7448
A42: CNS 1PL | B42: half cup and saucer up the pole | C42: Black | D42: 5 | E42: =D42*2.8 -> 14 | F42: 85 | G42: =F42-E42 -> 71 | H42: =(CleanedDataset!$F48-CleanedDataset!$E48)/CleanedDataset!$F48 -> 0.75111111 | I42: 268 | J42: =I42*F42-I42*E42 -> 19028 | K42: 253 | L42: =K42*F42-I42*E42 -> 17753 | M42: 178 | N42: =M42*F42-M42*E42 -> 12638 | O42: 360 | P42: =O42*F42-O42*E42 -> 25560 | Q42: 816 | R42: =Q42*F42-Q42*E42 -> 57936 | S42: 410 | T42: =S42*F42-S42*E42 -> 29110 | U42: 301 | V42: =U42*F42-U42*E42 -> 21371 | W42: =SUM(S42,Q42,O42,M42,K42,I42) -> 2285 | X42: Self-Watering | Y42: 93 | Z42: =D42*I42 -> 1340
A43: CNS 1PL | B43: half cup and saucer up the pole | C43: Standard Green | D43: 5 | E43: =D43*3 -> 15 | F43: 85 | G43: =F43-E43 -> 70 | H43: =(CleanedDataset!$F153-CleanedDataset!$E153)/CleanedDataset!$F153 -> 0.64893617 | I43: 180 | J43: =I43*F43-I43*E43 -> 12600 | K43: 0 | L43: =K43*F43-I43*E43 -> -2700 | M43: 0 | N43: =M43*F43-M43*E43 -> 0 | O43: 0 | P43: =O43*F43-O43*E43 -> 0 | Q43: 0 | R43: =Q43*F43-Q43*E43 -> 0 | S43: 0 | T43: =S43*F43-S43*E43 -> 0 | U43: 0 | V43: =U43*F43-U43*E43 -> 0 | W43: =SUM(S43,Q43,O43,M43,K43,I43) -> 180 | X43: Self-Watering | Y43: 98 | Z43: =D43*I43 -> 900
A44: CUH 1P | B44: up the pole basket | C44: Cherry | D44: 5 | E44: =D44*3 -> 15 | F44: 49 | G44: =F44-E44 -> 34 | H44: =(CleanedDataset!$F69-CleanedDataset!$E69)/CleanedDataset!$F69 -> 0.77931034 | I44: 1 | J44: =I44*F44-I44*E44 -> 34 | K44: 0 | L44: =K44*F44-I44*E44 -> -15 | M44: 0 | N44: =M44*F44-M44*E44 -> 0 | O44: 0 | P44: =O44*F44-O44*E44 -> 0 | Q44: 0 | R44: =Q44*F44-Q44*E44 -> 0 | S44: 0 | T44: =S44*F44-S44*E44 -> 0 | U44: 0 | V44: =U44*F44-U44*E44 -> 0 | W44: =SUM(S44,Q44,O44,M44,K44,I44) -> 1 | X44: Self-Watering | Y44: 100 | Z44: =D44*I44 -> 5
A45: CUH 1P | B45: up the pole basket | C45: Sky Blue | D45: 5 | E45: =D45*3 -> 15 | F45: 49 | G45: =F45-E45 -> 34 | H45: =(CleanedDataset!$F128-CleanedDataset!$E128)/CleanedDataset!$F128 -> 0.65490196 | I45: 1 | J45: =I45*F45-I45*E45 -> 34 | K45: 0 | L45: =K45*F45-I45*E45 -> -15 | M45: 0 | N45: =M45*F45-M45*E45 -> 0 | O45: 0 | P45: =O45*F45-O45*E45 -> 0 | Q45: 0 | R45: =Q45*F45-Q45*E45 -> 0 | S45: 0 | T45: =S45*F45-S45*E45 -> 0 | U45: 0 | V45: =U45*F45-U45*E45 -> 0 | W45: =SUM(S45,Q45,O45,M45,K45,I45) -> 1 | X45: Self-Watering | Y45: 95 | Z45: =D45*I45 -> 5
A46: CUH 1P | B46: up the pole basket | C46: Standard Green | D46: 5 | E46: =D46*3 -> 15 | F46: 49 | G46: =F46-E46 -> 34 | H46: =(CleanedDataset!$F149-CleanedDataset!$E149)/CleanedDataset!$F149 -> 0.58529412 | I46: 68 | J46: =I46*F46-I46*E46 -> 2312 | K46: 55 | L46: =K46*F46-I46*E46 -> 1675 | M46: 20 | N46: =M46*F46-M46*E46 -> 680 | O46: 25 | P46: =O46*F46-O46*E46 -> 850 | Q46: 30 | R46: =Q46*F46-Q46*E46 -> 1020 | S46: 44 | T46: =S46*F46-S46*E46 -> 1496 | U46: 10 | V46: =U46*F46-U46*E46 -> 340 | W46: =SUM(S46,Q46,O46,M46,K46,I46) -> 242 | X46: Self-Watering | Y46: 93 | Z46: =D46*I46 -> 340
A47: CUH 1P | B47: up the pole basket | C47: Black | D47: 5 | E47: =D47*2.8 -> 14 | F47: 39 | G47: =F47-E47 -> 25 | H47: =(CleanedDataset!$F25-CleanedDataset!$E25)/CleanedDataset!$F25 -> 0.475 | I47: 36 | J47: =I47*F47-I47*E47 -> 900 | K47: 49 | L47: =K47*F47-I47*E47 -> 1407 | M47: 38 | N47: =M47*F47-M47*E47 -> 950 | O47: 69 | P47: =O47*F47-O47*E47 -> 1725 | Q47: 39 | R47: =Q47*F47-Q47*E47 -> 975 | S47: 46 | T47: =S47*F47-S47*E47 -> 1150 | U47: 8 | V47: =U47*F47-U47*E47 -> 200 | W47: =SUM(S47,Q47,O47,M47,K47,I47) -> 277 | X47: Self-Watering | Y47: 94 | Z47: =D47*I47 -> 180
A48: CUH 2P | B48: Up the pole basket | C48: Pink Granite | D48: 7 | E48: =D48*3.2 -> 22.4 | F48: 90 | G48: =F48-E48 -> 67.6 | H48: =(CleanedDataset!$F115-CleanedDataset!$E115)/CleanedDataset!$F115 -> 0.37777778 | I48: 25 | J48: =I48*F48-I48*E48 -> 1690 | K48: 0 | L48: =K48*F48-I48*E48 -> -560 | M48: 0 | N48: =M48*F48-M48*E48 -> 0 | O48: 0 | P48: =O48*F48-O48*E48 -> 0 | Q48: 0 | R48: =Q48*F48-Q48*E48 -> 0 | S48: 0 | T48: =S48*F48-S48*E48 -> 0 | U48: 0 | V48: =U48*F48-U48*E48 -> 0 | W48: =SUM(S48,Q48,O48,M48,K48,I48) -> 25 | X48: Self-Watering | Y48: 92 | Z48: =D48*I48 -> 175
A49: CUH 2P | B49: Up the pole basket | C49: Cherry | D49: 7 | E49: =D49*3 -> 21 | F49: 79 | G49: =F49-E49 -> 58 | H49: =(CleanedDataset!$F66-CleanedDataset!$E66)/CleanedDataset!$F66 -> 0.73 | I49: 0 | J49: =I49*F49-I49*E49 -> 0 | K49: 3 | L49: =K49*F49-I49*E49 -> 237 | M49: 0 | N49: =M49*F49-M49*E49 -> 0 | O49: 0 | P49: =O49*F49-O49*E49 -> 0 | Q49: 0 | R49: =Q49*F49-Q49*E49 -> 0 | S49: 0 | T49: =S49*F49-S49*E49 -> 0 | U49: 0 | V49: =U49*F49-U49*E49 -> 0 | W49: =SUM(S49,Q49,O49,M49,K49,I49) -> 3 | X49: Self-Watering | Y49: 93 | Z49: =D49*I49 -> 0
A50: CUH 2P | B50: Up the pole basket | C50: Standard Green | D50: 7 | E50: =D50*3 -> 21 | F50: 79 | G50: =F50-E50 -> 58 | H50: =(CleanedDataset!$F146-CleanedDataset!$E146)/CleanedDataset!$F146 -> 0.552 | I50: 40 | J50: =I50*F50-I50*E50 -> 2320 | K50: 32 | L50: =K50*F50-I50*E50 -> 1688 | M50: 45 | N50: =M50*F50-M50*E50 -> 2610 | O50: 13 | P50: =O50*F50-O50*E50 -> 754 | Q50: 25 | R50: =Q50*F50-Q50*E50 -> 1450 | S50: 66 | T50: =S50*F50-S50*E50 -> 3828 | U50: 45 | V50: =U50*F50-U50*E50 -> 2610 | W50: =SUM(S50,Q50,O50,M50,K50,I50) -> 221 | X50: Self-Watering | Y50: 92 | Z50: =D50*I50 -> 280
A51: CUH 2P | B51: Up the pole basket | C51: Black | D51: 7 | E51: =D51*2.8 -> 19.6 | F51: 69 | G51: =F51-E51 -> 49.4 | H51: =(CleanedDataset!$F22-CleanedDataset!$E22)/CleanedDataset!$F22 -> 0.68835616 | I51: 32 | J51: =I51*F51-I51*E51 -> 1580.8 | K51: 20 | L51: =K51*F51-I51*E51 -> 752.8 | M51: 24 | N51: =M51*F51-M51*E51 -> 1185.6 | O51: 49 | P51: =O51*F51-O51*E51 -> 2420.6 | Q51: 40 | R51: =Q51*F51-Q51*E51 -> 1976 | S51: 69 | T51: =S51*F51-S51*E51 -> 3408.6 | U51: 59 | V51: =U51*F51-U51*E51 -> 2914.6 | W51: =SUM(S51,Q51,O51,M51,K51,I51) -> 234 | X51: Self-Watering | Y51: 94 | Z51: =D51*I51 -> 224
A52: ECO 1P | B52: Eco bin | C52: Black | D52: 30 | E52: =D52*2.8 -> 84 | F52: 200 | G52: =F52-E52 -> 116 | H52: =(CleanedDataset!$F19-CleanedDataset!$E19)/CleanedDataset!$F19 -> 0.70285714 | I52: 20 | J52: =I52*F52-I52*E52 -> 2320 | K52: 25 | L52: =K52*F52-I52*E52 -> 3320 | M52: 60 | N52: =M52*F52-M52*E52 -> 6960 | O52: 45 | P52: =O52*F52-O52*E52 -> 5220 | Q52: 55 | R52: =Q52*F52-Q52*E52 -> 6380 | S52: 130 | T52: =S52*F52-S52*E52 -> 15080 | U52: 0 | V52: =U52*F52-U52*E52 -> 0 | W52: =SUM(S52,Q52,O52,M52,K52,I52) -> 335 | X52: Bins | Y52: 91 | Z52: =D52*I52 -> 600
A53: ENV 0P | B53: Eviro bin - floor | C53: Black | D53: 30 | E53: =D53*2.8 -> 84 | F53: 280 | G53: =F53-E53 -> 196 | H53: =(CleanedDataset!$F23-CleanedDataset!$E23)/CleanedDataset!$F23 -> 0.4 | I53: 35 | J53: =I53*F53-I53*E53 -> 6860 | K53: 55 | L53: =K53*F53-I53*E53 -> 12460 | M53: 2 | N53: =M53*F53-M53*E53 -> 392 | O53: 10 | P53: =O53*F53-O53*E53 -> 1960 | Q53: 62 | R53: =Q53*F53-Q53*E53 -> 12152 | S53: 57 | T53: =S53*F53-S53*E53 -> 11172 | U53: 315 | V53: =U53*F53-U53*E53 -> 61740 | W53: =SUM(S53,Q53,O53,M53,K53,I53) -> 221 | X53: Bins | Y53: 92 | Z53: =D53*I53 -> 1050
A54: FF 2P | B54: Floural fountain | C54: Guerney Granite | D54: 40 | E54: =D54*3.2 -> 128 | F54: 399 | G54: =F54-E54 -> 271 | H54: =(CleanedDataset!$F80-CleanedDataset!$E80)/CleanedDataset!$F80 -> -0.20888889 | I54: 30 | J54: =I54*F54-I54*E54 -> 8130 | K54: 0 | L54: =K54*F54-I54*E54 -> -3840 | M54: 0 | N54: =M54*F54-M54*E54 -> 0 | O54: 0 | P54: =O54*F54-O54*E54 -> 0 | Q54: 0 | R54: =Q54*F54-Q54*E54 -> 0 | S54: 0 | T54: =S54*F54-S54*E54 -> 0 | U54: 0 | V54: =U54*F54-U54*E54 -> 0 | W54: =SUM(S54,Q54,O54,M54,K54,I54) -> 30 | X54: Self-Watering | Y54: 99 | Z54: =D54*I54 -> 1200
A55: FF 2P | B55: Floural fountain | C55: Pink Granite | D55: 40 | E55: =D55*3.2 -> 128 | F55: 399 | G55: =F55-E55 -> 271 | H55: =(CleanedDataset!$F123-CleanedDataset!$E123)/CleanedDataset!$F123 -> 0.624 | I55: 55 | J55: =I55*F55-I55*E55 -> 14905 | K55: 45 | L55: =K55*F55-I55*E55 -> 10915 | M55: 0 | N55: =M55*F55-M55*E55 -> 0 | O55: 0 | P55: =O55*F55-O55*E55 -> 0 | Q55: 0 | R55: =Q55*F55-Q55*E55 -> 0 | S55: 0 | T55: =S55*F55-S55*E55 -> 0 | U55: 0 | V55: =U55*F55-U55*E55 -> 0 | W55: =SUM(S55,Q55,O55,M55,K55,I55) -> 100 | X55: Self-Watering | Y55: 98 | Z55: =D55*I55 -> 2200
A56: FF 2P | B56: Floural fountain | C56: Black | D56: 40 | E56: =D56*2.8 -> 112 | F56: 359 | G56: =F56-E56 -> 247 | H56: =(CleanedDataset!$F28-CleanedDataset!$E28)/CleanedDataset!$F28 -> 0.73333333 | I56: 41 | J56: =I56*F56-I56*E56 -> 10127 | K56: 106 | L56: =K56*F56-I56*E56 -> 33462 | M56: 81 | N56: =M56*F56-M56*E56 -> 20007 | O56: 215 | P56: =O56*F56-O56*E56 -> 53105 | Q56: 255 | R56: =Q56*F56-Q56*E56 -> 62985 | S56: 72 | T56: =S56*F56-S56*E56 -> 17784 | U56: 21 | V56: =U56*F56-U56*E56 -> 5187 | W56: =SUM(S56,Q56,O56,M56,K56,I56) -> 770 | X56: Self-Watering | Y56: 93 | Z56: =D56*I56 -> 1640
A57: HBB 1P | B57: Half barrier basket | C57: Pink Granite | D57: 8 | E57: =D57*3.2 -> 25.6 | F57: 85 | G57: =F57-E57 -> 59.4 | H57: =(CleanedDataset!$F110-CleanedDataset!$E110)/CleanedDataset!$F110 -> 0.48 | I57: 5 | J57: =I57*F57-I57*E57 -> 297 | K57: 0 | L57: =K57*F57-I57*E57 -> -128 | M57: 0 | N57: =M57*F57-M57*E57 -> 0 | O57: 0 | P57: =O57*F57-O57*E57 -> 0 | Q57: 0 | R57: =Q57*F57-Q57*E57 -> 0 | S57: 0 | T57: =S57*F57-S57*E57 -> 0 | U57: 0 | V57: =U57*F57-U57*E57 -> 0 | W57: =SUM(S57,Q57,O57,M57,K57,I57) -> 5 | X57: Self-Watering | Y57: 97 | Z57: =D57*I57 -> 40
A58: HBB 1P | B58: Half barrier basket | C58: Standard Green | D58: 8 | E58: =D58*3 -> 24 | F58: 75 | G58: =F58-E58 -> 51 | H58: =(CleanedDataset!$F151-CleanedDataset!$E151)/CleanedDataset!$F151 -> 0.648 | I58: 135 | J58: =I58*F58-I58*E58 -> 6885 | K58: 100 | L58: =K58*F58-I58*E58 -> 4260 | M58: 87 | N58: =M58*F58-M58*E58 -> 4437 | O58: 15 | P58: =O58*F58-O58*E58 -> 765 | Q58: 57 | R58: =Q58*F58-Q58*E58 -> 2907 | S58: 180 | T58: =S58*F58-S58*E58 -> 9180 | U58: 167 | V58: =U58*F58-U58*E58 -> 8517 | W58: =SUM(S58,Q58,O58,M58,K58,I58) -> 574 | X58: Self-Watering | Y58: 100 | Z58: =D58*I58 -> 1080
A59: HBB 1P | B59: Half barrier basket | C59: Black | D59: 8 | E59: =D59*2.8 -> 22.4 | F59: 65 | G59: =F59-E59 -> 42.6 | H59: =(CleanedDataset!$F34-CleanedDataset!$E34)/CleanedDataset!$F34 -> 0.77272727 | I59: 60 | J59: =I59*F59-I59*E59 -> 2556 | K59: 68 | L59: =K59*F59-I59*E59 -> 3076 | M59: 315 | N59: =M59*F59-M59*E59 -> 13419 | O59: 56 | P59: =O59*F59-O59*E59 -> 2385.6 | Q59: 132 | R59: =Q59*F59-Q59*E59 -> 5623.2 | S59: 160 | T59: =S59*F59-S59*E59 -> 6816 | U59: 168 | V59: =U59*F59-U59*E59 -> 7156.8 | W59: =SUM(S59,Q59,O59,M59,K59,I59) -> 791 | X59: Self-Watering | Y59: 99 | Z59: =D59*I59 -> 480
A60: HBB 1PL | B60: Half barrier basket | C60: Pink Granite | D60: 3.5 | E60: =D60*3.2 -> 11.2 | F60: 60 | G60: =F60-E60 -> 48.8 | H60: =(CleanedDataset!$F107-CleanedDataset!$E107)/CleanedDataset!$F107 -> 0.4 | I60: 3 | J60: =I60*F60-I60*E60 -> 146.4 | K60: 0 | L60: =K60*F60-I60*E60 -> -33.6 | M60: 0 | N60: =M60*F60-M60*E60 -> 0 | O60: 0 | P60: =O60*F60-O60*E60 -> 0 | Q60: 0 | R60: =Q60*F60-Q60*E60 -> 0 | S60: 0 | T60: =S60*F60-S60*E60 -> 0 | U60: 0 | V60: =U60*F60-U60*E60 -> 0 | W60: =SUM(S60,Q60,O60,M60,K60,I60) -> 3 | X60: Self-Watering | Y60: 94 | Z60: =D60*I60 -> 10.5
A61: HBB 1PL | B61: Half barrier basket | C61: Standard Green | D61: 3.5 | E61: =D61*3 -> 10.5 | F61: 45 | G61: =F61-E61 -> 34.5 | H61: =(CleanedDataset!$F143-CleanedDataset!$E143)/CleanedDataset!$F143 -> 0.55862069 | I61: 24 | J61: =I61*F61-I61*E61 -> 828 | K61: 0 | L61: =K61*F61-I61*E61 -> -252 | M61: 0 | N61: =M61*F61-M61*E61 -> 0 | O61: 0 | P61: =O61*F61-O61*E61 -> 0 | Q61: 0 | R61: =Q61*F61-Q61*E61 -> 0 | S61: 0 | T61: =S61*F61-S61*E61 -> 0 | U61: 0 | V61: =U61*F61-U61*E61 -> 0 | W61: =SUM(S61,Q61,O61,M61,K61,I61) -> 24 | X61: Self-Watering | Y61: 91 | Z61: =D61*I61 -> 84
A62: HBB 1PL | B62: Half barrier basket | C62: Black | D62: 3.5 | E62: =D62*2.8 -> 9.8 | F62: 35 | G62: =F62-E62 -> 25.2 | H62: =(CleanedDataset!$F44-CleanedDataset!$E44)/CleanedDataset!$F44 -> 0.69387755 | I62: 124 | J62: =I62*F62-I62*E62 -> 3124.8 | K62: 4 | L62: =K62*F62-I62*E62 -> -1075.2 | M62: 127 | N62: =M62*F62-M62*E62 -> 3200.4 | O62: 35 | P62: =O62*F62-O62*E62 -> 882 | Q62: 38 | R62: =Q62*F62-Q62*E62 -> 957.6 | S62: 12 | T62: =S62*F62-S62*E62 -> 302.4 | U62: 0 | V62: =U62*F62-U62*E62 -> 0 | W62: =SUM(S62,Q62,O62,M62,K62,I62) -> 340 | X62: Self-Watering | Y62: 97 | Z62: =D62*I62 -> 434
A63: HBB 2P | B63: Half barrier basket | C63: Standard Green | D63: 9 | E63: =D63*3 -> 27 | F63: 55 | G63: =F63-E63 -> 28 | H63: =(CleanedDataset!$F157-CleanedDataset!$E157)/CleanedDataset!$F157 -> 0.25 | I63: 230 | J63: =I63*F63-I63*E63 -> 6440 | K63: 185 | L63: =K63*F63-I63*E63 -> 3965 | M63: 74 | N63: =M63*F63-M63*E63 -> 2072 | O63: 67 | P63: =O63*F63-O63*E63 -> 1876 | Q63: 55 | R63: =Q63*F63-Q63*E63 -> 1540 | S63: 80 | T63: =S63*F63-S63*E63 -> 2240 | U63: 250 | V63: =U63*F63-U63*E63 -> 7000 | W63: =SUM(S63,Q63,O63,M63,K63,I63) -> 691 | X63: Self-Watering | Y63: 90 | Z63: =D63*I63 -> 2070
A64: HBB 2P | B64: Half barrier basket | C64: Black | D64: 9 | E64: =D64*2.8 -> 25.2 | F64: 45 | G64: =F64-E64 -> 19.8 | H64: =(CleanedDataset!$F39-CleanedDataset!$E39)/CleanedDataset!$F39 -> 0.61818182 | I64: 80 | J64: =I64*F64-I64*E64 -> 1584 | K64: 71 | L64: =K64*F64-I64*E64 -> 1179 | M64: 200 | N64: =M64*F64-M64*E64 -> 3960 | O64: 114 | P64: =O64*F64-O64*E64 -> 2257.2 | Q64: 210 | R64: =Q64*F64-Q64*E64 -> 4158 | S64: 116 | T64: =S64*F64-S64*E64 -> 2296.8 | U64: 408 | V64: =U64*F64-U64*E64 -> 8078.4 | W64: =SUM(S64,Q64,O64,M64,K64,I64) -> 791 | X64: Self-Watering | Y64: 97 | Z64: =D64*I64 -> 720
A65: HBB 2PL | B65: Half barrier basket | C65: Pink Granite | D65: 4.5 | E65: =D65*3.2 -> 14.4 | F65: 65 | G65: =F65-E65 -> 50.6 | H65: =(CleanedDataset!$F109-CleanedDataset!$E109)/CleanedDataset!$F109 -> 0.44615385 | I65: 5 | J65: =I65*F65-I65*E65 -> 253 | K65: 0 | L65: =K65*F65-I65*E65 -> -72 | M65: 0 | N65: =M65*F65-M65*E65 -> 0 | O65: 0 | P65: =O65*F65-O65*E65 -> 0 | Q65: 0 | R65: =Q65*F65-Q65*E65 -> 0 | S65: 0 | T65: =S65*F65-S65*E65 -> 0 | U65: 0 | V65: =U65*F65-U65*E65 -> 0 | W65: =SUM(S65,Q65,O65,M65,K65,I65) -> 5 | X65: Self-Watering | Y65: 94 | Z65: =D65*I65 -> 22.5
A66: HBB 2PL | B66: Half barrier basket | C66: Standard Green | D66: 4.5 | E66: =D66*3 -> 13.5 | F66: 50 | G66: =F66-E66 -> 36.5 | H66: =(CleanedDataset!$F145-CleanedDataset!$E145)/CleanedDataset!$F145 -> 0.53846154 | I66: 40 | J66: =I66*F66-I66*E66 -> 1460 | K66: 33 | L66: =K66*F66-I66*E66 -> 1110 | M66: 45 | N66: =M66*F66-M66*E66 -> 1642.5 | O66: 20 | P66: =O66*F66-O66*E66 -> 730 | Q66: 15 | R66: =Q66*F66-Q66*E66 -> 547.5 | S66: 55 | T66: =S66*F66-S66*E66 -> 2007.5 | U66: 46 | V66: =U66*F66-U66*E66 -> 1679 | W66: =SUM(S66,Q66,O66,M66,K66,I66) -> 208 | X66: Self-Watering | Y66: 100 | Z66: =D66*I66 -> 180
A67: HBB 2PL | B67: Half barrier basket | C67: Black | D67: 4.5 | E67: =D67*2.8 -> 12.6 | F67: 40 | G67: =F67-E67 -> 27.4 | H67: =(CleanedDataset!$F29-CleanedDataset!$E29)/CleanedDataset!$F29 -> 0.7 | I67: 41 | J67: =I67*F67-I67*E67 -> 1123.4 | K67: 68 | L67: =K67*F67-I67*E67 -> 2203.4 | M67: 183 | N67: =M67*F67-M67*E67 -> 5014.2 | O67: 73 | P67: =O67*F67-O67*E67 -> 2000.2 | Q67: 79 | R67: =Q67*F67-Q67*E67 -> 2164.6 | S67: 314 | T67: =S67*F67-S67*E67 -> 8603.6 | U67: 156 | V67: =U67*F67-U67*E67 -> 4274.4 | W67: =SUM(S67,Q67,O67,M67,K67,I67) -> 758 | X67: Self-Watering | Y67: 97 | Z67: =D67*I67 -> 184.5
A68: HBB 3P | B68: Half barrier basket | C68: Cherry | D68: 10 | E68: =D68*3 -> 30 | F68: 145 | G68: =F68-E68 -> 115 | H68: =(CleanedDataset!$F70-CleanedDataset!$E70)/CleanedDataset!$F70 -> 0.79310345 | I68: 2 | J68: =I68*F68-I68*E68 -> 230 | K68: 0 | L68: =K68*F68-I68*E68 -> -60 | M68: 0 | N68: =M68*F68-M68*E68 -> 0 | O68: 0 | P68: =O68*F68-O68*E68 -> 0 | Q68: 0 | R68: =Q68*F68-Q68*E68 -> 0 | S68: 0 | T68: =S68*F68-S68*E68 -> 0 | U68: 0 | V68: =U68*F68-U68*E68 -> 0 | W68: =SUM(S68,Q68,O68,M68,K68,I68) -> 2 | X68: Self-Watering | Y68: 100 | Z68: =D68*I68 -> 20
A69: HBB 3P | B69: Half barrier basket | C69: Pink Granite | D69: 10 | E69: =D69*3.2 -> 32 | F69: 145 | G69: =F69-E69 -> 113 | H69: =(CleanedDataset!$F113-CleanedDataset!$E113)/CleanedDataset!$F113 -> 0.37777778 | I69: 13 | J69: =I69*F69-I69*E69 -> 1469 | K69: 10 | L69: =K69*F69-I69*E69 -> 1034 | M69: 0 | N69: =M69*F69-M69*E69 -> 0 | O69: 0 | P69: =O69*F69-O69*E69 -> 0 | Q69: 0 | R69: =Q69*F69-Q69*E69 -> 0 | S69: 0 | T69: =S69*F69-S69*E69 -> 0 | U69: 0 | V69: =U69*F69-U69*E69 -> 0 | W69: =SUM(S69,Q69,O69,M69,K69,I69) -> 23 | X69: Self-Watering | Y69: 96 | Z69: =D69*I69 -> 130
A70: HBB 3P | B70: Half barrier basket | C70: Standard Green | D70: 10 | E70: =D70*3 -> 30 | F70: 145 | G70: =F70-E70 -> 115 | H70: =(CleanedDataset!$F140-CleanedDataset!$E140)/CleanedDataset!$F140 -> 0.58 | I70: 10 | J70: =I70*F70-I70*E70 -> 1150 | K70: 0 | L70: =K70*F70-I70*E70 -> -300 | M70: 0 | N70: =M70*F70-M70*E70 -> 0 | O70: 0 | P70: =O70*F70-O70*E70 -> 0 | Q70: 0 | R70: =Q70*F70-Q70*E70 -> 0 | S70: 0 | T70: =S70*F70-S70*E70 -> 0 | U70: 0 | V70: =U70*F70-U70*E70 -> 0 | W70: =SUM(S70,Q70,O70,M70,K70,I70) -> 10 | X70: Self-Watering | Y70: 94 | Z70: =D70*I70 -> 100
A71: HBB 3P | B71: Half barrier basket | C71: Black | D71: 10 | E71: =D71*2.8 -> 28 | F71: 130 | G71: =F71-E71 -> 102 | H71: =(CleanedDataset!$F14-CleanedDataset!$E14)/CleanedDataset!$F14 -> 0.70666667 | I71: 15 | J71: =I71*F71-I71*E71 -> 1530 | K71: 15 | L71: =K71*F71-I71*E71 -> 1530 | M71: 0 | N71: =M71*F71-M71*E71 -> 0 | O71: 0 | P71: =O71*F71-O71*E71 -> 0 | Q71: 0 | R71: =Q71*F71-Q71*E71 -> 0 | S71: 0 | T71: =S71*F71-S71*E71 -> 0 | U71: 0 | V71: =U71*F71-U71*E71 -> 0 | W71: =SUM(S71,Q71,O71,M71,K71,I71) -> 30 | X71: Self-Watering | Y71: 94 | Z71: =D71*I71 -> 150
A72: HBB 3PL | B72: Half barrier basket liner | C72: Cherry | D72: 5.5 | E72: =D72*3 -> 16.5 | F72: 99 | G72: =F72-E72 -> 82.5 | H72: =(CleanedDataset!$F71-CleanedDataset!$E71)/CleanedDataset!$F71 -> 0.78461538 | I72: 2 | J72: =I72*F72-I72*E72 -> 165 | K72: 0 | L72: =K72*F72-I72*E72 -> -33 | M72: 0 | N72: =M72*F72-M72*E72 -> 0 | O72: 0 | P72: =O72*F72-O72*E72 -> 0 | Q72: 0 | R72: =Q72*F72-Q72*E72 -> 0 | S72: 0 | T72: =S72*F72-S72*E72 -> 0 | U72: 0 | V72: =U72*F72-U72*E72 -> 0 | W72: =SUM(S72,Q72,O72,M72,K72,I72) -> 2 | X72: Self-Watering | Y72: 90 | Z72: =D72*I72 -> 11
A73: HBB 3PL | B73: Half barrier basket liner | C73: Pink Granite | D73: 5.5 | E73: =D73*3.2 -> 17.6 | F73: 99 | G73: =F73-E73 -> 81.4 | H73: =(CleanedDataset!$F114-CleanedDataset!$E114)/CleanedDataset!$F114 -> 0.37777778 | I73: 13 | J73: =I73*F73-I73*E73 -> 1058.2 | K73: 10 | L73: =K73*F73-I73*E73 -> 761.2 | M73: 0 | N73: =M73*F73-M73*E73 -> 0 | O73: 0 | P73: =O73*F73-O73*E73 -> 0 | Q73: 0 | R73: =Q73*F73-Q73*E73 -> 0 | S73: 0 | T73: =S73*F73-S73*E73 -> 0 | U73: 0 | V73: =U73*F73-U73*E73 -> 0 | W73: =SUM(S73,Q73,O73,M73,K73,I73) -> 23 | X73: Self-Watering | Y73: 93 | Z73: =D73*I73 -> 71.5
A74: HBB 3PL | B74: Half barrier basket liner | C74: Standard Green | D74: 5.5 | E74: =D74*3 -> 16.5 | F74: 85 | G74: =F74-E74 -> 68.5 | H74: =(CleanedDataset!$F141-CleanedDataset!$E141)/CleanedDataset!$F141 -> 0.47027027 | I74: 10 | J74: =I74*F74-I74*E74 -> 685 | K74: 0 | L74: =K74*F74-I74*E74 -> -165 | M74: 0 | N74: =M74*F74-M74*E74 -> 0 | O74: 0 | P74: =O74*F74-O74*E74 -> 0 | Q74: 0 | R74: =Q74*F74-Q74*E74 -> 0 | S74: 0 | T74: =S74*F74-S74*E74 -> 0 | U74: 0 | V74: =U74*F74-U74*E74 -> 0 | W74: =SUM(S74,Q74,O74,M74,K74,I74) -> 10 | X74: Self-Watering | Y74: 100 | Z74: =D74*I74 -> 55
A75: HBB 3PL | B75: Half barrier basket liner | C75: Black | D75: 5.5 | E75: =D75*2.8 -> 15.4 | F75: 75 | G75: =F75-E75 -> 59.6 | H75: =(CleanedDataset!$F15-CleanedDataset!$E15)/CleanedDataset!$F15 -> 0.725 | I75: 15 | J75: =I75*F75-I75*E75 -> 894 | K75: 15 | L75: =K75*F75-I75*E75 -> 894 | M75: 7 | N75: =M75*F75-M75*E75 -> 417.2 | O75: 8 | P75: =O75*F75-O75*E75 -> 476.8 | Q75: 27 | R75: =Q75*F75-Q75*E75 -> 1609.2 | S75: 12 | T75: =S75*F75-S75*E75 -> 715.2 | U75: 177 | V75: =U75*F75-U75*E75 -> 10549.2 | W75: =SUM(S75,Q75,O75,M75,K75,I75) -> 84 | X75: Self-Watering | Y75: 97 | Z75: =D75*I75 -> 82.5
A76: J-C40 | B76: Cylinder | C76: Terracotta | D76: 14 | E76: =D76*3 -> 42 | F76: 35 | G76: =F76-E76 -> -7 | H76: =(CleanedDataset!$F188-CleanedDataset!$E188)/CleanedDataset!$F188 -> 0.72 | I76: 134 | J76: =I76*F76-I76*E76 -> -938 | K76: 1 | L76: =K76*F76-I76*E76 -> -5593 | M76: 0 | N76: =M76*F76-M76*E76 -> 0 | O76: 0 | P76: =O76*F76-O76*E76 -> 0 | Q76: 0 | R76: =Q76*F76-Q76*E76 -> 0 | S76: 0 | T76: =S76*F76-S76*E76 -> 0 | U76: 0 | V76: =U76*F76-U76*E76 -> 0 | W76: =SUM(S76,Q76,O76,M76,K76,I76) -> 135 | X76: Planterware | Y76: 96 | Z76: =D76*I76 -> 1876
A77: J-C41 | B77: Cylinder | C77: Black | D77: 14 | E77: =D77*2.8 -> 39.2 | F77: 30 | G77: =F77-E77 -> -9.2 | H77: =(CleanedDataset!$F5-CleanedDataset!$E5)/CleanedDataset!$F5 -> 0.67857143 | I77: 0 | J77: =I77*F77-I77*E77 -> 0 | K77: 0 | L77: =K77*F77-I77*E77 -> 0 | M77: 0 | N77: =M77*F77-M77*E77 -> 0 | O77: 0 | P77: =O77*F77-O77*E77 -> 0 | Q77: 0 | R77: =Q77*F77-Q77*E77 -> 0 | S77: 0 | T77: =S77*F77-S77*E77 -> 0 | U77: 0 | V77: =U77*F77-U77*E77 -> 0 | W77: =SUM(S77,Q77,O77,M77,K77,I77) -> 0 | X77: Planterware | Y77: 93 | Z77: =D77*I77 -> 0
A78: J-C45-T2 | B78: Cylinder | C78: Terracotta | D78: 17 | E78: =D78*3 -> 51 | F78: 40 | G78: =F78-E78 -> -11 | H78: =(CleanedDataset!$F178-CleanedDataset!$E178)/CleanedDataset!$F178 -> 0.608 | I78: 60 | J78: =I78*F78-I78*E78 -> -660 | K78: 5 | L78: =K78*F78-I78*E78 -> -2860 | M78: 1 | N78: =M78*F78-M78*E78 -> -11 | O78: 0 | P78: =O78*F78-O78*E78 -> 0 | Q78: 0 | R78: =Q78*F78-Q78*E78 -> 0 | S78: 0 | T78: =S78*F78-S78*E78 -> 0 | U78: 0 | V78: =U78*F78-U78*E78 -> 0 | W78: =SUM(S78,Q78,O78,M78,K78,I78) -> 66 | X78: Planterware | Y78: 99 | Z78: =D78*I78 -> 1020
A79: J-C45-T3 | B79: Cylinder | C79: Black | D79: 17 | E79: =D79*2.8 -> 47.6 | F79: 38 | G79: =F79-E79 -> -9.6 | H79: =(CleanedDataset!$F6-CleanedDataset!$E6)/CleanedDataset!$F6 -> 0.67857143 | I79: 0 | J79: =I79*F79-I79*E79 -> 0 | K79: 0 | L79: =K79*F79-I79*E79 -> 0 | M79: 0 | N79: =M79*F79-M79*E79 -> 0 | O79: 0 | P79: =O79*F79-O79*E79 -> 0 | Q79: 0 | R79: =Q79*F79-Q79*E79 -> 0 | S79: 0 | T79: =S79*F79-S79*E79 -> 0 | U79: 0 | V79: =U79*F79-U79*E79 -> 0 | W79: =SUM(S79,Q79,O79,M79,K79,I79) -> 0 | X79: Planterware | Y79: 99 | Z79: =D79*I79 -> 0
A80: J-C45-T4 | B80: Cylinder | C80: Light Sandstone | D80: 17 | E80: =D80*3.2 -> 54.4 | F80: 45 | G80: =F80-E80 -> -9.4 | H80: =(CleanedDataset!$F92-CleanedDataset!$E92)/CleanedDataset!$F92 -> 0.41558442 | I80: 0 | J80: =I80*F80-I80*E80 -> 0 | K80: 0 | L80: =K80*F80-I80*E80 -> 0 | M80: 0 | N80: =M80*F80-M80*E80 -> 0 | O80: 0 | P80: =O80*F80-O80*E80 -> 0 | Q80: 0 | R80: =Q80*F80-Q80*E80 -> 0 | S80: 0 | T80: =S80*F80-S80*E80 -> 0 | U80: 0 | V80: =U80*F80-U80*E80 -> 0 | W80: =SUM(S80,Q80,O80,M80,K80,I80) -> 0 | X80: Planterware | Y80: 97 | Z80: =D80*I80 -> 0
A81: J-C65 | B81: Cylinder | C81: Terracotta | D81: 20 | E81: =D81*3 -> 60 | F81: 60 | G81: =F81-E81 -> 0 | H81: =(CleanedDataset!$F177-CleanedDataset!$E177)/CleanedDataset!$F177 -> 0.7 | I81: 55 | J81: =I81*F81-I81*E81 -> 0 | K81: 35 | L81: =K81*F81-I81*E81 -> -1200 | M81: 7 | N81: =M81*F81-M81*E81 -> 0 | O81: 0 | P81: =O81*F81-O81*E81 -> 0 | Q81: 0 | R81: =Q81*F81-Q81*E81 -> 0 | S81: 0 | T81: =S81*F81-S81*E81 -> 0 | U81: 0 | V81: =U81*F81-U81*E81 -> 0 | W81: =SUM(S81,Q81,O81,M81,K81,I81) -> 97 | X81: Planterware | Y81: 100 | Z81: =D81*I81 -> 1100
A82: J-EPS40-DG | B82: Egg pot square | C82: Light Sandstone | D82: 11 | E82: =D82*3.2 -> 35.2 | F82: 85 | G82: =F82-E82 -> 49.8 | H82: =(CleanedDataset!$F93-CleanedDataset!$E93)/CleanedDataset!$F93 -> 0.66666667 | I82: 0 | J82: =I82*F82-I82*E82 -> 0 | K82: 0 | L82: =K82*F82-I82*E82 -> 0 | M82: 0 | N82: =M82*F82-M82*E82 -> 0 | O82: 0 | P82: =O82*F82-O82*E82 -> 0 | Q82: 0 | R82: =Q82*F82-Q82*E82 -> 0 | S82: 0 | T82: =S82*F82-S82*E82 -> 0 | U82: 0 | V82: =U82*F82-U82*E82 -> 0 | W82: =SUM(S82,Q82,O82,M82,K82,I82) -> 0 | X82: Planterware | Y82: 98 | Z82: =D82*I82 -> 0
A83: J-EPS40-DG | B83: Egg pot square | C83: Terracotta | D83: 11 | E83: =D83*3 -> 33 | F83: 75 | G83: =F83-E83 -> 42 | H83: =(CleanedDataset!$F186-CleanedDataset!$E186)/CleanedDataset!$F186 -> 0.74285714 | I83: 130 | J83: =I83*F83-I83*E83 -> 5460 | K83: 77 | L83: =K83*F83-I83*E83 -> 1485 | M83: 12 | N83: =M83*F83-M83*E83 -> 504 | O83: 0 | P83: =O83*F83-O83*E83 -> 0 | Q83: 0 | R83: =Q83*F83-Q83*E83 -> 0 | S83: 0 | T83: =S83*F83-S83*E83 -> 0 | U83: 0 | V83: =U83*F83-U83*E83 -> 0 | W83: =SUM(S83,Q83,O83,M83,K83,I83) -> 219 | X83: Planterware | Y83: 90 | Z83: =D83*I83 -> 1430
A84: J-EPS50 | B84: Egg pot square | C84: Terracotta | D84: 15 | E84: =D84*3 -> 45 | F84: 60 | G84: =F84-E84 -> 15 | H84: =(CleanedDataset!$F189-CleanedDataset!$E189)/CleanedDataset!$F189 -> 0.68 | I84: 135 | J84: =I84*F84-I84*E84 -> 2025 | K84: 65 | L84: =K84*F84-I84*E84 -> -2175 | M84: 7 | N84: =M84*F84-M84*E84 -> 105 | O84: 0 | P84: =O84*F84-O84*E84 -> 0 | Q84: 0 | R84: =Q84*F84-Q84*E84 -> 0 | S84: 0 | T84: =S84*F84-S84*E84 -> 0 | U84: 0 | V84: =U84*F84-U84*E84 -> 0 | W84: =SUM(S84,Q84,O84,M84,K84,I84) -> 207 | X84: Planterware | Y84: 91 | Z84: =D84*I84 -> 2025
A85: J-EPS60-AT | B85: Egg pot square | C85: Terracotta | D85: 20 | E85: =D85*3 -> 60 | F85: 85 | G85: =F85-E85 -> 25 | H85: =(CleanedDataset!$F195-CleanedDataset!$E195)/CleanedDataset!$F195 -> 0.72 | I85: 208 | J85: =I85*F85-I85*E85 -> 5200 | K85: 83 | L85: =K85*F85-I85*E85 -> -5425 | M85: 20 | N85: =M85*F85-M85*E85 -> 500 | O85: 0 | P85: =O85*F85-O85*E85 -> 0 | Q85: 0 | R85: =Q85*F85-Q85*E85 -> 0 | S85: 0 | T85: =S85*F85-S85*E85 -> 0 | U85: 0 | V85: =U85*F85-U85*E85 -> 0 | W85: =SUM(S85,Q85,O85,M85,K85,I85) -> 311 | X85: Planterware | Y85: 94 | Z85: =D85*I85 -> 4160
A86: J-EPV40-DG | B86: Egg pot vase | C86: Terracotta | D86: 5 | E86: =D86*3 -> 15 | F86: 45 | G86: =F86-E86 -> 30 | H86: =(CleanedDataset!$F185-CleanedDataset!$E185)/CleanedDataset!$F185 -> 0.65 | I86: 122 | J86: =I86*F86-I86*E86 -> 3660 | K86: 91 | L86: =K86*F86-I86*E86 -> 2265 | M86: 3 | N86: =M86*F86-M86*E86 -> 90 | O86: 0 | P86: =O86*F86-O86*E86 -> 0 | Q86: 0 | R86: =Q86*F86-Q86*E86 -> 0 | S86: 0 | T86: =S86*F86-S86*E86 -> 0 | U86: 0 | V86: =U86*F86-U86*E86 -> 0 | W86: =SUM(S86,Q86,O86,M86,K86,I86) -> 216 | X86: Planterware | Y86: 97 | Z86: =D86*I86 -> 610
A87: J-EPV50-T2 | B87: Egg pot vase | C87: Terracotta | D87: 10 | E87: =D87*3 -> 30 | F87: 59 | G87: =F87-E87 -> 29 | H87: =(CleanedDataset!$F194-CleanedDataset!$E194)/CleanedDataset!$F194 -> 0.79 | I87: 194 | J87: =I87*F87-I87*E87 -> 5626 | K87: 102 | L87: =K87*F87-I87*E87 -> 198 | M87: 2 | N87: =M87*F87-M87*E87 -> 58 | O87: 0 | P87: =O87*F87-O87*E87 -> 0 | Q87: 0 | R87: =Q87*F87-Q87*E87 -> 0 | S87: 0 | T87: =S87*F87-S87*E87 -> 0 | U87: 0 | V87: =U87*F87-U87*E87 -> 0 | W87: =SUM(S87,Q87,O87,M87,K87,I87) -> 298 | X87: Planterware | Y87: 96 | Z87: =D87*I87 -> 1940
A88: J-EPV60 | B88: Egg pot vase | C88: Terracotta | D88: 13 | E88: =D88*3 -> 39 | F88: 75 | G88: =F88-E88 -> 36 | H88: =(CleanedDataset!$F190-CleanedDataset!$E190)/CleanedDataset!$F190 -> 0.7 | I88: 147 | J88: =I88*F88-I88*E88 -> 5292 | K88: 110 | L88: =K88*F88-I88*E88 -> 2517 | M88: 17 | N88: =M88*F88-M88*E88 -> 612 | O88: 0 | P88: =O88*F88-O88*E88 -> 0 | Q88: 0 | R88: =Q88*F88-Q88*E88 -> 0 | S88: 0 | T88: =S88*F88-S88*E88 -> 0 | U88: 0 | V88: =U88*F88-U88*E88 -> 0 | W88: =SUM(S88,Q88,O88,M88,K88,I88) -> 274 | X88: Planterware | Y88: 91 | Z88: =D88*I88 -> 1911
A89: J-EPV75 | B89: Egg pot vase | C89: Terracotta | D89: 17 | E89: =D89*3 -> 51 | F89: 90 | G89: =F89-E89 -> 39 | H89: =(CleanedDataset!$F187-CleanedDataset!$E187)/CleanedDataset!$F187 -> 0.74285714 | I89: 133 | J89: =I89*F89-I89*E89 -> 5187 | K89: 93 | L89: =K89*F89-I89*E89 -> 1587 | M89: 8 | N89: =M89*F89-M89*E89 -> 312 | O89: 0 | P89: =O89*F89-O89*E89 -> 0 | Q89: 0 | R89: =Q89*F89-Q89*E89 -> 0 | S89: 0 | T89: =S89*F89-S89*E89 -> 0 | U89: 0 | V89: =U89*F89-U89*E89 -> 0 | W89: =SUM(S89,Q89,O89,M89,K89,I89) -> 234 | X89: Planterware | Y89: 95 | Z89: =D89*I89 -> 2261
A90: J-R100 | B90: Rectangular container | C90: Terracotta | D90: 8 | E90: =D90*3 -> 24 | F90: 45 | G90: =F90-E90 -> 21 | H90: =(CleanedDataset!$F193-CleanedDataset!$E193)/CleanedDataset!$F193 -> 0.79 | I90: 173 | J90: =I90*F90-I90*E90 -> 3633 | K90: 91 | L90: =K90*F90-I90*E90 -> -57 | M90: 75 | N90: =M90*F90-M90*E90 -> 1575 | O90: 0 | P90: =O90*F90-O90*E90 -> 0 | Q90: 0 | R90: =Q90*F90-Q90*E90 -> 0 | S90: 0 | T90: =S90*F90-S90*E90 -> 0 | U90: 0 | V90: =U90*F90-U90*E90 -> 0 | W90: =SUM(S90,Q90,O90,M90,K90,I90) -> 339 | X90: Planterware | Y90: 91 | Z90: =D90*I90 -> 1384
A91: J-R100/40 | B91: Rectangular container | C91: Terracotta | D91: 10 | E91: =D91*3 -> 30 | F91: 60 | G91: =F91-E91 -> 30 | H91: =(CleanedDataset!$F202-CleanedDataset!$E202)/CleanedDataset!$F202 -> 0.552 | I91: 430 | J91: =I91*F91-I91*E91 -> 12900 | K91: 223 | L91: =K91*F91-I91*E91 -> 480 | M91: 157 | N91: =M91*F91-M91*E91 -> 4710 | O91: 0 | P91: =O91*F91-O91*E91 -> 0 | Q91: 0 | R91: =Q91*F91-Q91*E91 -> 0 | S91: 0 | T91: =S91*F91-S91*E91 -> 0 | U91: 0 | V91: =U91*F91-U91*E91 -> 0 | W91: =SUM(S91,Q91,O91,M91,K91,I91) -> 810 | X91: Planterware | Y91: 95 | Z91: =D91*I91 -> 4300
A92: J-R120 | B92: Rectangular container | C92: Terracotta | D92: 15 | E92: =D92*3 -> 45 | F92: 77 | G92: =F92-E92 -> 32 | H92: =(CleanedDataset!$F184-CleanedDataset!$E184)/CleanedDataset!$F184 -> 0.7 | I92: 109 | J92: =I92*F92-I92*E92 -> 3488 | K92: 102 | L92: =K92*F92-I92*E92 -> 2949 | M92: 32 | N92: =M92*F92-M92*E92 -> 1024 | O92: 0 | P92: =O92*F92-O92*E92 -> 0 | Q92: 0 | R92: =Q92*F92-Q92*E92 -> 0 | S92: 0 | T92: =S92*F92-S92*E92 -> 0 | U92: 0 | V92: =U92*F92-U92*E92 -> 0 | W92: =SUM(S92,Q92,O92,M92,K92,I92) -> 243 | X92: Planterware | Y92: 98 | Z92: =D92*I92 -> 1635
A93: J-R65 | B93: Rectangular container | C93: Terracotta | D93: 5 | E93: =D93*3 -> 15 | F93: 45 | G93: =F93-E93 -> 30 | H93: =(CleanedDataset!$F180-CleanedDataset!$E180)/CleanedDataset!$F180 -> 0.78571429 | I93: 79 | J93: =I93*F93-I93*E93 -> 2370 | K93: 29 | L93: =K93*F93-I93*E93 -> 120 | M93: 0 | N93: =M93*F93-M93*E93 -> 0 | O93: 0 | P93: =O93*F93-O93*E93 -> 0 | Q93: 0 | R93: =Q93*F93-Q93*E93 -> 0 | S93: 0 | T93: =S93*F93-S93*E93 -> 0 | U93: 0 | V93: =U93*F93-U93*E93 -> 0 | W93: =SUM(S93,Q93,O93,M93,K93,I93) -> 108 | X93: Planterware | Y93: 95 | Z93: =D93*I93 -> 395
A94: J-S40 | B94: Square | C94: Terracotta | D94: 5 | E94: =D94*3 -> 15 | F94: 32 | G94: =F94-E94 -> 17 | H94: =(CleanedDataset!$F181-CleanedDataset!$E181)/CleanedDataset!$F181 -> 0.78571429 | I94: 82 | J94: =I94*F94-I94*E94 -> 1394 | K94: 33 | L94: =K94*F94-I94*E94 -> -174 | M94: 20 | N94: =M94*F94-M94*E94 -> 340 | O94: 0 | P94: =O94*F94-O94*E94 -> 0 | Q94: 0 | R94: =Q94*F94-Q94*E94 -> 0 | S94: 0 | T94: =S94*F94-S94*E94 -> 0 | U94: 0 | V94: =U94*F94-U94*E94 -> 0 | W94: =SUM(S94,Q94,O94,M94,K94,I94) -> 135 | X94: Planterware | Y94: 92 | Z94: =D94*I94 -> 410
A95: J-S50 | B95: Square | C95: Terracotta | D95: 7 | E95: =D95*3 -> 21 | F95: 45 | G95: =F95-E95 -> 24 | H95: =(CleanedDataset!$F192-CleanedDataset!$E192)/CleanedDataset!$F192 -> 0.82769231 | I95: 153 | J95: =I95*F95-I95*E95 -> 3672 | K95: 93 | L95: =K95*F95-I95*E95 -> 972 | M95: 50 | N95: =M95*F95-M95*E95 -> 1200 | O95: 0 | P95: =O95*F95-O95*E95 -> 0 | Q95: 0 | R95: =Q95*F95-Q95*E95 -> 0 | S95: 0 | T95: =S95*F95-S95*E95 -> 0 | U95: 0 | V95: =U95*F95-U95*E95 -> 0 | W95: =SUM(S95,Q95,O95,M95,K95,I95) -> 296 | X95: Planterware | Y95: 93 | Z95: =D95*I95 -> 1071
A96: J-S60 | B96: Square | C96: Terracotta | D96: 8 | E96: =D96*3 -> 24 | F96: 51 | G96: =F96-E96 -> 27 | H96: =(CleanedDataset!$F182-CleanedDataset!$E182)/CleanedDataset!$F182 -> 0.78461538 | I96: 90 | J96: =I96*F96-I96*E96 -> 2430 | K96: 35 | L96: =K96*F96-I96*E96 -> -375 | M96: 15 | N96: =M96*F96-M96*E96 -> 405 | O96: 0 | P96: =O96*F96-O96*E96 -> 0 | Q96: 0 | R96: =Q96*F96-Q96*E96 -> 0 | S96: 0 | T96: =S96*F96-S96*E96 -> 0 | U96: 0 | V96: =U96*F96-U96*E96 -> 0 | W96: =SUM(S96,Q96,O96,M96,K96,I96) -> 140 | X96: Planterware | Y96: 100 | Z96: =D96*I96 -> 720
A97: J-S75-AG | B97: Square | C97: Terracotta | D97: 11 | E97: =D97*3 -> 33 | F97: 60 | G97: =F97-E97 -> 27 | H97: =(CleanedDataset!$F173-CleanedDataset!$E173)/CleanedDataset!$F173 -> 0.78181818 | I97: 24 | J97: =I97*F97-I97*E97 -> 648 | K97: 21 | L97: =K97*F97-I97*E97 -> 468 | M97: 3 | N97: =M97*F97-M97*E97 -> 81 | O97: 0 | P97: =O97*F97-O97*E97 -> 0 | Q97: 0 | R97: =Q97*F97-Q97*E97 -> 0 | S97: 0 | T97: =S97*F97-S97*E97 -> 0 | U97: 0 | V97: =U97*F97-U97*E97 -> 0 | W97: =SUM(S97,Q97,O97,M97,K97,I97) -> 48 | X97: Planterware | Y97: 94 | Z97: =D97*I97 -> 264
A98: J-TS3550 | B98: Tall square | C98: Terracotta | D98: 15 | E98: =D98*3 -> 45 | F98: 45 | G98: =F98-E98 -> 0 | H98: =(CleanedDataset!$F183-CleanedDataset!$E183)/CleanedDataset!$F183 -> 0.7 | I98: 103 | J98: =I98*F98-I98*E98 -> 0 | K98: 77 | L98: =K98*F98-I98*E98 -> -1170 | M98: 4 | N98: =M98*F98-M98*E98 -> 0 | O98: 0 | P98: =O98*F98-O98*E98 -> 0 | Q98: 0 | R98: =Q98*F98-Q98*E98 -> 0 | S98: 0 | T98: =S98*F98-S98*E98 -> 0 | U98: 0 | V98: =U98*F98-U98*E98 -> 0 | W98: =SUM(S98,Q98,O98,M98,K98,I98) -> 184 | X98: Planterware | Y98: 94 | Z98: =D98*I98 -> 1545
A99: J-TS4056 | B99: Tall square | C99: Terracotta | D99: 15 | E99: =D99*3 -> 45 | F99: 48 | G99: =F99-E99 -> 3 | H99: =(CleanedDataset!$F176-CleanedDataset!$E176)/CleanedDataset!$F176 -> 0.75111111 | I99: 54 | J99: =I99*F99-I99*E99 -> 162 | K99: 0 | L99: =K99*F99-I99*E99 -> -2430 | M99: 0 | N99: =M99*F99-M99*E99 -> 0 | O99: 0 | P99: =O99*F99-O99*E99 -> 0 | Q99: 0 | R99: =Q99*F99-Q99*E99 -> 0 | S99: 0 | T99: =S99*F99-S99*E99 -> 0 | U99: 0 | V99: =U99*F99-U99*E99 -> 0 | W99: =SUM(S99,Q99,O99,M99,K99,I99) -> 54 | X99: Planterware | Y99: 100 | Z99: =D99*I99 -> 810
A100: J-TS4070 | B100: Tall square | C100: Terracotta | D100: 15 | E100: =D100*3 -> 45 | F100: 50 | G100: =F100-E100 -> 5 | H100: =(CleanedDataset!$F174-CleanedDataset!$E174)/CleanedDataset!$F174 -> 0.78181818 | I100: 35 | J100: =I100*F100-I100*E100 -> 175 | K100: 85 | L100: =K100*F100-I100*E100 -> 2675 | M100: 5 | N100: =M100*F100-M100*E100 -> 25 | O100: 0 | P100: =O100*F100-O100*E100 -> 0 | Q100: 0 | R100: =Q100*F100-Q100*E100 -> 0 | S100: 0 | T100: =S100*F100-S100*E100 -> 0 | U100: 0 | V100: =U100*F100-U100*E100 -> 0 | W100: =SUM(S100,Q100,O100,M100,K100,I100) -> 125 | X100: Planterware | Y100: 93 | Z100: =D100*I100 -> 525
...

Sheet Sheet19
A1: Product | B1: Cost | C1: Selling Price | D1: Ideal Price | E1: Profit | F1: Profit Margin | G1: Sales in 2012 | H1: Margin = cost * Profit Margin % | J1: Ideal Price = Product Cost + Margin
A2: BRL 0P | B2: 45 | C2: 75 | D2: =B2+H2 -> 82 | E2: 30 | F2: 0.82222222 | G2: 496 | H2: =B2*F2 -> 37
A3: BBU 1P | B3: 16.8 | C3: 40 | D3: =B3+H3 -> 28.540235 | E3: 23.2 | F3: 0.69882353 | G3: 405 | H3: =B3*F3 -> 11.740235
A4: BBU 1P | B4: 19.2 | C4: 55 | D4: =B4+H4 -> 32.522449 | E4: 35.8 | F4: 0.69387755 | G4: 530 | H4: =B4*F4 -> 13.322449
A5: BBU 1P | B5: 18 | C5: 50 | D5: =B5+H5 -> 26.795455 | E5: 32 | F5: 0.48863636 | G5: 450 | H5: =B5*F5 -> 8.7954545
A6: BBU 1PL | B6: 9.8 | C6: 25 | D6: =B6+H6 -> 17.313333 | E6: 15.2 | F6: 0.76666667 | G6: 604 | H6: =B6*F6 -> 7.5133333
A7: BBU 1PL | B7: 10.5 | C7: 35 | D7: =B7+H7 -> 14.986364 | E7: 24.5 | F7: 0.42727273 | G7: 1350 | H7: =B7*F7 -> 4.4863636
A8: BHV 5P | B8: 154 | C8: 530 | D8: =B8+H8 -> 249.2 | E8: 376 | F8: 0.61818182 | G8: 58 | H8: =B8*F8 -> 95.2
A9: BHV 5P | B9: 176 | C9: 615 | D9: =B9+H9 -> 242.48889 | E9: 439 | F9: 0.37777778 | G9: 57 | H9: =B9*F9 -> 66.488889
A10: BHV 5P | B10: 176 | C10: 600 | D10: =B10+H10 -> 279.01176 | E10: 424 | F10: 0.58529412 | G10: 35 | H10: =B10*F10 -> 103.01176
A11: BHV 5P | B11: 165 | C11: 600 | D11: =B11+H11 -> 123.31579 | E11: 435 | F11: -0.25263158 | G11: 66 | H11: =B11*F11 -> -41.684211
A12: BHV 6P | B12: 182 | C12: 584 | D12: =B12+H12 -> 284.72889 | E12: 402 | F12: 0.56444444 | G12: 51 | H12: =B12*F12 -> 102.72889
A13: BHV 6P | B13: 208 | C13: 700 | D13: =B13+H13 -> 353.6 | E13: 492 | F13: 0.7 | G13: 5 | H13: =B13*F13 -> 145.6
... A203: RCY 1P | B203: 84 | C203: 300 | D203: =B203+H203 -> 140 | E203: 216 | F203: 0.66666667 | G203: 25 | H203: =B203*F203 -> 56

Sheet Sheet18
A3: Row Labels | B3: Average of Profit Margin | C3: Sum of Sales
A4: Light Green | B4: 0.72347403 | C4: 59
A5: Moss Stone | B5: 0.70285714 | C5: 5
A6: Standard Green | B6: 0.69263234 | C6: 51299
A7: Orange | B7: 0.67651515 | C7: 27
A8: Cherry | B8: 0.67585009 | C8: 87
A9: Pink Granite | B9: 0.66633687 | C9: 1658
A10: Black | B10: 0.62360726 | C10: 88453
A11: Guerney Granite | B11: 0.60305699 | C11: 466
A12: Sky Blue | B12: 0.57783879 | C12: 226
A13: Dark Sandstone | B13: 0.552 | C13: 39
A14: Millstone Gritt | B14: 0.552 | C14: 23
A15: Light Sandstone | B15: 0.51901875 | C15: 81
... A19: Grand Total | B19: 0.59640618 | C19: 151180

Sheet Sheet16
A1: Product Family | B1: Colour | C1: Profit Margin | D1: Total Nr of Sales | E1: Selling_Price_Pound | F1: Performance Score (Number of Sales * Profit Margin) / Selling Price) | K1: Product Family | L1: Column1 | M1: Colour | N1: Sales | O1: Profit Margin
A2: Self-Watering | B2: Black | C2: 0.49090909 | D2: 40 | E2: 220 | F2: =(D2*C2)/E2 -> 0.089256198 | K2: Self-Watering | M2: Black | N2: 40 | O2: 0.49090909
A3: Self-Watering | B3: Black | C3: 0.70984456 | D3: 12 | E3: 579 | F3: =(D3*C3)/E3 -> 0.014711804 | K3: Self-Watering | M3: Black | N3: 12 | O3: 0.70984456
A4: Self-Watering | B4: Black | C4: 0.58222222 | D4: 1 | E4: 315 | F4: =(D4*C4)/E4 -> 0.0018483245 | K4: Self-Watering | M4: Black | N4: 1 | O4: 0.58222222
A5: Planterware | B5: Black | C5: -0.30666667 | D5: 0 | E5: 30 | F5: =(D5*C5)/E5 -> 0 | K5: Planterware | M5: Black | N5: 0 | O5: -0.30666667
A6: Planterware | B6: Black | C6: -0.25263158 | D6: 0 | E6: 38 | F6: =(D6*C6)/E6 -> 0 | K6: Planterware | M6: Black | N6: 0 | O6: -0.25263158
A7: Self-Watering | B7: Black | C7: 0.61294118 | D7: 74 | E7: 340 | F7: =(D7*C7)/E7 -> 0.13340484 | K7: Self-Watering | M7: Black | N7: 74 | O7: 0.61294118
A8: Self-Watering | B8: Black | C8: 0.552 | D8: 59 | E8: 250 | F8: =(D8*C8)/E8 -> 0.130272 | K8: Self-Watering | M8: Black | N8: 59 | O8: 0.552
A9: Bins | B9: Black | C9: 0.86 | D9: 23 | E9: 100 | F9: =(D9*C9)/E9 -> 0.1978 | K9: Bins | M9: Black | N9: 23 | O9: 0.86
A10: Self-Watering | B10: Black | C10: 0.65777778 | D10: 21 | E10: 450 | F10: =(D10*C10)/E10 -> 0.030696296 | K10: Self-Watering | M10: Black | N10: 21 | O10: 0.65777778
A11: Self-Watering | B11: Black | C11: 0.72 | D11: 115 | E11: 60 | F11: =(D11*C11)/E11 -> 1.38 | K11: Self-Watering | M11: Black | N11: 115 | O11: 0.72
A12: Bins | B12: Black | C12: 0.83666667 | D12: 10 | E12: 120 | F12: =(D12*C12)/E12 -> 0.069722222 | K12: Bins | M12: Black | N12: 10 | O12: 0.83666667
A13: Bins | B13: Black | C13: 0.7 | D13: 69 | E13: 280 | F13: =(D13*C13)/E13 -> 0.1725 | K13: Bins | M13: Black | N13: 69 | O13: 0.7
... A203: Self-Watering | B203: White Marble | C203: 0.37777778 | D203: 5 | E203: 180 | F203: =(D203*C203)/E203 -> 0.010493827 | K203: Self-Watering | M203: White Marble | N203: 5 | O203: 0.37777778

Sheet Sheet11
A1: Product Family | B1: Bins | C1: Forecast(Bins) | D1: Lower Confidence Bound(Bins) | E1: Upper Confidence Bound(Bins)
A2: 2006 | B2: 1230
A3: 2007 | B3: 1453
A4: 2008 | B4: 1674
A5: 2009 | B5: 1328
A6: 2010 | B6: 2543
A7: 2011 | B7: 2081
A8: 2012 | B8: 2048 | C8: 2048 | D8: 2048 | E8: 2048
A9: 2013 | C9: =_xlfn.FORECAST.ETS(A9,$B$2:$B$8,$A$2:$A$8,1,1) -> 2376.6128 | D9: =C9-_xlfn.FORECAST.ETS.CONFINT(A9,$B$2:$B$8,$A$2:$A$8,0.95,1,1) -> 1786.4394 | E9: =C9+_xlfn.FORECAST.ETS.CONFINT(A9,$B$2:$B$8,$A$2:$A$8,0.95,1,1) -> 2966.7861
A10: 2014 | C10: =_xlfn.FORECAST.ETS(A10,$B$2:$B$8,$A$2:$A$8,1,1) -> 2540.4576 | D10: =C10-_xlfn.FORECAST.ETS.CONFINT(A10,$B$2:$B$8,$A$2:$A$8,0.95,1,1) -> 1950.2817 | E10: =C10+_xlfn.FORECAST.ETS.CONFINT(A10,$B$2:$B$8,$A$2:$A$8,0.95,1,1) -> 3130.6336
A11: 2015 | C11: =_xlfn.FORECAST.ETS(A11,$B$2:$B$8,$A$2:$A$8,1,1) -> 2704.3025 | D11: =C11-_xlfn.FORECAST.ETS.CONFINT(A11,$B$2:$B$8,$A$2:$A$8,0.95,1,1) -> 2114.1218 | E11: =C11+_xlfn.FORECAST.ETS.CONFINT(A11,$B$2:$B$8,$A$2:$A$8,0.95,1,1) -> 3294.4832
A12: 2016 | C12: =_xlfn.FORECAST.ETS(A12,$B$2:$B$8,$A$2:$A$8,1,1) -> 2868.1474 | D12: =C12-_xlfn.FORECAST.ETS.CONFINT(A12,$B$2:$B$8,$A$2:$A$8,0.95,1,1) -> 2277.9593 | E12: =C12+_xlfn.FORECAST.ETS.CONFINT(A12,$B$2:$B$8,$A$2:$A$8,0.95,1,1) -> 3458.3355
A13: 2017 | C13: =_xlfn.FORECAST.ETS(A13,$B$2:$B$8,$A$2:$A$8,1,1) -> 3031.9923 | D13: =C13-_xlfn.FORECAST.ETS.CONFINT(A13,$B$2:$B$8,$A$2:$A$8,0.95,1,1) -> 2441.7936 | E13: =C13+_xlfn.FORECAST.ETS.CONFINT(A13,$B$2:$B$8,$A$2:$A$8,0.95,1,1) -> 3622.191

Sheet All
A1: Product | B1: Description | C1: Colour | D1: Powder weight (kg) | E1: Selling Price £ | F1: 2012 | G1: 2011 | H1: 2010 | I1: 2009 | J1: 2008 | K1: 2007 | L1: 2006 | M1: Product Family | N1: Due Date Performance/%
A2: CAS 0P | B2: Cup and Saucer | C2: Black | D2: 7 | E2: 30 | F2: 2132 | G2: 2648 | H2: 2712 | I2: 1775 | J2: 2302 | K2: 2250 | L2: 2532 | M2: Self-Watering | N2: 91
A3: CAS 0P | B3: Cup and Saucer | C3: Standard Green | D3: 7 | E3: 40 | F3: 1300 | G3: 1250 | H3: 800 | I3: 750 | J3: 1200 | K3: 2050 | L3: 1980 | M3: Self-Watering | N3: 97
A4: CAS 0P | B4: Cup and Saucer | C4: Orange | D4: 7 | E4: 40 | F4: 6 | G4: 15 | M4: Self-Watering | N4: 94
A5: CAS 0P | B5: Cup and Saucer | C5: Sky Blue | D5: 7 | E5: 40 | F5: 135 | G5: 46 | M5: Self-Watering | N5: 95
A6: BBU 1P | B6: Barrier Basket | C6: Black | D6: 6 | E6: 40 | F6: 405 | G6: 534 | H6: 987 | I6: 1917 | J6: 1047 | K6: 326 | L6: 857 | M6: Self-Watering | N6: 92
A7: BBU 1P | B7: Barrier Basket | C7: Standard Green | D7: 6 | E7: 50 | F7: 450 | G7: 300 | H7: 230 | I7: 200 | J7: 225 | K7: 705 | L7: 680 | M7: Self-Watering | N7: 92
A8: BBU 1P | B8: Barrier Basket | C8: Pink Granite | D8: 6 | E8: 55 | F8: 530 | G8: 135 | M8: Self-Watering | N8: 90
A9: OCT 0P | B9: Octagonal fountain | C9: Black | D9: 35 | E9: 185 | F9: 112 | G9: 98 | H9: 92 | I9: 235 | J9: 176 | K9: 88 | L9: 28 | M9: Self-Watering | N9: 97
A10: OCT 0P | B10: Octagonal fountain | C10: Standard Green | D10: 35 | E10: 250 | F10: 230 | G10: 187 | H10: 135 | I10: 87 | J10: 53 | K10: 235 | L10: 200 | M10: Self-Watering | N10: 96
A11: OCT 0P | B11: Octagonal fountain | C11: Dark Sandstone | D11: 35 | E11: 250 | F11: 26 | G11: 13 | M11: Self-Watering | N11: 95
A12: OCT 0P | B12: Octagonal fountain | C12: Guerney Granite | D12: 35 | E12: 250 | F12: 135 | G12: 78 | M12: Self-Watering | N12: 95
A13: OCT 0P | B13: Octagonal fountain | C13: Millstone Gritt | D13: 35 | E13: 250 | F13: 15 | G13: 8 | M13: Self-Watering | N13: 97
A14: OCT 0P | B14: Octagonal fountain | C14: Pink Granite | D14: 35 | E14: 250 | F14: 76 | G14: 55 | M14: Self-Watering | N14: 95
A15: CNS 1P | B15: Cup and Saucer on pole | C15: Black | D15: 7 | E15: 45 | F15: 1064 | G15: 1153 | H15: 1979 | I15: 2901 | J15: 2434 | K15: 1693 | L15: 1311 | M15: Self-Watering | N15: 94
A16: CNS 1P | B16: Cup and Saucer on pole | C16: Standard Green | D16: 7 | E16: 55 | F16: 1578 | G16: 1450 | H16: 1135 | I16: 957 | J16: 2300 | K16: 2780 | L16: 2800 | M16: Self-Watering | N16: 95
A17: CNS 1P | B17: Cup and Saucer on pole | C17: Light Green | D17: 7 | E17: 55 | F17: 23 | G17: 15 | M17: Self-Watering | N17: 90
A18: BRL 0P | B18: Barrel | C18: Brown | D18: 15 | E18: 75 | F18: 496 | G18: 557 | M18: Self-Watering | N18: 91
A19: BHV 5P | B19: Bee hive fountain (5) | C19: Black | D19: 55 | E19: 530 | F19: 58 | G19: 75 | H19: 39 | I19: 16 | J19: 21 | K19: 60 | L19: 64 | M19: Self-Watering | N19: 100
A20: BHV 5P | B20: Bee hive fountain (5) | C20: Standard Green | D20: 55 | E20: 600 | F20: 66 | G20: 35 | H20: 12 | I20: 15 | J20: 33 | K20: 50 | L20: 45 | M20: Self-Watering | N20: 94
A21: BHV 5P | B21: Bee hive fountain (5) | C21: Pink Granite | D21: 55 | E21: 600 | F21: 35 | G21: 14 | M21: Self-Watering | N21: 90
A22: BHV 5P | B22: Bee hive fountain (5) | C22: Guerney Granite | D22: 55 | E22: 615 | F22: 57 | G22: 35 | M22: Self-Watering | N22: 93
A23: BHV 6P | B23: Bee hive fountain (6) | C23: Black | D23: 65 | E23: 584 | F23: 51 | G23: 78 | H23: 193 | I23: 0 | J23: 0 | K23: 0 | L23: 0 | M23: Self-Watering | N23: 94
A24: BHV 6P | B24: Bee hive fountain (6) | C24: Standard Green | D24: 65 | E24: 650 | F24: 158 | G24: 113 | H24: 250 | M24: Self-Watering | N24: 97
A25: BHV 6P | B25: Bee hive fountain (6) | C25: Light Green | D25: 65 | E25: 650 | F25: 3 | M25: Self-Watering | N25: 98
A26: BHV 6P | B26: Bee hive fountain (6) | C26: Moss Stone | D26: 65 | E26: 700 | G26: 5 | M26: Self-Watering | N26: 98
A27: BHV 6P | B27: Bee hive fountain (6) | C27: Guerney Granite | D27: 65 | E27: 700 | F27: 5 | M27: Self-Watering | N27: 99
A28: BHV 6P | B28: Bee hive fountain (6) | C28: Pink Granite | D28: 65 | E28: 700 | F28: 53 | G28: 28 | M28: Self-Watering | N28: 93
A29: UTP 2P | B29: Half basket up the pole | C29: Black | D29: 5 | E29: 65 | F29: 728 | G29: 871 | H29: 913 | I29: 1800 | J29: 1315 | K29: 577 | L29: 573 | M29: Self-Watering | N29: 93
A30: UTP 2P | B30: Half basket up the pole | C30: Standard Green | D30: 5 | E30: 70 | F30: 890 | G30: 765 | H30: 521 | I30: 220 | J30: 349 | K30: 1385 | L30: 1290 | M30: Self-Watering | N30: 93
A31: UTP 2P | B31: Half basket up the pole | C31: Sky Blue | D31: 5 | E31: 70 | F31: 23 | G31: 5 | M31: Self-Watering | N31: 93
A32: UTP 2P | B32: Half basket up the pole | C32: Light Green | D32: 5 | E32: 70 | F32: 15 | M32: Self-Watering | N32: 99
A33: CAS 1P | B33: Cup and Saucer (HB) | C33: Black | D33: 5 | E33: 45 | F33: 787 | G33: 478 | H33: 1235 | I33: 1450 | J33: 1728 | K33: 1182 | L33: 999 | M33: Self-Watering | N33: 97
A34: CAS 1P | B34: Cup and Saucer (HB) | C34: Standard Green | D34: 5 | E34: 50 | F34: 860 | G34: 744 | H34: 343 | I34: 320 | J34: 287 | K34: 680 | L34: 623 | M34: Self-Watering | N34: 96
A35: CAS 1P | B35: Cup and Saucer (HB) | C35: Light Sandstone | D35: 5 | E35: 60 | F35: 23 | G35: 35 | M35: Self-Watering | N35: 95
A36: MSP 0P | B36: Meter sq planter | C36: Black | D36: 35 | E36: 135 | F36: 116 | G36: 164 | H36: 319 | I36: 251 | J36: 207 | K36: 182 | L36: 54 | M36: Self-Watering | N36: 96
A37: MSP 0P | B37: Meter sq planter | C37: Pink Granite | D37: 35 | E37: 180 | G37: 89 | M37: Self-Watering | N37: 92
A38: MSP 0P | B38: Meter sq planter | C38: Light Sandstone | D38: 35 | E38: 180 | F38: 5 | M38: Self-Watering | N38: 98
A39: MSP 0P | B39: Meter sq planter | C39: White Marble | D39: 35 | E39: 180 | F39: 5 | M39: Self-Watering | N39: 97
A40: UTP 1P | B40: Half basket up the pole | C40: Black | D40: 4 | E40: 45 | F40: 962 | G40: 1465 | H40: 1334 | I40: 2383 | J40: 1525 | K40: 1582 | L40: 1539 | M40: Self-Watering | N40: 100
A41: UTP 1P | B41: Half basket up the pole | C41: Standard Green | D41: 4 | E41: 55 | F41: 1450 | G41: 834 | H41: 620 | I41: 348 | J41: 930 | K41: 870 | L41: 850 | M41: Self-Watering | N41: 96
A42: UTP 1P | B42: Half basket up the pole | C42: Orange | D42: 4 | E42: 55 | G42: 5 | M42: Self-Watering | N42: 100
A43: UTP 1P | B43: Half basket up the pole | C43: Sky Blue | D43: 4 | E43: 55 | F43: 5 | M43: Self-Watering | N43: 95
A44: UTP 1P | B44: Half basket up the pole | C44: Cherry | D44: 4 | E44: 55 | G44: 5 | M44: Self-Watering | N44: 100
A45: BBU 1PL | B45: Barrier Basket Liner | C45: Black | D45: 3.5 | E45: 25 | F45: 604 | G45: 339 | H45: 853 | I45: 2331 | J45: 1049 | K45: 326 | L45: 708 | M45: Self-Watering | N45: 99
A46: BBU 1PL | B46: Barrier Basket Liner | C46: Standard Green | D46: 3.5 | E46: 35 | F46: 1350 | G46: 1200 | H46: 567 | I46: 200 | J46: 540 | K46: 1250 | L46: 890 | M46: Self-Watering | N46: 91
A47: CHB 1P | B47: Conventional Hanging Basket | C47: Black | D47: 5 | E47: 35 | F47: 527 | G47: 203 | H47: 395 | I47: 499 | J47: 915 | K47: 230 | L47: 532 | M47: Self-Watering | N47: 91
A48: CHB 1P | B48: Conventional Hanging Basket | C48: Standard Green | D48: 5 | E48: 45 | F48: 342 | G48: 280 | H48: 133 | I48: 200 | J48: 187 | K48: 850 | L48: 345 | M48: Self-Watering | N48: 94
A49: CHB 1P | B49: Conventional Hanging Basket | C49: Cherry | D49: 5 | E49: 45 | F49: 28 | G49: 5 | M49: Self-Watering | N49: 90
A50: MSP 3P | B50: Meter sq planter (3) | C50: Black | D50: 55 | E50: 375 | F50: 36 | G50: 40 | H50: 45 | I50: 141 | J50: 156 | K50: 73 | L50: 39 | M50: Self-Watering | N50: 92
A51: MSP 3P | B51: Meter sq planter (3) | C51: Standard Green | D51: 55 | E51: 400 | F51: 25 | G51: 30 | H51: 23 | I51: 22 | J51: 35 | K51: 135 | L51: 142 | M51: Self-Watering | N51: 95
A52: MSP 3P | B52: Meter sq planter (3) | C52: Pink Granite | D52: 55 | E52: 510 | F52: 33 | G52: 15 | M52: Self-Watering | N52: 98
A53: MSP 3P | B53: Meter sq planter (3) | C53: Guerney Granite | D53: 55 | E53: 510 | F53: 53 | G53: 21 | M53: Self-Watering | N53: 99
A54: FF 2P | B54: Floural fountain | C54: Black | D54: 40 | E54: 359 | F54: 41 | G54: 106 | H54: 81 | I54: 215 | J54: 255 | K54: 72 | L54: 21 | M54: Self-Watering | N54: 93
A55: FF 2P | B55: Floural fountain | C55: Pink Granite | D55: 40 | E55: 399 | F55: 55 | G55: 45 | M55: Self-Watering | N55: 98
A56: FF 2P | B56: Floural fountain | C56: Guerney Granite | D56: 40 | E56: 399 | F56: 30 | M56: Self-Watering | N56: 99
A57: OVL 0P | B57: Floor standing oval planter | C57: Pink Granite | D57: 30 | E57: 120 | F57: 42 | G57: 47 | H57: 12 | I57: 7 | J57: 71 | K57: 29 | L57: 31 | M57: Self-Watering | N57: 96
A58: OVL 0P | B58: Floor standing oval planter | C58: Guerney Granite | D58: 30 | E58: 150 | F58: 26 | G58: 25 | M58: Self-Watering | N58: 100
A59: OVL 0P | B59: Floor standing oval planter | C59: Sky Blue | D59: 30 | E59: 120 | F59: 5 | M59: Self-Watering | N59: 96
A60: OVL 0P | B60: Floor standing oval planter | C60: Cherry | D60: 30 | E60: 120 | F60: 8 | M60: Self-Watering | N60: 97
A61: HBB 2P | B61: Half barrier basket | C61: Black | D61: 9 | E61: 45 | F61: 80 | G61: 71 | H61: 200 | I61: 114 | J61: 210 | K61: 116 | L61: 408 | M61: Self-Watering | N61: 97
A62: HBB 2P | B62: Half barrier basket | C62: Standard Green | D62: 9 | E62: 55 | F62: 230 | G62: 185 | H62: 74 | I62: 67 | J62: 55 | K62: 80 | L62: 250 | M62: Self-Watering | N62: 90
A63: BBU 0P | B63: Full barrier basket | C63: Black | D63: 7.5 | E63: 58 | F63: 94 | G63: 138 | H63: 124 | I63: 72 | J63: 10 | K63: 0 | L63: 0 | M63: Self-Watering | N63: 99
A64: BBU 0P | B64: Full barrier basket | C64: Standard Green | D64: 7.5 | E64: 70 | F64: 360 | G64: 245 | H64: 133 | I64: 88 | J64: 10 | M64: Self-Watering | N64: 99
A65: BBU 0P | B65: Full barrier basket | C65: Cherry | D65: 7.5 | E65: 70 | F65: 5 | M65: Self-Watering | N65: 96
A66: WBX 1PL | B66: Wall and window box | C66: Black | D66: 3.5 | E66: 35 | F66: 62 | G66: 36 | H66: 46 | I66: 34 | J66: 1 | K66: 1 | L66: 4 | M66: Self-Watering | N66: 100
A67: WBX 1PL | B67: Wall and window box | C67: Standard Green | D67: 3.5 | E67: 50 | F67: 5 | M67: Self-Watering | N67: 92
A68: WBX 1PL | B68: Wall and window box | C68: Light Green | D68: 3.5 | E68: 50 | F68: 3 | M68: Self-Watering | N68: 93
A69: WBX 1PL | B69: Wall and window box | C69: Pink Granite | D69: 3.5 | E69: 65 | F69: 35 | M69: Self-Watering | N69: 96
A70: WBX 3PL | B70: Wall and window box | C70: Black | D70: 5.5 | E70: 75 | F70: 45 | G70: 3 | H70: 10 | I70: 21 | J70: 1 | K70: 40 | L70: 41 | M70: Self-Watering | N70: 91
A71: WBX 3PL | B71: Wall and window box | C71: Standard Green | D71: 5.5 | E71: 80 | F71: 200 | G71: 45 | H71: 5 | M71: Self-Watering | N71: 92
A72: WBX 3PL | B72: Wall and window box | C72: Pink Granite | D72: 5.5 | E72: 95 | F72: 35 | M72: Self-Watering | N72: 96
A73: UTP 2PL | B73: Half pole basket | C73: Black | D73: 3.5 | E73: 28 | F73: 299 | G73: 83 | H73: 176 | I73: 400 | J73: 427 | K73: 459 | L73: 369 | M73: Self-Watering | N73: 99
A74: UTP 2PL | B74: Half pole basket | C74: Standard Green | D74: 3.5 | E74: 35 | F74: 433 | G74: 350 | H74: 235 | I74: 170 | J74: 55 | K74: 135 | L74: 120 | M74: Self-Watering | N74: 99
A75: UTP 2PL | B75: Half pole basket | C75: Cherry | D75: 3.5 | E75: 35 | G75: 13 | M75: Self-Watering | N75: 100
A76: WBX 1P | B76: Wall and window box | C76: Black | D76: 8 | E76: 65 | F76: 163 | G76: 33 | H76: 68 | I76: 32 | J76: 138 | K76: 386 | L76: 233 | M76: Self-Watering | N76: 91
A77: WBX 1P | B77: Wall and window box | C77: Standard Green | D77: 8 | E77: 80 | F77: 189 | G77: 144 | H77: 64 | J77: 87 | K77: 153 | L77: 145 | M77: Self-Watering | N77: 98
A78: WBX 1P | B78: Wall and window box | C78: Pink Granite | D78: 8 | E78: 80 | F78: 35 | G78: 23 | M78: Self-Watering | N78: 93
A79: UTP 1PL | B79: Half pole basket | C79: Black | D79: 3.5 | E79: 25 | F79: 382 | G79: 425 | H79: 323 | I79: 238 | J79: 484 | K79: 394 | L79: 213 | M79: Self-Watering | N79: 97
A80: UTP 1PL | B80: Half pole basket | C80: Standard Green | D80: 3.5 | E80: 35 | F80: 530 | G80: 480 | H80: 257 | I80: 200 | J80: 230 | K80: 580 | L80: 578 | M80: Self-Watering | N80: 95
A81: WBX 3P | B81: Wall and window box | C81: Black | D81: 10 | E81: 130 | F81: 38 | G81: 16 | H81: 36 | I81: 79 | J81: 23 | K81: 78 | L81: 124 | M81: Self-Watering | N81: 97
A82: WBX 3P | B82: Wall and window box | C82: Standard Green | D82: 10 | E82: 145 | F82: 45 | G82: 35 | H82: 30 | I82: 20 | J82: 15 | K82: 50 | L82: 45 | M82: Self-Watering | N82: 100
A83: WBX 3P | B83: Wall and window box | C83: Pink Granite | D83: 10 | E83: 160 | F83: 55 | M83: Self-Watering | N83: 99
A84: HBB 2PL | B84: Half barrier basket | C84: Black | D84: 4.5 | E84: 40 | F84: 41 | G84: 68 | H84: 183 | I84: 73 | J84: 79 | K84: 314 | L84: 156 | M84: Self-Watering | N84: 97
A85: HBB 2PL | B85: Half barrier basket | C85: Standard Green | D85: 4.5 | E85: 50 | F85: 40 | G85: 33 | H85: 45 | I85: 20 | J85: 15 | K85: 55 | L85: 46 | M85: Self-Watering | N85: 100
A86: HBB 2PL | B86: Half barrier basket | C86: Pink Granite | D86: 4.5 | E86: 65 | F86: 5 | M86: Self-Watering | N86: 94
A87: CNS 1PL | B87: half cup and saucer up the pole | C87: Black | D87: 5 | E87: 85 | F87: 268 | G87: 253 | H87: 178 | I87: 360 | J87: 816 | K87: 410 | L87: 301 | M87: Self-Watering | N87: 93
A88: CNS 1PL | B88: half cup and saucer up the pole | C88: Standard Green | D88: 5 | E88: 85 | F88: 180 | M88: Self-Watering | N88: 98
A89: HBB 1PL | B89: Half barrier basket | C89: Black | D89: 3.5 | E89: 35 | F89: 124 | G89: 4 | H89: 127 | I89: 35 | J89: 38 | K89: 12 | L89: 0 | M89: Self-Watering | N89: 97
A90: HBB 1PL | B90: Half barrier basket | C90: Standard Green | D90: 3.5 | E90: 45 | F90: 24 | M90: Self-Watering | N90: 91
A91: HBB 1PL | B91: Half barrier basket | C91: Pink Granite | D91: 3.5 | E91: 60 | F91: 3 | M91: Self-Watering | N91: 94
A92: CHB 2P | B92: Conventional Hanging Basket | C92: Black | D92: 5 | E92: 56 | F92: 61 | G92: 97 | H92: 29 | I92: 91 | J92: 62 | K92: 419 | L92: 37 | M92: Self-Watering | N92: 96
A93: CHB 2P | B93: Conventional Hanging Basket | C93: Standard Green | D93: 5 | E93: 66 | F93: 87 | G93: 65 | H93: 50 | I93: 67 | J93: 50 | K93: 35 | L93: 55 | M93: Self-Watering | N93: 91
A94: CHB 2P | B94: Conventional Hanging Basket | C94: Cherry | D94: 5 | E94: 66 | G94: 5 | M94: Self-Watering | N94: 91
A95: CHB 2P | B95: Conventional Hanging Basket | C95: Orange | D95: 5 | E95: 66 | F95: 1 | M95: Self-Watering | N95: 98
A96: HBB 1P | B96: Half barrier basket | C96: Black | D96: 8 | E96: 65 | F96: 60 | G96: 68 | H96: 315 | I96: 56 | J96: 132 | K96: 160 | L96: 168 | M96: Self-Watering | N96: 99
A97: HBB 1P | B97: Half barrier basket | C97: Standard Green | D97: 8 | E97: 75 | F97: 135 | G97: 100 | H97: 87 | I97: 15 | J97: 57 | K97: 180 | L97: 167 | M97: Self-Watering | N97: 100
A98: HBB 1P | B98: Half barrier basket | C98: Pink Granite | D98: 8 | E98: 85 | F98: 5 | M98: Self-Watering | N98: 97
A99: CUH 2P | B99: Up the pole basket | C99: Black | D99: 7 | E99: 69 | F99: 32 | G99: 20 | H99: 24 | I99: 49 | J99: 40 | K99: 69 | L99: 59 | M99: Self-Watering | N99: 94
A100: CUH 2P | B100: Up the pole basket | C100: Standard Green | D100: 7 | E100: 79 | F100: 40 | G100: 32 | H100: 45 | I100: 13 | J100: 25 | K100: 66 | L100: 45 | M100: Self-Watering | N100: 92
...

Sheet Information
B2: The company produces own range of plastic planters and bins. There are two product families for planters: Self-watering and Planterware.
B3: Self-watering planters are planters designed with self-watering feature. This feature consists of a built-in water reservoir and capillary mechanisms.
B4: In order to increase competitiveness, the company has increased the colours offered. Majority of the colours were only introduced from year 2011 onwards
B5: except Black and Standard Green colors. Make-to-Order business model is adopted.
B7: Standard Industry Lead Time : 2 Weeks for Planters, 3 Weeks for Bins
B22: Powder Cost £/kg | F22: Typical Demand Distribution %
B23: Colour | C23: Cost | F23: Month | G23: Demand of Planters | H23: Demand of Bins
B24: White | C24: 3 | F24: Jan | G24: 3 | H24: 10
B25: Black | C25: 2.8 | F25: Feb | G25: 8 | H25: 11
B26: Biscuit | C26: 3 | F26: Mac | G26: 13 | H26: 8
B27: Terracotta | C27: 3 | F27: April | G27: 18 | H27: 4
B28: Cherry | C28: 3 | F28: May | G28: 18 | H28: 2
B29: Orange | C29: 3 | F29: June | G29: 15 | H29: 3
B30: Sky Blue | C30: 3 | F30: July | G30: 10 | H30: 7
B31: Navy Blue | C31: 3 | F31: August | G31: 8 | H31: 7
B32: Light Green | C32: 3 | F32: Sept | G32: 3 | H32: 8
B33: Standard Green | C33: 3 | F33: Oct | G33: 2 | H33: 13
B34: White Marble | C34: 3.2 | F34: Nov | G34: 1 | H34: 15
B35: Pink Granite | C35: 3.2 | F35: Dec | G35: 1 | H35: 12
B36: Tudor Brown Mottle | C36: 3 | F36: Total | G36: =SUM(G24:G35) -> 100 | H36: =SUM(H24:H35) -> 100
B37: Moss Stone | C37: 3.2
B38: Light Sandstone | C38: 3.2
B39: Dark Standstone | C39: 3.2
B40: Guernsey Granite | C40: 3.2
B41: Millstone Gritt | C41: 3.2
B42: Brown | C42: 3
B45: Transaction cost/order to supplier: £50
B47: Distance between Powder Supplier and the company is assumed to be 500 miles
B48: Delivery Cost/20 ft Container: £750 (for 500 miles)
B49: Capacity/20 ft Container: 10 pallets
B50: Delivery Cost/Pallet (500 miles): £100
B51: Minimum order quantity for powder is ONE pallet per colour; Each pallet is 500kg
B53: Warehouse: | C53: The company has their own warehouse and assumed to be always available (for both Raw Material and Finished Goods).
B54: Holding Cost: | C54: 7% of total capital tied up as inventory (Raw Material/Finished Goods)
B56: Product selling price is Ex Works: Delivery method and cost is chosen and paid by customers

Sheet Sheet3
J6: Years | K6: Total Sales | L6: New Colour Sales
J7: 2012 | K7: 29941 | L7: 2428 | M7: 25472 | N7: =SUM(L7:M7) -> 27900
J8: 2011 | K8: 24843 | L8: 1308
J9: 2010 | K9: 22470
J10: 2009 | K10: 23226
J11: 2008 | K11: 24809
J12: 2007 | K12: 25891
J13: 2006 | K13: 24122

Sheet ColorR
A1: Colours | B1: Sales_2012 | C1: Sales_2011
A2: Pink Granite | B2: 885 | C2: 462
A3: Brown | B3: 496 | C3: 557
A4: Terracota | B4: 249 | C4: 56
A5: Cherry | B5: 209 | C5: 0
A6: Sky Blue | B6: 295 | C6: 46
A7: Guerney Granite | B7: 140 | C7: 62
A8: Dark Sandstone | B8: 53 | C8: 21
A9: Light Green | B9: 38 | C9: 41
A10: Light Sandstone | B10: 36 | C10: 30
A11: Millstone Gritt | B11: 15 | C11: 8
A12: Orange | B12: 7 | C12: 20
A13: White Marble | B13: 5 | C13: 0
A14: Moss Stone | B14: 0 | C14: 5

Sheet All_Cleaned
A1: Product | B1: Description | C1: Colour | D1: Powder weight (kg) | E1: Selling Price £ | F1: Salesin_2012 | G1: Salesin_2011 | H1: Salesin_2010 | I1: Salesin_2009 | J1: Salesin_2008 | K1: Salesin_2007 | L1: Salesin_2006 | M1: Product Family | N1: Due Date Performance/% | O1: Powder Cost | P1: Cost | Q1: Net Profit | R1: Profit Margin %
A2: BHV 6P | B2: Bee hive fountain (6) | C2: Guerney Granite | D2: 65 | E2: 700 | F2: 5 | G2: 0 | H2: 0 | I2: 0 | J2: 0 | K2: 0 | L2: 0 | M2: Self-Watering | N2: 99 | O2: {=_xlfn.XLOOKUP(C2,Table1[[#All],[Colour]],Table1[[#All],[Cost]],0)} -> 0 | P2: =O2*D2 -> 0 | Q2: =E2-P2 -> 700 | R2: =Q2/E2*100 -> 100
A3: BHV 5P | B3: Bee hive fountain (5) | C3: Guerney Granite | D3: 55 | E3: 615 | F3: 57 | G3: 35 | H3: 0 | I3: 0 | J3: 0 | K3: 0 | L3: 0 | M3: Self-Watering | N3: 93 | O3: {=_xlfn.XLOOKUP(C3,Table1[[#All],[Colour]],Table1[[#All],[Cost]],0)} -> 0 | P3: =O3*D3 -> 0 | Q3: =E3-P3 -> 615 | R3: =Q3/E3*100 -> 100
A4: MSP 3P | B4: Meter sq planter (3) | C4: Guerney Granite | D4: 55 | E4: 510 | F4: 53 | G4: 21 | H4: 0 | I4: 0 | J4: 0 | K4: 0 | L4: 0 | M4: Self-Watering | N4: 99 | O4: {=_xlfn.XLOOKUP(C4,Table1[[#All],[Colour]],Table1[[#All],[Cost]],0)} -> 0 | P4: =O4*D4 -> 0 | Q4: =E4-P4 -> 510 | R4: =Q4/E4*100 -> 100
A5: BHV 6P | B5: Bee hive fountain (6) | C5: Moss Stone | D5: 65 | E5: 700 | F5: 0 | G5: 5 | H5: 0 | I5: 0 | J5: 0 | K5: 0 | L5: 0 | M5: Self-Watering | N5: 98 | O5: {=_xlfn.XLOOKUP(C5,Table1[[#All],[Colour]],Table1[[#All],[Cost]],0)} -> 3.2 | P5: =O5*D5 -> 208 | Q5: =E5-P5 -> 492 | R5: =Q5/E5*100 -> 70.285714
A6: BHV 6P | B6: Bee hive fountain (6) | C6: Pink Granite | D6: 65 | E6: 700 | F6: 53 | G6: 28 | H6: 0 | I6: 0 | J6: 0 | K6: 0 | L6: 0 | M6: Self-Watering | N6: 93 | O6: {=_xlfn.XLOOKUP(C6,Table1[[#All],[Colour]],Table1[[#All],[Cost]],0)} -> 3.2 | P6: =O6*D6 -> 208 | Q6: =E6-P6 -> 492 | R6: =Q6/E6*100 -> 70.285714
A7: MSP 4P | B7: Meter sq planter (4) | C7: Pink Granite | D7: 60 | E7: 650 | F7: 3 | G7: 0 | H7: 0 | I7: 0 | J7: 0 | K7: 0 | L7: 0 | M7: Self-Watering | N7: 92 | O7: {=_xlfn.XLOOKUP(C7,Table1[[#All],[Colour]],Table1[[#All],[Cost]],0)} -> 3.2 | P7: =O7*D7 -> 192 | Q7: =E7-P7 -> 458 | R7: =Q7/E7*100 -> 70.461538
A8: MSP 4P | B8: Meter sq planter (4) | C8: Light Sandstone | D8: 60 | E8: 650 | F8: 5 | G8: 0 | H8: 0 | I8: 0 | J8: 0 | K8: 0 | L8: 0 | M8: Self-Watering | N8: 99 | O8: {=_xlfn.XLOOKUP(C8,Table1[[#All],[Colour]],Table1[[#All],[Cost]],0)} -> 3.2 | P8: =O8*D8 -> 192 | Q8: =E8-P8 -> 458 | R8: =Q8/E8*100 -> 70.461538
A9: BHV 6P | B9: Bee hive fountain (6) | C9: Standard Green | D9: 65 | E9: 650 | F9: 158 | G9: 113 | H9: 250 | I9: 0 | J9: 0 | K9: 0 | L9: 0 | M9: Self-Watering | N9: 97 | O9: {=_xlfn.XLOOKUP(C9,Table1[[#All],[Colour]],Table1[[#All],[Cost]],0)} -> 3 | P9: =O9*D9 -> 195 | Q9: =E9-P9 -> 455 | R9: =Q9/E9*100 -> 70
A10: BHV 6P | B10: Bee hive fountain (6) | C10: Light Green | D10: 65 | E10: 650 | F10: 3 | G10: 0 | H10: 0 | I10: 0 | J10: 0 | K10: 0 | L10: 0 | M10: Self-Watering | N10: 98 | O10: {=_xlfn.XLOOKUP(C10,Table1[[#All],[Colour]],Table1[[#All],[Cost]],0)} -> 3 | P10: =O10*D10 -> 195 | Q10: =E10-P10 -> 455 | R10: =Q10/E10*100 -> 70
A11: BHV 5P | B11: Bee hive fountain (5) | C11: Standard Green | D11: 55 | E11: 600 | F11: 66 | G11: 35 | H11: 12 | I11: 15 | J11: 33 | K11: 50 | L11: 45 | M11: Self-Watering | N11: 94 | O11: {=_xlfn.XLOOKUP(C11,Table1[[#All],[Colour]],Table1[[#All],[Cost]],0)} -> 3 | P11: =O11*D11 -> 165 | Q11: =E11-P11 -> 435 | R11: =Q11/E11*100 -> 72.5
A12: BHV 5P | B12: Bee hive fountain (5) | C12: Pink Granite | D12: 55 | E12: 600 | F12: 35 | G12: 14 | H12: 0 | I12: 0 | J12: 0 | K12: 0 | L12: 0 | M12: Self-Watering | N12: 90 | O12: {=_xlfn.XLOOKUP(C12,Table1[[#All],[Colour]],Table1[[#All],[Cost]],0)} -> 3.2 | P12: =O12*D12 -> 176 | Q12: =E12-P12 -> 424 | R12: =Q12/E12*100 -> 70.666667
A13: MSP 4P | B13: Meter sq planter (4) | C13: Black | D13: 60 | E13: 579 | F13: 0 | G13: 0 | H13: 0 | I13: 0 | J13: 12 | K13: 0 | L13: 0 | M13: Self-Watering | N13: 96 | O13: {=_xlfn.XLOOKUP(C13,Table1[[#All],[Colour]],Table1[[#All],[Cost]],0)} -> 2.8 | P13: =O13*D13 -> 168 | Q13: =E13-P13 -> 411 | R13: =Q13/E13*100 -> 70.984456
... A155: BRL 0P | B155: Barrel | C155: Brown | D155: 15 | E155: 75 | F155: 496 | G155: 557 | H155: 0 | I155: 0 | J155: 0 | K155: 0 | L155: 0 | M155: Self-Watering | N155: 91 | O155: {=_xlfn.XLOOKUP(C155,Table1[[#All],[Colour]],Table1[[#All],[Cost]],0)} -> 3 | P155: =O155*D155 -> 45 | Q155: =E155-P155 -> 30 | R155: =Q155/E155*100 -> 40
A156: CAS 0P | B156: Cup and Saucer | C156: Black | D156: 7 | E156: 30 | F156: 2132 | G156: 2648 | H156: 2712 | I156: 1775 | J156: 2302 | K156: 2250 | L156: 2532 | M156: Self-Watering | N156: 91 | O156: {=_xlfn.XLOOKUP($C$2,Table1[[#All],[Colour]],Table1[[#All],[Cost]],0)} -> 0 | P156: =O156*D156 -> 0 | Q156: =E156-P156 -> 30 | R156: =Q156/E156*100 -> 100
A157: OVL 0P | B157: Floor standing oval planter | C157: Sky Blue | D157: 30 | E157: 120 | F157: 5 | G157: 0 | H157: 0 | I157: 0 | J157: 0 | K157: 0 | L157: 0 | M157: Self-Watering | N157: 96 | O157: {=_xlfn.XLOOKUP(C157,Table1[[#All],[Colour]],Table1[[#All],[Cost]],0)} -> 3 | P157: =O157*D157 -> 90 | Q157: =E157-P157 -> 30 | R157: =Q157/E157*100 -> 25
A158: OVL 0P | B158: Floor standing oval planter | C158: Cherry | D158: 30 | E158: 120 | F158: 8 | G158: 0 | H158: 0 | I158: 0 | J158: 0 | K158: 0 | L158: 0 | M158: Self-Watering | N158: 97 | O158: {=_xlfn.XLOOKUP(C158,Table1[[#All],[Colour]],Table1[[#All],[Cost]],0)} -> 3 | P158: =O158*D158 -> 90 | Q158: =E158-P158 -> 30 | R158: =Q158/E158*100 -> 25
A159: J-EPV50-T2 | B159: Egg pot vase | C159: Terracotta | D159: 10 | E159: 59 | F159: 194 | G159: 102 | H159: 2 | I159: 0 | J159: 0 | K159: 0 | L159: 0 | M159: Planterware | N159: 96 | O159: {=_xlfn.XLOOKUP(C159,Table1[[#All],[Colour]],Table1[[#All],[Cost]],0)} -> 3 | P159: =O159*D159 -> 30 | Q159: =E159-P159 -> 29 | R159: =Q159/E159*100 -> 49.152542
A160: J-V85-PR | B160: Plain vase | C160: Terracotta | D160: 12 | E160: 65 | F160: 240 | G160: 170 | H160: 15 | I160: 0 | J160: 0 | K160: 0 | L160: 0 | M160: Planterware | N160: 97 | O160: {=_xlfn.XLOOKUP(C160,Table1[[#All],[Colour]],Table1[[#All],[Cost]],0)} -> 3 | P160: =O160*D160 -> 36 | Q160: =E160-P160 -> 29 | R160: =Q160/E160*100 -> 44.615385
A161: SLM 0P | B161: Slim bin | C161: Black | D161: 25 | E161: 99 | F161: 65 | G161: 50 | H161: 95 | I161: 89 | J161: 66 | K161: 30 | L161: 0 | M161: Bins | N161: 93 | O161: {=_xlfn.XLOOKUP(C161,Table1[[#All],[Colour]],Table1[[#All],[Cost]],0)} -> 2.8 | P161: =O161*D161 -> 70 | Q161: =E161-P161 -> 29 | R161: =Q161/E161*100 -> 29.292929
A162: HBB 2P | B162: Half barrier basket | C162: Standard Green | D162: 9 | E162: 55 | F162: 230 | G162: 185 | H162: 74 | I162: 67 | J162: 55 | K162: 80 | L162: 250 | M162: Self-Watering | N162: 90 | O162: {=_xlfn.XLOOKUP(C162,Table1[[#All],[Colour]],Table1[[#All],[Cost]],0)} -> 3 | P162: =O162*D162 -> 27 | Q162: =E162-P162 -> 28 | R162: =Q162/E162*100 -> 50.909091
A163: HBB 2PL | B163: Half barrier basket | C163: Black | D163: 4.5 | E163: 40 | F163: 41 | G163: 68 | H163: 183 | I163: 73 | J163: 79 | K163: 314 | L163: 156 | M163: Self-Watering | N163: 97 | O163: {=_xlfn.XLOOKUP(C163,Table1[[#All],[Colour]],Table1[[#All],[Cost]],0)} -> 2.8 | P163: =O163*D163 -> 12.6 | Q163: =E163-P163 -> 27.4 | R163: =Q163/E163*100 -> 68.5
A164: J-S60 | B164: Square | C164: Terracotta | D164: 8 | E164: 51 | F164: 90 | G164: 35 | H164: 15 | I164: 0 | J164: 0 | K164: 0 | L164: 0 | M164: Planterware | N164: 100 | O164: {=_xlfn.XLOOKUP(C164,Table1[[#All],[Colour]],Table1[[#All],[Cost]],0)} -> 3 | P164: =O164*D164 -> 24 | Q164: =E164-P164 -> 27 | R164: =Q164/E164*100 -> 52.941176
A165: ST 1P | B165: Stipple bin | C165: Black | D165: 10 | E165: 55 | F165: 200 | G165: 233 | H165: 150 | I165: 200 | J165: 148 | K165: 150 | L165: 170 | M165: Bins | N165: 96 | O165: {=_xlfn.XLOOKUP(C165,Table1[[#All],[Colour]],Table1[[#All],[Cost]],0)} -> 2.8 | P165: =O165*D165 -> 28 | Q165: =E165-P165 -> 27 | R165: =Q165/E165*100 -> 49.090909
A166: J-S75-AG | B166: Square | C166: Terracotta | D166: 11 | E166: 60 | F166: 24 | G166: 21 | H166: 3 | I166: 0 | J166: 0 | K166: 0 | L166: 0 | M166: Planterware | N166: 94 | O166: {=_xlfn.XLOOKUP(C166,Table1[[#All],[Colour]],Table1[[#All],[Cost]],0)} -> 3 | P166: =O166*D166 -> 33 | Q166: =E166-P166 -> 27 | R166: =Q166/E166*100 -> 45
A167: CNS 1P | B167: Cup and Saucer on pole | C167: Black | D167: 7 | E167: 45 | F167: 1064 | G167: 1153 | H167: 1979 | I167: 2901 | J167: 2434 | K167: 1693 | L167: 1311 | M167: Self-Watering | N167: 94 | O167: {=_xlfn.XLOOKUP(C167,Table1[[#All],[Colour]],Table1[[#All],[Cost]],0)} -> 2.8 | P167: =O167*D167 -> 19.6 | Q167: =E167-P167 -> 25.4 | R167: =Q167/E167*100 -> 56.444444
A168: WBX 1PL | B168: Wall and window box | C168: Black | D168: 3.5 | E168: 35 | F168: 62 | G168: 36 | H168: 46 | I168: 34 | J168: 1 | K168: 1 | L168: 4 | M168: Self-Watering | N168: 100 | O168: {=_xlfn.XLOOKUP(C168,Table1[[#All],[Colour]],Table1[[#All],[Cost]],0)} -> 2.8 | P168: =O168*D168 -> 9.8 | Q168: =E168-P168 -> 25.2 | R168: =Q168/E168*100 -> 72
... A203: J-C45-T2 | B203: Cylinder | C203: Terracotta | D203: 17 | E203: 40 | F203: 60 | G203: 5 | H203: 1 | I203: 0 | J203: 0 | K203: 0 | L203: 0 | M203: Planterware | N203: 99 | O203: {=_xlfn.XLOOKUP(C203,Table1[[#All],[Colour]],Table1[[#All],[Cost]],0)} -> 3 | P203: =O203*D203 -> 51 | Q203: =E203-P203 -> -11 | R203: =Q203/E203*100 -> -27.5

Sheet Pivot 
A1: Colour | B1: (All)
A3: Row Labels | B3: Sum of Cost | C3: Sum of Profit Margin | D3: Sum of Powder Cost | G3: Row Labels | H3: Sum of Powder Cost
A4: Bins | B4: 1265.6 | C4: 2678.4 | D4: 56 | G4: Bins | H4: 56
A5: Planterware | B5: 1341.9 | C5: 782.1 | D5: 111 | G5: Planterware | H5: 111
A6: Self-Watering | B6: 8787.1 | C6: 19327.9 | D6: 410.4 | G6: Self-Watering | H6: 410.4
A7: Grand Total | B7: 11394.6 | C7: 22788.4 | D7: 577.4 | G7: Grand Total | H7: 577.4
B12: Product | C12: (All)
B14: Row Labels | C14: Sum of Cost | D14: Sum of Profit Margin | F14: Product family | G14: Sum of Cost | H14: Sum of Selling Price £
B15: Bins | C15: 1265.6 | D15: 2678.4 | F15: Bins | G15: 1265.6 | H15: 3944
B16: Planterware | C16: 1341.9 | D16: 782.1 | F16: Planterware | G16: 1341.9 | H16: 2124
B17: Self-Watering | C17: 8787.1 | D17: 19327.9 | F17: Self-Watering | G17: 8787.1 | H17: 28115
B18: Grand Total | C18: 11394.6 | D18: 22788.4
F19: Product Family | G19: Sum of Cost | H19: Sum of Profit Margin
F20: Bins | G20: 1265.6 | H20: 2678.4
F21: Planterware | G21: 1341.9 | H21: 782.1
F22: Self-Watering | G22: 8787.1 | H22: 19327.9
F23: Grand Total | G23: 11394.6 | H23: 22788.4

Sheet Powder Cost
A2: Colour | B2: Sum of Cost
A3: Light Sandstone | B3: 3.2 | Q3: Powder Cost
A4: Pink Granite | B4: 3.2 | Q4: 3.2 | R4: Light Sandstone | S4: Pink Granite | T4: Millstone Gritt | U4: Dark Standstone | V4: White Marble | W4: Guernsey Granite | X4: Moss Stone
A5: Millstone Gritt | B5: 3.2 | Q5: 3 | R5: Terracotta | S5: Sky Blue | T5: White | U5: Biscuit | V5: Standard Green | W5: Navy Blue | X5: Tudor Brown Mottle | Y5: Orange | Z5: Light Green | AA5: Cherry | AB5: Brown
A6: Dark Standstone | B6: 3.2 | Q6: 2.8 | R6: Black
A7: White Marble | B7: 3.2
A8: Guernsey Granite | B8: 3.2
A9: Moss Stone | B9: 3.2
A10: Terracotta | B10: 3
A11: Sky Blue | B11: 3
A12: White | B12: 3
A13: Biscuit | B13: 3 | O13: Color | P13: Cost
A14: Standard Green | B14: 3 | O14: Light Sandstone | P14: 3.2
A15: Navy Blue | B15: 3 | O15: Pink Granite | P15: 3.2
A16: Tudor Brown Mottle | B16: 3 | O16: Millstone Gritt | P16: 3.2
A17: Orange | B17: 3 | O17: Dark Standstone | P17: 3.2
A18: Light Green | B18: 3 | O18: White Marble | P18: 3.2
A19: Cherry | B19: 3 | O19: Guernsey Granite | P19: 3.2
A20: Brown | B20: 3 | O20: Moss Stone | P20: 3.2
A21: Black | B21: 2.8 | O21: Terracotta | P21: 3
A22: Grand Total | B22: 58.2 | O22: Sky Blue | P22: 3
O23: White | P23: 3
O24: Biscuit | P24: 3
O25: Standard Green | P25: 3
O26: Navy Blue | P26: 3
O27: Tudor Brown Mottle | P27: 3
O28: Orange | P28: 3
O29: Light Green | P29: 3
O30: Cherry | P30: 3
O31: Brown | P31: 3
O32: Black | P32: 2.8

Sheet Demand Distribution
A1: Typical Demand Distribution %
A2: Month | B2: Demand of Planters | C2: Demand of Bins
A3: Jan | B3: 3 | C3: 10
A4: Feb | B4: 8 | C4: 11
A5: Mac | B5: 13 | C5: 8
A6: April | B6: 18 | C6: 4
A7: May | B7: 18 | C7: 2
A8: June | B8: 15 | C8: 3
A9: July | B9: 10 | C9: 7
A10: August | B10: 8 | C10: 7
A11: Sept | B11: 3 | C11: 8
A12: Oct | B12: 2 | C12: 13
A13: Nov | B13: 1 | C13: 15
A14: Dec | B14: 1 | C14: 12
A15: TOTAL | B15: =SUM(B3:B14) -> 100 | C15: =SUM(C3:C14) -> 100

Sheet Suggestion3
A2: Description | B2: Sum of Profitin_2011 | C2: Sum of Profitin_2006 | D2: Sum of Profitin_2007 | E2: Sum of Profitin_2008 | F2: Sum of Profitin_2009 | G2: Sum of Profitin_2010 | H2: Sum of Profitin_2012
A3: Half basket up the pole | B3: 170513.6 | C3: 188741.2 | D3: 196483.6 | E3: 177795 | F3: 199409.4 | G3: 146967.2 | H3: 228391
A4: Olympic dual bin | B4: 147956 | C4: 0 | D4: 0 | E4: 0 | F4: 8450 | G4: 322452 | H4: 168750
A5: Bee hive fountain (6) | B5: 89361 | C5: 0 | D5: 0 | E5: 0 | F5: 0 | G5: 191336 | H5: -621554
A6: Cup and Saucer on pole | B6: 77984.6 | C6: 128499.4 | D6: 137522.2 | E6: 140023.6 | F6: 106223.4 | G6: 88856.6 | H6: 132743
A7: Bee hive fountain (5) | B7: 54661 | C7: 43639 | D7: 44310 | E7: 22251 | F7: 12541 | G7: 19884 | H7: -268065
A8: Floural fountain | B8: 40537 | C8: 5187 | D8: 17784 | E8: 62985 | F8: 53105 | G8: 20007 | H8: -93718
A9: Octagonal fountain | B9: 40030 | C9: 31436 | D9: 41731 | E9: 22997 | F9: 33060 | G9: 27579 | H9: -15160
A10: Cup and Saucer | B10: 37131.8 | C10: 26332.8 | D10: 23400 | E10: 23940.8 | F10: 18460 | G10: 28204.8 | H10: 67332
A11: Cup and Saucer (HB) | B11: 36524 | C11: 52774 | D11: 60442 | E11: 63613 | F11: 56150 | G11: 50290 | H11: 77455
A12: Barrier Basket Liner | B12: 30380.8 | C12: 32566.6 | D12: 35580.2 | E12: 29174.8 | F12: 40331.2 | G12: 26857.1 | H12: 61737.5
A13: Meter sq planter | B13: 25672 | C13: 1998 | D13: 6734 | E13: 7659 | F13: 9287 | G13: 11803 | H13: -56250
A14: Half pole basket | B14: 25668.7 | C14: 27054.4 | D14: 31860.1 | E14: 22110.7 | F14: 19962.6 | G14: 20166.8 | H14: 50005.1
... A62: Grand Total | B62: 1068083.3 | C62: 943793.2 | D62: 1028316.8 | E62: 982504.6 | F62: 836814 | G62: 1246212.9 | H62: -1689588

Sheet Forecast
A1: Product | B1: Description | C1: Colour | D1: Salesin_2012 | E1: Salesin_2011 | F1: Salesin_2010 | G1: Salesin_2009 | H1: Salesin_2008 | I1: Salesin_2007 | J1: Salesin_2006
A2: MSP 1P | B2: Meter sq planter (1) | C2: Black | D2: 0 | E2: 1 | F2: 0 | G2: 1 | H2: 38 | I2: 0 | J2: 0 | M2: Years | N2: Total Sales
A3: MSP 4P | B3: Meter sq planter (4) | C3: Black | D3: 0 | E3: 0 | F3: 0 | G3: 0 | H3: 12 | I3: 0 | J3: 0 | M3: 2006 | N3: 24122
A4: OCT 2P | B4: Octagonal fountain (2) | C4: Black | D4: 0 | E4: 0 | F4: 0 | G4: 1 | H4: 0 | I4: 0 | J4: 0 | M4: =M3+1 -> 2007 | N4: 25891
A5: J-C41 | B5: Cylinder | C5: Black | D5: 0 | E5: 0 | F5: 0 | G5: 0 | H5: 0 | I5: 0 | J5: 0 | M5: =M4+1 -> 2008 | N5: 24809
A6: J-C45-T3 | B6: Cylinder | C6: Black | D6: 0 | E6: 0 | F6: 0 | G6: 0 | H6: 0 | I6: 0 | J6: 0 | M6: =M5+1 -> 2009 | N6: 23226
A7: UTP 1P | B7: Half basket up the pole | C7: Cherry | D7: 0 | E7: 5 | F7: 0 | G7: 0 | H7: 0 | I7: 0 | J7: 0 | M7: =M6+1 -> 2010 | N7: 22470
A8: UTP 2PL | B8: Half pole basket | C8: Cherry | D8: 0 | E8: 13 | F8: 0 | G8: 0 | H8: 0 | I8: 0 | J8: 0 | M8: =M7+1 -> 2011 | N8: 24843
A9: CHB 2P | B9: Conventional Hanging Basket | C9: Cherry | D9: 0 | E9: 5 | F9: 0 | G9: 0 | H9: 0 | I9: 0 | J9: 0 | M9: =M8+1 -> 2012 | N9: 29941
A10: CUH 2P | B10: Up the pole basket | C10: Cherry | D10: 0 | E10: 3 | F10: 0 | G10: 0 | H10: 0 | I10: 0 | J10: 0
A11: WBX 0P | B11: Wall and window box | C11: Cherry | D11: 0 | E11: 3 | F11: 0 | G11: 0 | H11: 0 | I11: 0 | J11: 0
A12: MSP 1P | B12: Meter sq planter (1) | C12: Cherry | D12: 0 | E12: 5 | F12: 0 | G12: 0 | H12: 0 | I12: 0 | J12: 0
A13: OCT 1P | B13: Octagonal fountain (1) | C13: Guerney Granite | D13: 0 | E13: 1 | F13: 0 | G13: 0 | H13: 0 | I13: 0 | J13: 0
A14: MSP 1P | B14: Meter sq planter (1) | C14: Light Sandstone | D14: 0 | E14: 5 | F14: 0 | G14: 0 | H14: 0 | I14: 0 | J14: 0 | M14: Years | N14: Annual Total Profit
A15: MSP 2P | B15: Meter sq planter (2) | C15: Light Sandstone | D15: 0 | E15: 1 | F15: 0 | G15: 0 | H15: 0 | I15: 0 | J15: 0 | M15: 2006 | N15: 943783
A16: OCT 2P | B16: Octagonal fountain (2) | C16: Light Sandstone | D16: 0 | E16: 1 | F16: 0 | G16: 0 | H16: 0 | I16: 0 | J16: 0 | M16: =M15+1 -> 2007 | N16: 1028317
A17: OCT 3P | B17: Octagonal fountain (3) | C17: Light Sandstone | D17: 0 | E17: 1 | F17: 0 | G17: 0 | H17: 0 | I17: 0 | J17: 0 | M17: =M16+1 -> 2008 | N17: 982505
A18: J-C45-T4 | B18: Cylinder | C18: Light Sandstone | D18: 0 | E18: 0 | F18: 0 | G18: 0 | H18: 0 | I18: 0 | J18: 0 | M18: =M17+1 -> 2009 | N18: 836814
A19: J-EPS40-DG | B19: Egg pot square | C19: Light Sandstone | D19: 0 | E19: 0 | F19: 0 | G19: 0 | H19: 0 | I19: 0 | J19: 0 | M19: =M18+1 -> 2010 | N19: 1246213
A20: BHV 6P | B20: Bee hive fountain (6) | C20: Moss Stone | D20: 0 | E20: 5 | F20: 0 | G20: 0 | H20: 0 | I20: 0 | J20: 0 | M20: =M19+1 -> 2011 | N20: 1068083
A21: UTP 1P | B21: Half basket up the pole | C21: Orange | D21: 0 | E21: 5 | F21: 0 | G21: 0 | H21: 0 | I21: 0 | J21: 0 | M21: =M20+1 -> 2012 | N21: 1475767
A22: MSP 0P | B22: Meter sq planter | C22: Pink Granite | D22: 0 | E22: 89 | F22: 0 | G22: 0 | H22: 0 | I22: 0 | J22: 0
A23: MSP 1P | B23: Meter sq planter (1) | C23: Pink Granite | D23: 0 | E23: 5 | F23: 0 | G23: 0 | H23: 0 | I23: 0 | J23: 0
A24: MSP 1P | B24: Meter sq planter (1) | C24: Sky Blue | D24: 0 | E24: 5 | F24: 0 | G24: 0 | H24: 0 | I24: 0 | J24: 0
A25: CUH 1P | B25: up the pole basket | C25: Cherry | D25: 1 | E25: 0 | F25: 0 | G25: 0 | H25: 0 | I25: 0 | J25: 0
A26: CHB 2P | B26: Conventional Hanging Basket | C26: Orange | D26: 1 | E26: 0 | F26: 0 | G26: 0 | H26: 0 | I26: 0 | J26: 0
A27: OCT 2P | B27: Octagonal fountain (2) | C27: Pink Granite | D27: 1 | E27: 0 | F27: 0 | G27: 0 | H27: 0 | I27: 0 | J27: 0
A28: OCT 3P | B28: Octagonal fountain (3) | C28: Pink Granite | D28: 1 | E28: 0 | F28: 0 | G28: 0 | H28: 0 | I28: 0 | J28: 0
A29: CUH 1P | B29: up the pole basket | C29: Sky Blue | D29: 1 | E29: 0 | F29: 0 | G29: 0 | H29: 0 | I29: 0 | J29: 0
A30: OCT 1P | B30: Octagonal fountain (1) | C30: Sky Blue | D30: 1 | E30: 0 | F30: 0 | G30: 0 | H30: 0 | I30: 0 | J30: 0
A31: MSP 1P | B31: Meter sq planter (1) | C31: Standard Green | D31: 1 | E31: 0 | F31: 0 | G31: 0 | H31: 0 | I31: 0 | J31: 0
A32: OCT 2P | B32: Octagonal fountain (2) | C32: Standard Green | D32: 1 | E32: 0 | F32: 0 | G32: 0 | H32: 0 | I32: 0 | J32: 0
A33: MSP 2P | B33: Meter sq planter (2) | C33: Black | D33: 2 | E33: 34 | F33: 36 | G33: 2 | H33: 0 | I33: 0 | J33: 0
... A203: CAS 0P | B203: Cup and Saucer | C203: Black | D203: 2132 | E203: 2648 | F203: 2712 | G203: 1775 | H203: 2302 | I203: 2250 | J203: 2532

Sheet AnnualPDashBoard
K2: Years | L2: Profit
A3: 2012 | B3: 2011 | C3: 2010 | D3: 2009 | E3: 2008 | F3: 2007 | G3: 2006 | K3: 2006 | L3: =G19 -> 943793.2
A4: 596474.6 | B4: 652631.6 | C4: 888836.4 | D4: 676723 | E4: 709490.6 | F4: 519258.8 | G4: 491717.2 | K4: =K3+1 -> 2007 | L4: =F19 -> 1028316.8
A5: 550299 | B5: 345693 | C5: 337576 | D5: 159923 | E5: 271310 | F5: 508362 | G5: 451332 | K5: =K4+1 -> 2008 | L5: =E19 -> 982504.6
A6: 119738.2 | B6: 42071.2 | C6: 288 | D6: 168 | E6: 1704 | F6: 696 | G6: 744 | K6: =K5+1 -> 2009 | L6: =D19 -> 836814
A7: 100747.5 | B7: -12815.5 | C7: 19512.5 | D7: 0 | E7: 0 | F7: 0 | G7: 0 | K7: =K6+1 -> 2010 | L7: =C19 -> 1246212.9
A8: 73349 | B8: 13919 | C8: 0 | D8: 0 | E8: 0 | F8: 0 | G8: 0 | K8: =K7+1 -> 2011 | L8: =B19 -> 1068083.3
A9: 14880 | B9: 19455 | C9: 0 | D9: 0 | E9: 0 | F9: 0 | G9: 0 | K9: =K8+1 -> 2012 | L9: =A19 -> 1475767.3
A10: 4452 | B10: 2342 | C10: 0 | D10: 0 | E10: 0 | F10: 0 | G10: 0
A11: 4369 | B11: -385 | C11: 0 | D11: 0 | E11: 0 | F11: 0 | G11: 0
A12: 3588 | B12: 338 | C12: 0 | D12: 0 | E12: 0 | F12: 0 | G12: 0
A13: 3090.5 | B13: -499.5 | C13: 0 | D13: 0 | E13: 0 | F13: 0 | G13: 0
A14: 2204.5 | B14: 1339.5 | C14: 0 | D14: 0 | E14: 0 | F14: 0 | G14: 0
A15: 2070 | B15: 320 | C15: 0 | D15: 0 | E15: 0 | F15: 0 | G15: 0
A16: 340 | B16: -560 | C16: 0 | D16: 0 | E16: 0 | F16: 0 | G16: 0
A17: 165 | B17: 734 | C17: 0 | D17: 0 | E17: 0 | F17: 0 | G17: 0
A18: 0 | B18: 3500 | C18: 0 | D18: 0 | E18: 0 | F18: 0 | G18: 0
A19: 1475767.3 | B19: 1068083.3 | C19: 1246212.9 | D19: 836814 | E19: 982504.6 | F19: 1028316.8 | G19: =SUM(G4:G18) -> 943793.2

Sheet Profit ForeCast
A1: Years | B1: Annual Total Profit | C1: Forecast(Annual Total Profit ) | D1: Confidence Interval(Annual Total Profit ) | G1: Statistic | H1: Value
A2: 2006 | B2: 943783 | G2: Alpha | H2: =_xlfn.FORECAST.ETS.STAT($B$2:$B$8,$A$2:$A$8,1,1,1) -> 0.002
A3: 2007 | B3: 1028317 | G3: Beta | H3: =_xlfn.FORECAST.ETS.STAT($B$2:$B$8,$A$2:$A$8,2,1,1) -> 0.001
A4: 2008 | B4: 982505 | G4: Gamma | H4: =_xlfn.FORECAST.ETS.STAT($B$2:$B$8,$A$2:$A$8,3,1,1) -> 2.220446e-16
A5: 2009 | B5: 836814 | G5: MASE | H5: =_xlfn.FORECAST.ETS.STAT($B$2:$B$8,$A$2:$A$8,4,1,1) -> 0.53653308
A6: 2010 | B6: 1246213 | G6: SMAPE | H6: =_xlfn.FORECAST.ETS.STAT($B$2:$B$8,$A$2:$A$8,5,1,1) -> 0.10297149
A7: 2011 | B7: 1068083 | G7: MAE | H7: =_xlfn.FORECAST.ETS.STAT($B$2:$B$8,$A$2:$A$8,6,1,1) -> 113677.95
A8: 2012 | B8: 1475767 | G8: RMSE | H8: =_xlfn.FORECAST.ETS.STAT($B$2:$B$8,$A$2:$A$8,7,1,1) -> 157014.34
A9: 2013 | C9: =_xlfn.FORECAST.ETS(A9,$B$2:$B$8,$A$2:$A$8,1,1) -> 1425726.3 | D9: =_xlfn.FORECAST.ETS.CONFINT(A9,$B$2:$B$8,$A$2:$A$8,0.95,1,1) -> 307742.45
A10: 2014 | C10: =_xlfn.FORECAST.ETS(A10,$B$2:$B$8,$A$2:$A$8,1,1) -> 1494509.4 | D10: =_xlfn.FORECAST.ETS.CONFINT(A10,$B$2:$B$8,$A$2:$A$8,0.95,1,1) -> 307743.83
A11: 2015 | C11: =_xlfn.FORECAST.ETS(A11,$B$2:$B$8,$A$2:$A$8,1,1) -> 1563292.5 | D11: =_xlfn.FORECAST.ETS.CONFINT(A11,$B$2:$B$8,$A$2:$A$8,0.95,1,1) -> 307746.29
A12: 2016 | C12: =_xlfn.FORECAST.ETS(A12,$B$2:$B$8,$A$2:$A$8,1,1) -> 1632075.7 | D12: =_xlfn.FORECAST.ETS.CONFINT(A12,$B$2:$B$8,$A$2:$A$8,0.95,1,1) -> 307750.14

Sheet ForecastDashboard2
A1: Years | B1: Total Sales | C1: Forecast(Total Sales) | D1: Lower Confidence Bound(Total Sales) | E1: Upper Confidence Bound(Total Sales)
A2: 2006 | B2: 24122
A3: 2007 | B3: 25891
A4: 2008 | B4: 24809
A5: 2009 | B5: 23226
A6: 2010 | B6: 22470
A7: 2011 | B7: 24843
A8: 2012 | B8: 29941 | C8: 29941 | D8: 29941 | E8: 29941
A9: 2013 | C9: =_xlfn.FORECAST.ETS(A9,$B$2:$B$8,$A$2:$A$8,1,1) -> 30406.071 | D9: =C9-_xlfn.FORECAST.ETS.CONFINT(A9,$B$2:$B$8,$A$2:$A$8,0.95,1,1) -> 26356.873 | E9: =C9+_xlfn.FORECAST.ETS.CONFINT(A9,$B$2:$B$8,$A$2:$A$8,0.95,1,1) -> 34455.27
A10: 2014 | C10: =_xlfn.FORECAST.ETS(A10,$B$2:$B$8,$A$2:$A$8,1,1) -> 30871.143 | D10: =C10-_xlfn.FORECAST.ETS.CONFINT(A10,$B$2:$B$8,$A$2:$A$8,0.95,1,1) -> 25147.574 | E10: =C10+_xlfn.FORECAST.ETS.CONFINT(A10,$B$2:$B$8,$A$2:$A$8,0.95,1,1) -> 36594.711
A11: 2015 | C11: =_xlfn.FORECAST.ETS(A11,$B$2:$B$8,$A$2:$A$8,1,1) -> 31336.214 | D11: =C11-_xlfn.FORECAST.ETS.CONFINT(A11,$B$2:$B$8,$A$2:$A$8,0.95,1,1) -> 24325.134 | E11: =C11+_xlfn.FORECAST.ETS.CONFINT(A11,$B$2:$B$8,$A$2:$A$8,0.95,1,1) -> 38347.294
A12: 2016 | C12: =_xlfn.FORECAST.ETS(A12,$B$2:$B$8,$A$2:$A$8,1,1) -> 31801.286 | D12: =C12-_xlfn.FORECAST.ETS.CONFINT(A12,$B$2:$B$8,$A$2:$A$8,0.95,1,1) -> 23702.887 | E12: =C12+_xlfn.FORECAST.ETS.CONFINT(A12,$B$2:$B$8,$A$2:$A$8,0.95,1,1) -> 39899.684
A41: Years | B41: Annual Total Profit | C41: Forecast(Annual Total Profit ) | D41: Confidence Interval(Annual Total Profit )
A42: 2006 | B42: 943783
A43: 2007 | B43: 1028317
A44: 2008 | B44: 982505
A45: 2009 | B45: 836814
A46: 2010 | B46: 1246213
A47: 2011 | B47: 1068083
A48: 2012 | B48: 1475767
A49: 2013 | C49: =_xlfn.FORECAST.ETS(A49,$B$2:$B$8,$A$2:$A$8,1,1) -> 30406.071 | D49: =_xlfn.FORECAST.ETS.CONFINT(A49,$B$2:$B$8,$A$2:$A$8,0.95,1,1) -> 4049.1982
A50: 2014 | C50: =_xlfn.FORECAST.ETS(A50,$B$2:$B$8,$A$2:$A$8,1,1) -> 30871.143 | D50: =_xlfn.FORECAST.ETS.CONFINT(A50,$B$2:$B$8,$A$2:$A$8,0.95,1,1) -> 5723.5685
A51: 2015 | C51: =_xlfn.FORECAST.ETS(A51,$B$2:$B$8,$A$2:$A$8,1,1) -> 31336.214 | D51: =_xlfn.FORECAST.ETS.CONFINT(A51,$B$2:$B$8,$A$2:$A$8,0.95,1,1) -> 7011.08
A52: 2016 | C52: =_xlfn.FORECAST.ETS(A52,$B$2:$B$8,$A$2:$A$8,1,1) -> 31801.286 | D52: =_xlfn.FORECAST.ETS.CONFINT(A52,$B$2:$B$8,$A$2:$A$8,0.95,1,1) -> 8098.3985
A54: Statistic | B54: Value
A55: Alpha | B55: =_xlfn.FORECAST.ETS.STAT($B$2:$B$8,$A$2:$A$8,1,1,1) -> 0.998
A56: Beta | B56: =_xlfn.FORECAST.ETS.STAT($B$2:$B$8,$A$2:$A$8,2,1,1) -> 0.001
A57: Gamma | B57: =_xlfn.FORECAST.ETS.STAT($B$2:$B$8,$A$2:$A$8,3,1,1) -> 2.220446e-16
A58: MASE | B58: =_xlfn.FORECAST.ETS.STAT($B$2:$B$8,$A$2:$A$8,4,1,1) -> 0.80005244
A59: SMAPE | B59: =_xlfn.FORECAST.ETS.STAT($B$2:$B$8,$A$2:$A$8,5,1,1) -> 0.066885962
A60: MAE | B60: =_xlfn.FORECAST.ETS.STAT($B$2:$B$8,$A$2:$A$8,6,1,1) -> 1688.244
A61: RMSE | B61: =_xlfn.FORECAST.ETS.STAT($B$2:$B$8,$A$2:$A$8,7,1,1) -> 2065.9554

Sheet MovingAverage
A1: Year | B1: Total Profit | C1: Total Sales | E1: #N/A | F1: #N/A
A2: 2006 | B2: 943793 | C2: 24122 | E2: =AVERAGE(B2:B3) -> 986055 | F2: #N/A
A3: 2007 | B3: 1028317 | C3: 25891 | E3: =AVERAGE(B3:B4) -> 1005411 | F3: =SQRT(SUMXMY2(B3:B4,E2:E3)/2) -> 33990.892
A4: 2008 | B4: 982505 | C4: 24809 | E4: =AVERAGE(B4:B5) -> 909659.5 | F4: =SQRT(SUMXMY2(B4:B5,E3:E4)/2) -> 53996.073
A5: 2009 | B5: 836814 | C5: 23226 | E5: =AVERAGE(B5:B6) -> 1041513.5 | F5: =SQRT(SUMXMY2(B5:B6,E4:E5)/2) -> 153636.51
A6: 2010 | B6: 1246213 | C6: 22470 | E6: =AVERAGE(B6:B7) -> 1157148 | F6: =SQRT(SUMXMY2(B6:B7,E5:E6)/2) -> 157851.92
A7: 2011 | B7: 1068083 | C7: 24843 | E7: =AVERAGE(B7:B8) -> 1271925 | F7: =SQRT(SUMXMY2(B7:B8,E6:E7)/2) -> 157296.11
A8: 2012 | B8: 1475767 | C8: 29941
A11: Year | B11: Total Profit | C11: Total Sales | E11: #N/A | F11: #N/A
A12: 2006 | B12: 943793 | C12: 24122 | E12: =AVERAGE(C2:C3) -> 25006.5 | F12: #N/A
A13: 2007 | B13: 1028317 | C13: 25891 | E13: =AVERAGE(C3:C4) -> 25350 | F13: =SQRT(SUMXMY2(C3:C4,E12:E13)/2) -> 733.15116
A14: 2008 | B14: 982505 | C14: 24809 | E14: =AVERAGE(C4:C5) -> 24017.5 | F14: =SQRT(SUMXMY2(C4:C5,E13:E14)/2) -> 677.92081
A15: 2009 | B15: 836814 | C15: 23226 | E15: =AVERAGE(C5:C6) -> 22848 | F15: =SQRT(SUMXMY2(C5:C6,E14:E15)/2) -> 620.22425
A16: 2010 | B16: 1246213 | C16: 22470 | E16: =AVERAGE(C6:C7) -> 23656.5 | F16: =SQRT(SUMXMY2(C6:C7,E15:E16)/2) -> 880.53003
A17: 2011 | B17: 1068083 | C17: 24843 | E17: =AVERAGE(C7:C8) -> 27392 | F17: =SQRT(SUMXMY2(C7:C8,E16:E17)/2) -> 1988.1126
A18: 2012 | B18: 1475767 | C18: 29941

Sheet Suggestion5
A2: Month | B2: Sum of Demand of Bins | C2: Sum of Demand of Planters
A3: Nov | B3: 15 | C3: 1
A4: Oct | B4: 13 | C4: 2
A5: Dec | B5: 12 | C5: 1
A6: Feb | B6: 11 | C6: 8
A7: Jan | B7: 10 | C7: 3
A8: Mac | B8: 8 | C8: 13
A9: Sept | B9: 8 | C9: 3
A10: August | B10: 7 | C10: 8
A11: July | B11: 7 | C11: 10
A12: April | B12: 4 | C12: 18
A13: June | B13: 3 | C13: 15
A14: May | B14: 2 | C14: 18
A15: Grand Total | B15: 100 | C15: 100

Sheet Suggestion4
A2: Colour | B2: Sum of Salesin_2006 | C2: Sum of Profitin_2006 | D2: Sum of Salesin_2007 | E2: Sum of Profitin_2007 | F2: Sum of Salesin_2008 | G2: Sum of Profitin_2008 | H2: Sum of Salesin_2009 | I2: Sum of Profitin_2009 | J2: Sum of Salesin_2010 | K2: Sum of Profitin_2010 | L2: Sum of Salesin_2011 | M2: Sum of Profitin_2011 | N2: Sum of Salesin_2012 | O2: Sum of Profitin_2012
A3: Black | B3: 12785 | C3: 491717.2 | D3: 13044 | E3: 519258.8 | F3: 17477 | G3: 709490.6 | H3: 18993 | I3: 676723 | J3: 15655 | K3: 888836.4 | L3: 11774 | M3: 652631.6 | N3: 11510 | O3: 596474.6
A4: Brown | B4: 0 | C4: 0 | D4: 0 | E4: 0 | F4: 0 | G4: 0 | H4: 0 | I4: 0 | J4: 0 | K4: 0 | L4: 557 | M4: 19455 | N4: 496 | O4: 14880
A5: Cherry | B5: 0 | C5: 0 | D5: 0 | E5: 0 | F5: 0 | G5: 0 | H5: 0 | I5: 0 | J5: 0 | K5: 0 | L5: 39 | M5: 1339.5 | N5: 48 | O5: 2204.5
A6: Dark Sandstone | B6: 0 | C6: 0 | D6: 0 | E6: 0 | F6: 0 | G6: 0 | H6: 0 | I6: 0 | J6: 0 | K6: 0 | L6: 13 | M6: 338 | N6: 26 | O6: 3588
A7: Guerney Granite | B7: 0 | C7: 0 | D7: 0 | E7: 0 | F7: 0 | G7: 0 | H7: 0 | I7: 0 | J7: 0 | K7: 0 | L7: 160 | M7: 13919 | N7: 306 | O7: 73349
A8: Light Green | B8: 0 | C8: 0 | D8: 0 | E8: 0 | F8: 0 | G8: 0 | H8: 0 | I8: 0 | J8: 0 | K8: 0 | L8: 15 | M8: -499.5 | N8: 44 | O8: 3090.5
A9: Light Sandstone | B9: 0 | C9: 0 | D9: 0 | E9: 0 | F9: 0 | G9: 0 | H9: 0 | I9: 0 | J9: 0 | K9: 0 | L9: 43 | M9: 2342 | N9: 38 | O9: 4452
A10: Millstone Gritt | B10: 0 | C10: 0 | D10: 0 | E10: 0 | F10: 0 | G10: 0 | H10: 0 | I10: 0 | J10: 0 | K10: 0 | L10: 8 | M10: 320 | N10: 15 | O10: 2070
A11: Moss Stone | B11: 0 | C11: 0 | D11: 0 | E11: 0 | F11: 0 | G11: 0 | H11: 0 | I11: 0 | J11: 0 | K11: 0 | L11: 5 | M11: 3500 | N11: 0 | O11: 0
A12: Orange | B12: 0 | C12: 0 | D12: 0 | E12: 0 | F12: 0 | G12: 0 | H12: 0 | I12: 0 | J12: 0 | K12: 0 | L12: 20 | M12: 734 | N12: 7 | O12: 165
A13: Pink Granite | B13: 31 | C13: 744 | D13: 29 | E13: 696 | F13: 71 | G13: 1704 | H13: 7 | I13: 168 | J13: 12 | K13: 288 | L13: 476 | M13: 42071.2 | N13: 1063 | O13: 119738.2
A14: Sky Blue | B14: 0 | C14: 0 | D14: 0 | E14: 0 | F14: 0 | G14: 0 | H14: 0 | I14: 0 | J14: 0 | K14: 0 | L14: 56 | M14: -385 | N14: 170 | O14: 4369
... A18: Grand Total | B18: 24122 | C18: 943793.2 | D18: 25891 | E18: 1028316.8 | F18: 24809 | G18: 982504.6 | H18: 23226 | I18: 836814 | J18: 22470 | K18: 1246212.9 | L18: 24843 | M18: 1068083.3 | N18: 29941 | O18: 1475767.3

Sheet Sheet2
A1: Colour | B1: Sum of Salesin_2006 | C1: Sum of Profitin_2006 | D1: Sum of Salesin_2007 | E1: Sum of Profitin_2007 | F1: Sum of Salesin_2008 | G1: Sum of Profitin_2008 | H1: Sum of Salesin_2009 | I1: Sum of Profitin_2009 | J1: Sum of Salesin_2010 | K1: Sum of Profitin_2010 | L1: Sum of Salesin_2011 | M1: Sum of Profitin_2011 | N1: Salesin_2012 | O1: Profitin_2012
A2: Black | B2: 12785 | C2: 491717.2 | D2: 13044 | E2: 519258.8 | F2: 17477 | G2: 709490.6 | H2: 18993 | I2: 676723 | J2: 15655 | K2: 888836.4 | L2: 11774 | M2: 652631.6 | N2: 11510 | O2: 596474.6
A3: Brown | B3: 0 | C3: 0 | D3: 0 | E3: 0 | F3: 0 | G3: 0 | H3: 0 | I3: 0 | J3: 0 | K3: 0 | L3: 557 | M3: 19455 | N3: 496 | O3: 14880
A4: Cherry | B4: 0 | C4: 0 | D4: 0 | E4: 0 | F4: 0 | G4: 0 | H4: 0 | I4: 0 | J4: 0 | K4: 0 | L4: 39 | M4: 1339.5 | N4: 48 | O4: 2204.5
A5: Dark Sandstone | B5: 0 | C5: 0 | D5: 0 | E5: 0 | F5: 0 | G5: 0 | H5: 0 | I5: 0 | J5: 0 | K5: 0 | L5: 13 | M5: 338 | N5: 26 | O5: 3588
A6: Guerney Granite | B6: 0 | C6: 0 | D6: 0 | E6: 0 | F6: 0 | G6: 0 | H6: 0 | I6: 0 | J6: 0 | K6: 0 | L6: 160 | M6: 13919 | N6: 306 | O6: 73349
A7: Light Green | B7: 0 | C7: 0 | D7: 0 | E7: 0 | F7: 0 | G7: 0 | H7: 0 | I7: 0 | J7: 0 | K7: 0 | L7: 15 | M7: -499.5 | N7: 44 | O7: 3090.5
A8: Light Sandstone | B8: 0 | C8: 0 | D8: 0 | E8: 0 | F8: 0 | G8: 0 | H8: 0 | I8: 0 | J8: 0 | K8: 0 | L8: 43 | M8: 2342 | N8: 38 | O8: 4452
A9: Millstone Gritt | B9: 0 | C9: 0 | D9: 0 | E9: 0 | F9: 0 | G9: 0 | H9: 0 | I9: 0 | J9: 0 | K9: 0 | L9: 8 | M9: 320 | N9: 15 | O9: 2070
A10: Moss Stone | B10: 0 | C10: 0 | D10: 0 | E10: 0 | F10: 0 | G10: 0 | H10: 0 | I10: 0 | J10: 0 | K10: 0 | L10: 5 | M10: 3500 | N10: 0 | O10: 0
A11: Orange | B11: 0 | C11: 0 | D11: 0 | E11: 0 | F11: 0 | G11: 0 | H11: 0 | I11: 0 | J11: 0 | K11: 0 | L11: 20 | M11: 734 | N11: 7 | O11: 165
A12: Pink Granite | B12: 31 | C12: 744 | D12: 29 | E12: 696 | F12: 71 | G12: 1704 | H12: 7 | I12: 168 | J12: 12 | K12: 288 | L12: 476 | M12: 42071.2 | N12: 1063 | O12: 119738.2
A13: Sky Blue | B13: 0 | C13: 0 | D13: 0 | E13: 0 | F13: 0 | G13: 0 | H13: 0 | I13: 0 | J13: 0 | K13: 0 | L13: 56 | M13: -385 | N13: 170 | O13: 4369
... A16: White Marble | B16: 0 | C16: 0 | D16: 0 | E16: 0 | F16: 0 | G16: 0 | H16: 0 | I16: 0 | J16: 0 | K16: 0 | L16: 0 | M16: -560 | N16: 5 | O16: 340

Sheet Regression
A1: SUMMARY OUTPUT
A3: Regression Statistics
A4: Multiple R | B4: 0.40047259
A5: R Square | B5: 0.16037829
A6: Adjusted R Square | B6: 0.11373264
A7: Standard Error | B7: 0.84179877
A8: Observations | B8: 96
A10: ANOVA
B11: df | C11: SS | D11: MS | E11: F | F11: Significance F
A12: Regression | B12: 5 | C12: 12.182068 | D12: 2.4364135 | E12: 3.4382261 | F12: 0.0068753738
A13: Residual | B13: 90 | C13: 63.776266 | D13: 0.70862517
A14: Total | B14: 95 | C14: 75.958333
B16: Coefficients | C16: Standard Error | D16: t Stat | E16: P-value | F16: Lower 95% | G16: Upper 95% | H16: Lower 95.0% | I16: Upper 95.0%
A17: Intercept | B17: 0.57431978 | C17: 0.15393007 | D17: 3.7310435 | E17: 0.00033339239 | F17: 0.26851083 | G17: 0.88012873 | H17: 0.26851083 | I17: 0.88012873
A18: Powder_weight_kg | B18: 0.29684118 | C18: 0.097216763 | D18: 3.053395 | E18: 0.0029753343 | F18: 0.10370311 | G18: 0.48997925 | H18: 0.10370311 | I18: 0.48997925
A19: Powder_Cost | B19: -0.099685131 | C19: 0.034556489 | D19: -2.8847008 | E19: 0.0049020998 | F19: -0.16833763 | G19: -0.031032634 | H19: -0.16833763 | I19: -0.031032634
A20: Selling_Price_Pound | B20: -0.0015041307 | C20: 0.0019546328 | D20: -0.76952088 | E20: 0.44359912 | F20: -0.0053873499 | G20: 0.0023790884 | H20: -0.0053873499 | I20: 0.0023790884
A21: Sales_in2012 | B21: -0.00071575799 | C21: 0.00029337953 | D21: -2.4396999 | E21: 0.016660179 | F21: -0.0012986076 | G21: -0.00013290835 | H21: -0.0012986076 | I21: -0.00013290835
A22: Profit_in2012 | B22: 9.3252876e-06 | C22: 5.5381428e-06 | D22: 1.6838294 | E22: 0.09568016 | F22: -1.6771998e-06 | G22: 2.0327775e-05 | H22: -1.6771998e-06 | I22: 2.0327775e-05

Sheet Sheet5
A1: Product | B1: Powder_weight_kg | C1: Powder_Cost | D1: Selling_Price_Pound | E1: Sales_in2012 | F1: Profit_in2012 | G1: Product Family | H1: Due Date Performance | I1: NumProductFamily
A2: MSP 1P | B2: 40 | C2: 112 | D2: 220 | E2: 0 | F2: 0 | G2: Self-Watering | H2: 98 | I2: 0
A3: MSP 4P | B3: 60 | C3: 168 | D3: 579 | E3: 0 | F3: 0 | G3: Self-Watering | H3: 96 | I3: 0
A4: OCT 2P | B4: 47 | C4: 131.6 | D4: 315 | E4: 0 | F4: 0 | G4: Self-Watering | H4: 93 | I4: 0
A5: J-C41 | B5: 14 | C5: 39.2 | D5: 30 | E5: 0 | F5: 0 | G5: Planterware | H5: 93 | I5: =IF(G5="Self Watering", 1, IF(G5="Bins", 2, IF(G5="Planterware", 3, ""))) -> 3
A6: J-C45-T3 | B6: 17 | C6: 47.6 | D6: 38 | E6: 0 | F6: 0 | G6: Planterware | H6: 99 | I6: =IF(G6="Self Watering", 1, IF(G6="Bins", 2, IF(G6="Planterware", 3, ""))) -> 3
A7: MSP 2P | B7: 47 | C7: 131.6 | D7: 340 | E7: 2 | F7: 416.8 | G7: Self-Watering | H7: 92 | I7: 0
A8: OCT 1P | B8: 40 | C8: 112 | D8: 250 | E8: 5 | F8: 690 | G8: Self-Watering | H8: 95 | I8: 0
A9: SCW 0P | B9: 5 | C9: 14 | D9: 100 | E9: 5 | F9: 430 | G9: Bins | H9: 91 | I9: =IF(G9="Self Watering", 1, IF(G9="Bins", 2, IF(G9="Planterware", 3, ""))) -> 2
A10: OCT 3P | B10: 55 | C10: 154 | D10: 450 | E10: 7 | F10: 2072 | G10: Self-Watering | H10: 95 | I10: 0
A11: WBX 0P | B11: 6 | C11: 16.8 | D11: 60 | E11: 10 | F11: 432 | G11: Self-Watering | H11: 98 | I11: 0
A12: POOP 0P | B12: 7 | C12: 19.6 | D12: 120 | E12: 10 | F12: 1004 | G12: Bins | H12: 98 | I12: =IF(G12="Self Watering", 1, IF(G12="Bins", 2, IF(G12="Planterware", 3, ""))) -> 2
A13: PAR 1P | B13: 30 | C13: 84 | D13: 280 | E13: 12 | F13: 2352 | G13: Bins | H13: 93 | I13: =IF(G13="Self Watering", 1, IF(G13="Bins", 2, IF(G13="Planterware", 3, ""))) -> 2
A14: HBB 3P | B14: 10 | C14: 28 | D14: 130 | E14: 15 | F14: 1530 | G14: Self-Watering | H14: 94 | I14: 0
A15: HBB 3PL | B15: 5.5 | C15: 15.4 | D15: 75 | E15: 15 | F15: 894 | G15: Self-Watering | H15: 97 | I15: 0
A16: ROB 1P | B16: 30 | C16: 84 | D16: 250 | E16: 15 | F16: 2490 | G16: Bins | H16: 96 | I16: =IF(G16="Self Watering", 1, IF(G16="Bins", 2, IF(G16="Planterware", 3, ""))) -> 2
A17: CHK 1P | B17: 30 | C17: 84 | D17: 250 | E17: 15 | F17: 2490 | G17: Bins | H17: 90 | I17: =IF(G17="Self Watering", 1, IF(G17="Bins", 2, IF(G17="Planterware", 3, ""))) -> 2
A18: TAR 1P | B18: 35 | C18: 98 | D18: 300 | E18: 19 | F18: 3838 | G18: Bins | H18: 97 | I18: =IF(G18="Self Watering", 1, IF(G18="Bins", 2, IF(G18="Planterware", 3, ""))) -> 2
A19: ECO 1P | B19: 30 | C19: 84 | D19: 200 | E19: 20 | F19: 2320 | G19: Bins | H19: 91 | I19: =IF(G19="Self Watering", 1, IF(G19="Bins", 2, IF(G19="Planterware", 3, ""))) -> 2
A20: AMB 1P | B20: 45 | C20: 126 | D20: 300 | E20: 23 | F20: 4002 | G20: Bins | H20: 98 | I20: =IF(G20="Self Watering", 1, IF(G20="Bins", 2, IF(G20="Planterware", 3, ""))) -> 2
A21: RCY 1P | B21: 30 | C21: 84 | D21: 300 | E21: 25 | F21: 5400 | G21: Bins | H21: 98 | I21: =IF(G21="Self Watering", 1, IF(G21="Bins", 2, IF(G21="Planterware", 3, ""))) -> 2
A22: CUH 2P | B22: 7 | C22: 19.6 | D22: 69 | E22: 32 | F22: 1580.8 | G22: Self-Watering | H22: 94 | I22: 0
A23: ENV 0P | B23: 30 | C23: 84 | D23: 280 | E23: 35 | F23: 6860 | G23: Bins | H23: 92 | I23: =IF(G23="Self Watering", 1, IF(G23="Bins", 2, IF(G23="Planterware", 3, ""))) -> 2
A24: MSP 3P | B24: 55 | C24: 154 | D24: 375 | E24: 36 | F24: 7956 | G24: Self-Watering | H24: 92 | I24: 0
A25: CUH 1P | B25: 5 | C25: 14 | D25: 39 | E25: 36 | F25: 900 | G25: Self-Watering | H25: 94 | I25: 0
A26: WBX 3P | B26: 10 | C26: 28 | D26: 130 | E26: 38 | F26: 3876 | G26: Self-Watering | H26: 97 | I26: 0
A27: SQD 0P | B27: 25 | C27: 70 | D27: 180 | E27: 40 | F27: 4400 | G27: Bins | H27: 91 | I27: =IF(G27="Self Watering", 1, IF(G27="Bins", 2, IF(G27="Planterware", 3, ""))) -> 2
A28: FF 2P | B28: 40 | C28: 112 | D28: 359 | E28: 41 | F28: 10127 | G28: Self-Watering | H28: 93 | I28: 0
A29: HBB 2PL | B29: 4.5 | C29: 12.6 | D29: 40 | E29: 41 | F29: 1123.4 | G29: Self-Watering | H29: 97 | I29: 0
A30: WBX 3PL | B30: 5.5 | C30: 15.4 | D30: 75 | E30: 45 | F30: 2682 | G30: Self-Watering | H30: 91 | I30: 0
A31: ACT 1P | B31: 8 | C31: 22.4 | D31: 125 | E31: 45 | F31: 4617 | G31: Bins | H31: 100 | I31: =IF(G31="Self Watering", 1, IF(G31="Bins", 2, IF(G31="Planterware", 3, ""))) -> 2
A32: BHV 6P | B32: 65 | C32: 182 | D32: 584 | E32: 51 | F32: 20502 | G32: Self-Watering | H32: 94 | I32: 0
A33: BHV 5P | B33: 55 | C33: 154 | D33: 530 | E33: 58 | F33: 21808 | G33: Self-Watering | H33: 100 | I33: 0
A34: HBB 1P | B34: 8 | C34: 22.4 | D34: 65 | E34: 60 | F34: 2556 | G34: Self-Watering | H34: 99 | I34: 0
A35: CHB 2P | B35: 5 | C35: 14 | D35: 56 | E35: 61 | F35: 2562 | G35: Self-Watering | H35: 96 | I35: 0
A36: WBX 1PL | B36: 3.5 | C36: 9.8 | D36: 35 | E36: 62 | F36: 1562.4 | G36: Self-Watering | H36: 100 | I36: 0
A37: SLM 0P | B37: 25 | C37: 70 | D37: 99 | E37: 65 | F37: 1885 | G37: Bins | H37: 93 | I37: =IF(G37="Self Watering", 1, IF(G37="Bins", 2, IF(G37="Planterware", 3, ""))) -> 2
A38: PEN 1P | B38: 30 | C38: 84 | D38: 250 | E38: 70 | F38: 11620 | G38: Bins | H38: 90 | I38: =IF(G38="Self Watering", 1, IF(G38="Bins", 2, IF(G38="Planterware", 3, ""))) -> 2
A39: HBB 2P | B39: 9 | C39: 25.2 | D39: 45 | E39: 80 | F39: 1584 | G39: Self-Watering | H39: 97 | I39: 0
A40: SCW TP | B40: 6 | C40: 16.8 | D40: 130 | E40: 85 | F40: 9622 | G40: Bins | H40: 92 | I40: =IF(G40="Self Watering", 1, IF(G40="Bins", 2, IF(G40="Planterware", 3, ""))) -> 2
A41: BBU 0P | B41: 7.5 | C41: 21 | D41: 58 | E41: 94 | F41: 3478 | G41: Self-Watering | H41: 99 | I41: 0
A42: OCT 0P | B42: 35 | C42: 98 | D42: 185 | E42: 112 | F42: 9744 | G42: Self-Watering | H42: 97 | I42: 0
A43: MSP 0P | B43: 35 | C43: 98 | D43: 135 | E43: 116 | F43: 4292 | G43: Self-Watering | H43: 96 | I43: 0
A44: HBB 1PL | B44: 3.5 | C44: 9.8 | D44: 35 | E44: 124 | F44: 3124.8 | G44: Self-Watering | H44: 97 | I44: 0
A45: WBX 1P | B45: 8 | C45: 22.4 | D45: 65 | E45: 163 | F45: 6943.8 | G45: Self-Watering | H45: 91 | I45: 0
A46: ST 1P | B46: 10 | C46: 28 | D46: 55 | E46: 200 | F46: 5400 | G46: Bins | H46: 96 | I46: =IF(G46="Self Watering", 1, IF(G46="Bins", 2, IF(G46="Planterware", 3, ""))) -> 2
A47: AMP 1P | B47: 20 | C47: 56 | D47: 150 | E47: 230 | F47: 21620 | G47: Bins | H47: 97 | I47: =IF(G47="Self Watering", 1, IF(G47="Bins", 2, IF(G47="Planterware", 3, ""))) -> 2
A48: CNS 1PL | B48: 5 | C48: 14 | D48: 85 | E48: 268 | F48: 19028 | G48: Self-Watering | H48: 93 | I48: 0
A49: UTP 2PL | B49: 3.5 | C49: 9.8 | D49: 28 | E49: 299 | F49: 5441.8 | G49: Self-Watering | H49: 99 | I49: 0
A50: WLB 1P | B50: 12 | C50: 33.6 | D50: 75 | E50: 315 | F50: 13041 | G50: Bins | H50: 96 | I50: =IF(G50="Self Watering", 1, IF(G50="Bins", 2, IF(G50="Planterware", 3, ""))) -> 2
A51: WLB 1PL | B51: 4 | C51: 11.2 | D51: 50 | E51: 332 | F51: 12881.6 | G51: Bins | H51: 94 | I51: =IF(G51="Self Watering", 1, IF(G51="Bins", 2, IF(G51="Planterware", 3, ""))) -> 2
A52: UTP 1PL | B52: 3.5 | C52: 9.8 | D52: 25 | E52: 382 | F52: 5806.4 | G52: Self-Watering | H52: 97 | I52: 0
A53: BBU 1P | B53: 6 | C53: 16.8 | D53: 40 | E53: 405 | F53: 9396 | G53: Self-Watering | H53: 92 | I53: 0
A54: OLY 1P | B54: 40 | C54: 112 | D54: 450 | E54: 487 | F54: 164606 | G54: Bins | H54: 90 | I54: =IF(G54="Self Watering", 1, IF(G54="Bins", 2, IF(G54="Planterware", 3, ""))) -> 2
A55: CHB 1P | B55: 5 | C55: 14 | D55: 35 | E55: 527 | F55: 11067 | G55: Self-Watering | H55: 91 | I55: 0
A56: BBU 1PL | B56: 3.5 | C56: 9.8 | D56: 25 | E56: 604 | F56: 9180.8 | G56: Self-Watering | H56: 99 | I56: 0
A57: UTP 2P | B57: 5 | C57: 14 | D57: 65 | E57: 728 | F57: 37128 | G57: Self-Watering | H57: 93 | I57: 0
A58: CAS 1P | B58: 5 | C58: 14 | D58: 45 | E58: 787 | F58: 24397 | G58: Self-Watering | H58: 97 | I58: 0
A59: UTP 1P | B59: 4 | C59: 11.2 | D59: 45 | E59: 962 | F59: 32515.6 | G59: Self-Watering | H59: 100 | I59: 0
A60: CNS 1P | B60: 7 | C60: 19.6 | D60: 45 | E60: 1064 | F60: 27025.6 | G60: Self-Watering | H60: 94 | I60: 0
A61: CAS 0P | B61: 7 | C61: 19.6 | D61: 30 | E61: 2132 | F61: 22172.8 | G61: Self-Watering | H61: 91 | I61: 0
A62: MSP 1P | B62: 40 | C62: 120 | D62: 250 | E62: 1 | F62: 130 | G62: Self-Watering | H62: 100 | I62: 0
A63: OCT 2P | B63: 47 | C63: 141 | D63: 340 | E63: 1 | F63: 199 | G63: Self-Watering | H63: 91 | I63: 0
A64: OCT 3P | B64: 55 | C64: 165 | D64: 470 | E64: 2 | F64: 610 | G64: Self-Watering | H64: 96 | I64: 0
A65: WBX 0P | B65: 6 | C65: 18 | D65: 70 | E65: 3 | F65: 156 | G65: Self-Watering | H65: 94 | I65: 0
A66: MSP 2P | B66: 47 | C66: 141 | D66: 370 | E66: 3 | F66: 687 | G66: Self-Watering | H66: 97 | I66: 0
... A97: CNS 1P | B97: 7 | C97: 21 | D97: 55 | E97: 1578 | F97: 53652 | G97: Self-Watering | H97: 95 | I97: 0

Sheet Suggestion6
A2: Colour | B2: Sum of Salesin_2012 | C2: Sum of Salesin_2011
A3: Pink Granite | B3: 1021 | C3: 429
A4: Brown | B4: 496 | C4: 557
A5: Terracotta | B5: 368 | C5: 37
A6: Guerney Granite | B6: 306 | C6: 160
A7: Sky Blue | B7: 170 | C7: 56
A8: Cherry | B8: 48 | C8: 39
A9: Light Green | B9: 44 | C9: 15
A10: Light Sandstone | B10: 38 | C10: 43
A11: Dark Sandstone | B11: 26 | C11: 13
A12: Millstone Gritt | B12: 15 | C12: 8
A13: Orange | B13: 7 | C13: 20
A14: White Marble | B14: 5 | C14: 0
... A16: Grand Total | B16: 2544 | C16: 1382

Sheet Suggestion7
A2: Years | B2: Profit of Bins | C2: Profit of Self Watering | D2: Profit of Planterware | E2: Sum of Total Profit
A3: 2006 | B3: 144584.8 | C3: 799208.4 | D3: 0 | E3: 943793
A4: 2007 | B4: 132479.8 | C4: 895837 | D4: 0 | E4: 1028317
A5: 2008 | B5: 141823.4 | C5: 840681.2 | D5: 0 | E5: 982505
A6: 2009 | B6: 88421.2 | C6: 748392.8 | D6: 0 | E6: 836814
A7: 2010 | B7: 422323.8 | C7: 804376.6 | D7: 19512.5 | E7: 1246213
A8: 2011 | B8: 271603.6 | C8: 809295.2 | D8: -12815.5 | E8: 1068083
A9: 2012 | B9: 280878.6 | C9: 1094141.2 | D9: -12815.5 | E9: 1475767
A10: Grand Total | B10: 1482115.2 | C10: 5991932.4 | D10: -6118.5 | E10: 7581492

Sheet Sheet12
A1: Product Family | B1: Planterware | C1: Forecast(Planterware) | D1: Lower Confidence Bound(Planterware) | E1: Upper Confidence Bound(Planterware)
A2: 2006 | B2: 0
A3: 2007 | B3: 0
A4: 2008 | B4: 0
A5: 2009 | B5: 0
A6: 2010 | B6: 809
A7: 2011 | B7: 2426
A8: 2012 | B8: 4464 | C8: 4464 | D8: 4464 | E8: 4464
A9: 2013 | C9: =_xlfn.FORECAST.ETS(A9,$B$2:$B$8,$A$2:$A$8,1,1) -> 5144.4643 | D9: =C9-_xlfn.FORECAST.ETS.CONFINT(A9,$B$2:$B$8,$A$2:$A$8,0.95,1,1) -> 4051.3382 | E9: =C9+_xlfn.FORECAST.ETS.CONFINT(A9,$B$2:$B$8,$A$2:$A$8,0.95,1,1) -> 6237.5903
A10: 2014 | C10: =_xlfn.FORECAST.ETS(A10,$B$2:$B$8,$A$2:$A$8,1,1) -> 5824.9286 | D10: =C10-_xlfn.FORECAST.ETS.CONFINT(A10,$B$2:$B$8,$A$2:$A$8,0.95,1,1) -> 4279.7877 | E10: =C10+_xlfn.FORECAST.ETS.CONFINT(A10,$B$2:$B$8,$A$2:$A$8,0.95,1,1) -> 7370.0695
A11: 2015 | C11: =_xlfn.FORECAST.ETS(A11,$B$2:$B$8,$A$2:$A$8,1,1) -> 6505.3929 | D11: =C11-_xlfn.FORECAST.ETS.CONFINT(A11,$B$2:$B$8,$A$2:$A$8,0.95,1,1) -> 4612.6739 | E11: =C11+_xlfn.FORECAST.ETS.CONFINT(A11,$B$2:$B$8,$A$2:$A$8,0.95,1,1) -> 8398.1118
A12: 2016 | C12: =_xlfn.FORECAST.ETS(A12,$B$2:$B$8,$A$2:$A$8,1,1) -> 7185.8571 | D12: =C12-_xlfn.FORECAST.ETS.CONFINT(A12,$B$2:$B$8,$A$2:$A$8,0.95,1,1) -> 4999.6045 | E12: =C12+_xlfn.FORECAST.ETS.CONFINT(A12,$B$2:$B$8,$A$2:$A$8,0.95,1,1) -> 9372.1098
A13: 2017 | C13: =_xlfn.FORECAST.ETS(A13,$B$2:$B$8,$A$2:$A$8,1,1) -> 7866.3214 | D13: =C13-_xlfn.FORECAST.ETS.CONFINT(A13,$B$2:$B$8,$A$2:$A$8,0.95,1,1) -> 5421.0383 | E13: =C13+_xlfn.FORECAST.ETS.CONFINT(A13,$B$2:$B$8,$A$2:$A$8,0.95,1,1) -> 10311.605

Sheet Sheet13
A1: Product Family | B1: Self-Watering | C1: Forecast(Self-Watering) | D1: Lower Confidence Bound(Self-Watering) | E1: Upper Confidence Bound(Self-Watering)
A2: 2006 | B2: 22892
A3: 2007 | B3: 24438
A4: 2008 | B4: 23135
A5: 2009 | B5: 21898
A6: 2010 | B6: 19118
A7: 2011 | B7: 20336
A8: 2012 | B8: 23429 | C8: 23429 | D8: 23429 | E8: 23429
A9: 2013 | C9: =_xlfn.FORECAST.ETS(A9,$B$2:$B$8,$A$2:$A$8,1,1) -> 20257.015 | D9: =C9-_xlfn.FORECAST.ETS.CONFINT(A9,$B$2:$B$8,$A$2:$A$8,0.95,1,1) -> 17098.742 | E9: =C9+_xlfn.FORECAST.ETS.CONFINT(A9,$B$2:$B$8,$A$2:$A$8,0.95,1,1) -> 23415.287
A10: 2014 | C10: =_xlfn.FORECAST.ETS(A10,$B$2:$B$8,$A$2:$A$8,1,1) -> 19880.996 | D10: =C10-_xlfn.FORECAST.ETS.CONFINT(A10,$B$2:$B$8,$A$2:$A$8,0.95,1,1) -> 16722.709 | E10: =C10+_xlfn.FORECAST.ETS.CONFINT(A10,$B$2:$B$8,$A$2:$A$8,0.95,1,1) -> 23039.282
A11: 2015 | C11: =_xlfn.FORECAST.ETS(A11,$B$2:$B$8,$A$2:$A$8,1,1) -> 19504.977 | D11: =C11-_xlfn.FORECAST.ETS.CONFINT(A11,$B$2:$B$8,$A$2:$A$8,0.95,1,1) -> 16346.665 | E11: =C11+_xlfn.FORECAST.ETS.CONFINT(A11,$B$2:$B$8,$A$2:$A$8,0.95,1,1) -> 22663.288
A12: 2016 | C12: =_xlfn.FORECAST.ETS(A12,$B$2:$B$8,$A$2:$A$8,1,1) -> 19128.958 | D12: =C12-_xlfn.FORECAST.ETS.CONFINT(A12,$B$2:$B$8,$A$2:$A$8,0.95,1,1) -> 15970.607 | E12: =C12+_xlfn.FORECAST.ETS.CONFINT(A12,$B$2:$B$8,$A$2:$A$8,0.95,1,1) -> 22287.309
A13: 2017 | C13: =_xlfn.FORECAST.ETS(A13,$B$2:$B$8,$A$2:$A$8,1,1) -> 18752.939 | D13: =C13-_xlfn.FORECAST.ETS.CONFINT(A13,$B$2:$B$8,$A$2:$A$8,0.95,1,1) -> 15594.532 | E13: =C13+_xlfn.FORECAST.ETS.CONFINT(A13,$B$2:$B$8,$A$2:$A$8,0.95,1,1) -> 21911.347

Sheet ProductFamilyForecast
A1: Years | B1: Bins Profit % | C1: Forecast(Bins Profit %) | D1: Lower Confidence Bound(Bins Profit %) | E1: Upper Confidence Bound(Bins Profit %)
A2: 2006 | B2: 0.15319546
A3: 2007 | B3: 0.12883167
A4: 2008 | B4: 0.14434878
A5: 2009 | B5: 0.1056641
A6: 2010 | B6: 0.33888573
A7: 2011 | B7: 0.25429072
A8: 2012 | B8: 0.1903272 | C8: 0.1903272 | D8: 0.1903272 | E8: 0.1903272
A9: 2013 | C9: =_xlfn.FORECAST.ETS(A9,$B$2:$B$8,$A$2:$A$8,1,1) -> 0.29137236 | D9: =C9-_xlfn.FORECAST.ETS.CONFINT(A9,$B$2:$B$8,$A$2:$A$8,0.95,1,1) -> 0.15517943 | E9: =C9+_xlfn.FORECAST.ETS.CONFINT(A9,$B$2:$B$8,$A$2:$A$8,0.95,1,1) -> 0.42756528
A10: 2014 | C10: =_xlfn.FORECAST.ETS(A10,$B$2:$B$8,$A$2:$A$8,1,1) -> 0.31108791 | D10: =C10-_xlfn.FORECAST.ETS.CONFINT(A10,$B$2:$B$8,$A$2:$A$8,0.95,1,1) -> 0.17489438 | E10: =C10+_xlfn.FORECAST.ETS.CONFINT(A10,$B$2:$B$8,$A$2:$A$8,0.95,1,1) -> 0.44728145

Sheet Sheet14
A1: Product Family | B1: Self-Watering | C1: Forecast(Self-Watering) | D1: Lower Confidence Bound(Self-Watering) | E1: Upper Confidence Bound(Self-Watering)
A2: 2006 | B2: 22892
A3: 2007 | B3: 24438
A4: 2008 | B4: 23135
A5: 2009 | B5: 21898
A6: 2010 | B6: 19118
A7: 2011 | B7: 20336
A8: 2012 | B8: 23429 | C8: 23429 | D8: 23429 | E8: 23429
A9: 2013 | C9: =_xlfn.FORECAST.ETS(A9,$B$2:$B$8,$A$2:$A$8,1,1) -> 20257.015 | D9: =C9-_xlfn.FORECAST.ETS.CONFINT(A9,$B$2:$B$8,$A$2:$A$8,0.95,1,1) -> 17098.742 | E9: =C9+_xlfn.FORECAST.ETS.CONFINT(A9,$B$2:$B$8,$A$2:$A$8,0.95,1,1) -> 23415.287
A10: 2014 | C10: =_xlfn.FORECAST.ETS(A10,$B$2:$B$8,$A$2:$A$8,1,1) -> 19880.996 | D10: =C10-_xlfn.FORECAST.ETS.CONFINT(A10,$B$2:$B$8,$A$2:$A$8,0.95,1,1) -> 16722.709 | E10: =C10+_xlfn.FORECAST.ETS.CONFINT(A10,$B$2:$B$8,$A$2:$A$8,0.95,1,1) -> 23039.282
A11: 2015 | C11: =_xlfn.FORECAST.ETS(A11,$B$2:$B$8,$A$2:$A$8,1,1) -> 19504.977 | D11: =C11-_xlfn.FORECAST.ETS.CONFINT(A11,$B$2:$B$8,$A$2:$A$8,0.95,1,1) -> 16346.665 | E11: =C11+_xlfn.FORECAST.ETS.CONFINT(A11,$B$2:$B$8,$A$2:$A$8,0.95,1,1) -> 22663.288
A12: 2016 | C12: =_xlfn.FORECAST.ETS(A12,$B$2:$B$8,$A$2:$A$8,1,1) -> 19128.958 | D12: =C12-_xlfn.FORECAST.ETS.CONFINT(A12,$B$2:$B$8,$A$2:$A$8,0.95,1,1) -> 15970.607 | E12: =C12+_xlfn.FORECAST.ETS.CONFINT(A12,$B$2:$B$8,$A$2:$A$8,0.95,1,1) -> 22287.309
A13: 2017 | C13: =_xlfn.FORECAST.ETS(A13,$B$2:$B$8,$A$2:$A$8,1,1) -> 18752.939 | D13: =C13-_xlfn.FORECAST.ETS.CONFINT(A13,$B$2:$B$8,$A$2:$A$8,0.95,1,1) -> 15594.532 | E13: =C13+_xlfn.FORECAST.ETS.CONFINT(A13,$B$2:$B$8,$A$2:$A$8,0.95,1,1) -> 21911.347

Sheet Suggestion8
A10: Product Family | B10: 2006 | C10: 2007 | D10: 2008 | E10: 2009 | F10: 2010 | G10: 2011 | H10: 2012
A11: Self-Watering | B11: 22892 | C11: 24438 | D11: 23135 | E11: 21898 | F11: 19118 | G11: 20336 | H11: 23429

Sheet PerformanceScore
A2: Average of Performance Score (Number of Sales * Profit Margin) / Selling Price) | B2: Product Family
A3: Colour | B3: Self-Watering | C3: Bins | D3: Planterware | E3: Grand Total
A4: Black | B4: 28.802433 | C4: 3.6281821 | D4: 0 | E4: 19.450935
A5: Standard Green | B5: 18.575569 | E5: 18.575569
A6: Brown | B6: 5.616 | E6: 5.616
A7: Terracotta | D7: 1.8020412 | E7: 1.8020412
A8: Pink Granite | B8: 0.46981714 | E8: 0.46981714
A9: Sky Blue | B9: 0.36739765 | E9: 0.36739765
A10: Light Green | B10: 0.16152639 | E10: 0.16152639
A11: Guerney Granite | B11: 0.12178946 | E11: 0.12178946
A12: Orange | B12: 0.11071912 | E12: 0.11071912
A13: Dark Sandstone | B13: 0.086112 | E13: 0.086112
A14: Cherry | B14: 0.081464369 | E14: 0.081464369
A15: Light Sandstone | B15: 0.093556234 | D15: 0 | E15: 0.074844987
A16: Millstone Gritt | B16: 0.050784 | E16: 0.050784
A17: White Marble | B17: 0.010493827 | E17: 0.010493827
A18: Moss Stone | B18: 0.0050204082 | E18: 0.0050204082
A19: Grand Total | B19: 12.320462 | C19: 3.6281821 | D19: 1.607226 | E19: 9.497515
A31: Product Family | B31: Colour | C31: Performance Score (Number of Sales * Profit Margin) / Selling Price) | D31: Profit Margin | E31: Total Nr of Sales
A32: Self-Watering | B32: Black | C32: 0.089256198 | D32: 0.49090909 | E32: 40
A33: Self-Watering | B33: Black | C33: 0.014711804 | D33: 0.70984456 | E33: 12
A34: Self-Watering | B34: Black | C34: 0.0018483245 | D34: 0.58222222 | E34: 1
A35: Planterware | B35: Black | C35: 0 | D35: -0.30666667 | E35: 0
A36: Planterware | B36: Black | C36: 0 | D36: -0.25263158 | E36: 0
A37: Self-Watering | B37: Black | C37: 0.13340484 | D37: 0.61294118 | E37: 74
A38: Self-Watering | B38: Black | C38: 0.130272 | D38: 0.552 | E38: 59
A39: Bins | B39: Black | C39: 0.1978 | D39: 0.86 | E39: 23
A40: Self-Watering | B40: Black | C40: 0.030696296 | D40: 0.65777778 | E40: 21
A41: Self-Watering | B41: Black | C41: 1.38 | D41: 0.72 | E41: 115
A42: Bins | B42: Black | C42: 0.069722222 | D42: 0.83666667 | E42: 10
A43: Bins | B43: Black | C43: 0.1725 | D43: 0.7 | E43: 69
... A233: Self-Watering | B233: White Marble | C233: 0.010493827 | D233: 0.37777778 | E233: 5

Sheet Profit Margin
A4: Product Family | B4: Sum of Total Nr of Sales
A5: Bins | B5: 11127
A6: Planterware | B6: 7699
A7: Self-Watering | B7: 132354
A8: Grand Total | B8: 151180

Sheet New Introduced Colour Analysis
A1: Colour | B1: Salesin_2012 | C1: Salesin_2011 | D1: Salesin_2010 | E1: Salesin_2009 | F1: Salesin_2008 | G1: Salesin_2007 | H1: Salesin_2006 | I1: Product Family
A2: Black | B2: 0 | C2: 1 | D2: 0 | E2: 1 | F2: 38 | G2: 0 | H2: 0 | I2: Self-Watering
A3: Black | B3: 0 | C3: 0 | D3: 0 | E3: 0 | F3: 12 | G3: 0 | H3: 0 | I3: Self-Watering
A4: Black | B4: 0 | C4: 0 | D4: 0 | E4: 1 | F4: 0 | G4: 0 | H4: 0 | I4: Self-Watering
A5: Black | B5: 0 | C5: 0 | D5: 0 | E5: 0 | F5: 0 | G5: 0 | H5: 0 | I5: Planterware
A6: Black | B6: 0 | C6: 0 | D6: 0 | E6: 0 | F6: 0 | G6: 0 | H6: 0 | I6: Planterware
A7: Black | B7: 2 | C7: 34 | D7: 36 | E7: 2 | F7: 0 | G7: 0 | H7: 0 | I7: Self-Watering
A8: Black | B8: 5 | C8: 0 | D8: 0 | E8: 2 | F8: 52 | G8: 0 | H8: 0 | I8: Self-Watering
A9: Black | B9: 5 | C9: 7 | D9: 3 | E9: 8 | F9: 0 | G9: 0 | H9: 0 | I9: Bins
A10: Black | B10: 7 | C10: 2 | D10: 3 | E10: 1 | F10: 8 | G10: 0 | H10: 0 | I10: Self-Watering
A11: Black | B11: 10 | C11: 10 | D11: 12 | E11: 13 | F11: 36 | G11: 34 | H11: 0 | I11: Self-Watering
A12: Black | B12: 10 | C12: 0 | D12: 0 | E12: 0 | F12: 0 | G12: 0 | H12: 0 | I12: Bins
A13: Black | B13: 12 | C13: 12 | D13: 9 | E13: 10 | F13: 13 | G13: 13 | H13: 15 | I13: Bins
... A203: White Marble | B203: 5 | C203: 0 | D203: 0 | E203: 0 | F203: 0 | G203: 0 | H203: 0 | I203: Self-Watering
A217: Colour | B217: Salesin_2012 | C217: Salesin_2011
A218: Brown | B218: 496 | C218: 557 | F218: Colours | G218: Sales_2012 | H218: Sales_2011
A219: Cherry | B219: 0 | C219: 13 | F219: Pink Granite | G219: 885 | H219: 462
A220: Cherry | B220: 0 | C220: 5 | F220: Brown | G220: 496 | H220: 557
A221: Cherry | B221: 0 | C221: 5 | F221: Terracota | G221: 249 | H221: 56
A222: Cherry | B222: 0 | C222: 5 | F222: Cherry | G222: 209 | H222: 0
A223: Cherry | B223: 28 | C223: 5 | F223: Sky Blue | G223: 295 | H223: 46
A224: Cherry | B224: 0 | C224: 3 | F224: Guerney Granite | G224: 140 | H224: 62
A225: Cherry | B225: 0 | C225: 3 | F225: Dark Sandstone | G225: 53 | H225: 21
A226: Cherry | B226: 1 | C226: 0 | F226: Light Green | G226: 38 | H226: 41
A227: Cherry | B227: 2 | C227: 0 | F227: Light Sandstone | G227: 36 | H227: 30
A228: Cherry | B228: 2 | C228: 0 | F228: Millstone Gritt | G228: 15 | H228: 8
A229: Cherry | B229: 2 | C229: 0 | F229: Orange | G229: 7 | H229: 20
A230: Cherry | B230: 5 | C230: 0 | F230: White Marble | G230: 5 | H230: 0
A231: Cherry | B231: 8 | C231: 0 | F231: Moss Stone | G231: 0 | H231: 5
A232: Dark Sandstone | B232: 26 | C232: 13 | G232: =SUM(G219:G231) -> 2428 | H232: =SUM(H219:H231) -> 1308 | J232: 29941
A233: Guerney Granite | B233: 135 | C233: 78
A234: Guerney Granite | B234: 57 | C234: 35 | G234: =G232/J232 -> 0.081092816
A235: Guerney Granite | B235: 26 | C235: 25
A236: Guerney Granite | B236: 53 | C236: 21 | I236: Sales of New Introduced Colours | J236: Total Sales
A237: Guerney Granite | B237: 0 | C237: 1 | I237: 2428 | J237: 29941
A238: Guerney Granite | B238: 5 | C238: 0
A239: Guerney Granite | B239: 30 | C239: 0
A240: Light Green | B240: 23 | C240: 15
A241: Light Green | B241: 3 | C241: 0
A242: Light Green | B242: 3 | C242: 0
A243: Light Green | B243: 15 | C243: 0
A244: Light Sandstone | B244: 23 | C244: 35
A245: Light Sandstone | B245: 0 | C245: 5
A246: Light Sandstone | B246: 0 | C246: 1
A247: Light Sandstone | B247: 0 | C247: 1
A248: Light Sandstone | B248: 0 | C248: 1
A249: Light Sandstone | B249: 0 | C249: 0
... A260: Pink Granite | B260: 0 | C260: 89
A261: Pink Granite | B261: 76 | C261: 55 | G261: Bins
A262: Pink Granite | B262: 55 | C262: 45 | G262: Toplam satış sayısı: 11,127 | J262: Product | K262: Total Sale | L262: Average Profit Margin (%)
A263: Pink Granite | B263: 53 | C263: 28 | G263: Ortalama kar marjı: %67 | J263: Bins | K263: 11127 | L263: 0.67
A264: Pink Granite | B264: 35 | C264: 23 | J264: Planterware | K264: 7699 | L264: 0.33
A265: Pink Granite | B265: 33 | C265: 15 | G265: Planterware | J265: Self Watering | K265: 132354 | L265: 0.65
A266: Pink Granite | B266: 35 | C266: 14 | G266: Toplam satış sayısı: 7,699
A267: Pink Granite | B267: 13 | C267: 10 | G267: Ortalama kar marjı: %33
A268: Pink Granite | B268: 13 | C268: 10
A269: Pink Granite | B269: 0 | C269: 5 | G269: Self-Watering
A270: Pink Granite | B270: 1 | C270: 0 | G270: Toplam satış sayısı: 132,354
A271: Pink Granite | B271: 1 | C271: 0 | G271: Ortalama kar marjı: %65
A272: Pink Granite | B272: 3 | C272: 0
A273: Pink Granite | B273: 3 | C273: 0
A274: Pink Granite | B274: 5 | C274: 0
A275: Pink Granite | B275: 5 | C275: 0
A276: Pink Granite | B276: 5 | C276: 0
A277: Pink Granite | B277: 5 | C277: 0
A278: Pink Granite | B278: 25 | C278: 0
A279: Pink Granite | B279: 35 | C279: 0
A280: Pink Granite | B280: 35 | C280: 0
A281: Pink Granite | B281: 55 | C281: 0
A282: Sky Blue | B282: 135 | C282: 46
A283: Sky Blue | B283: 0 | C283: 5
... A295: White Marble | B295: 5 | C295: 0

Sheet Sheet20
A1: Powder_weight_kg | B1: Powder_Cost | C1: Selling_Price_Pound | D1: Profit | E1: Profit_Margin | F1: Salesin_2012 | G1: Profitin_2012 | H1: Salesin_2011 | I1: Profitin_2011 | J1: Salesin_2010 | K1: Profitin_2010 | L1: Salesin_2009 | M1: Profitin_2009 | N1: Salesin_2008 | O1: Profitin_2008 | P1: Salesin_2007 | Q1: Profitin_2007 | R1: Salesin_2006 | S1: Profitin_2006 | T1: Total Nr of Sales | U1: Product_Family_Num | V1: Due Date Performance/% | W1: Total_Powder_Weight_kg
A2: 15 | B2: =A2*3 -> 45 | C2: 75 | D2: =C2-B2 -> 30 | E2: =(CleanedDataset!$F62-CleanedDataset!$E62)/CleanedDataset!$F62 -> 0.72 | F2: 496 | G2: =F2*C2-F2*B2 -> 14880 | H2: 557 | I2: =H2*C2-F2*B2 -> 19455 | J2: 0 | K2: =J2*C2-J2*B2 -> 0 | L2: 0 | M2: =L2*C2-L2*B2 -> 0 | N2: 0 | O2: =N2*C2-N2*B2 -> 0 | P2: 0 | Q2: =P2*C2-P2*B2 -> 0 | R2: 0 | S2: =R2*C2-R2*B2 -> 0 | T2: =SUM(P2,N2,L2,J2,H2,F2) -> 1053 | U2: 1 | V2: 91 | W2: =A2*F2 -> 7440
A3: 6 | B3: =A3*2.8 -> 16.8 | C3: 40 | D3: =C3-B3 -> 23.2 | E3: =(CleanedDataset!$F53-CleanedDataset!$E53)/CleanedDataset!$F53 -> 0.7 | F3: 405 | G3: =F3*C3-F3*B3 -> 9396 | H3: 534 | I3: =H3*C3-F3*B3 -> 14556 | J3: 987 | K3: =J3*C3-J3*B3 -> 22898.4 | L3: 1917 | M3: =L3*C3-L3*B3 -> 44474.4 | N3: 1047 | O3: =N3*C3-N3*B3 -> 24290.4 | P3: 326 | Q3: =P3*C3-P3*B3 -> 7563.2 | R3: 857 | S3: =R3*C3-R3*B3 -> 19882.4 | T3: =SUM(P3,N3,L3,J3,H3,F3) -> 5216 | U3: 1 | V3: 92 | W3: =A3*F3 -> 2430
A4: 6 | B4: =A4*3.2 -> 19.2 | C4: 55 | D4: =C4-B4 -> 35.8 | E4: =(CleanedDataset!$F126-CleanedDataset!$E126)/CleanedDataset!$F126 -> 0.61891892 | F4: 530 | G4: =F4*C4-F4*B4 -> 18974 | H4: 135 | I4: =H4*C4-F4*B4 -> -2751 | J4: 0 | K4: =J4*C4-J4*B4 -> 0 | L4: 0 | M4: =L4*C4-L4*B4 -> 0 | N4: 0 | O4: =N4*C4-N4*B4 -> 0 | P4: 0 | Q4: =P4*C4-P4*B4 -> 0 | R4: 0 | S4: =R4*C4-R4*B4 -> 0 | T4: =SUM(P4,N4,L4,J4,H4,F4) -> 665 | U4: 1 | V4: 90 | W4: =A4*F4 -> 3180
A5: 6 | B5: =A5*3 -> 18 | C5: 50 | D5: =C5-B5 -> 32 | E5: =(CleanedDataset!$F162-CleanedDataset!$E162)/CleanedDataset!$F162 -> 0.83666667 | F5: 450 | G5: =F5*C5-F5*B5 -> 14400 | H5: 300 | I5: =H5*C5-F5*B5 -> 6900 | J5: 230 | K5: =J5*C5-J5*B5 -> 7360 | L5: 200 | M5: =L5*C5-L5*B5 -> 6400 | N5: 225 | O5: =N5*C5-N5*B5 -> 7200 | P5: 705 | Q5: =P5*C5-P5*B5 -> 22560 | R5: 680 | S5: =R5*C5-R5*B5 -> 21760 | T5: =SUM(P5,N5,L5,J5,H5,F5) -> 2110 | U5: 1 | V5: 92 | W5: =A5*F5 -> 2700
A6: 3.5 | B6: =A6*2.8 -> 9.8 | C6: 25 | D6: =C6-B6 -> 15.2 | E6: =(CleanedDataset!$F56-CleanedDataset!$E56)/CleanedDataset!$F56 -> 0.68802228 | F6: 604 | G6: =F6*C6-F6*B6 -> 9180.8 | H6: 339 | I6: =H6*C6-F6*B6 -> 2555.8 | J6: 853 | K6: =J6*C6-J6*B6 -> 12965.6 | L6: 2331 | M6: =L6*C6-L6*B6 -> 35431.2 | N6: 1049 | O6: =N6*C6-N6*B6 -> 15944.8 | P6: 326 | Q6: =P6*C6-P6*B6 -> 4955.2 | R6: 708 | S6: =R6*C6-R6*B6 -> 10761.6 | T6: =SUM(P6,N6,L6,J6,H6,F6) -> 5502 | U6: 1 | V6: 99 | W6: =A6*F6 -> 2114
A7: 3.5 | B7: =A7*3 -> 10.5 | C7: 35 | D7: =C7-B7 -> 24.5 | E7: =(CleanedDataset!$F167-CleanedDataset!$E167)/CleanedDataset!$F167 -> 0.29292929 | F7: 1350 | G7: =F7*C7-F7*B7 -> 33075 | H7: 1200 | I7: =H7*C7-F7*B7 -> 27825 | J7: 567 | K7: =J7*C7-J7*B7 -> 13891.5 | L7: 200 | M7: =L7*C7-L7*B7 -> 4900 | N7: 540 | O7: =N7*C7-N7*B7 -> 13230 | P7: 1250 | Q7: =P7*C7-P7*B7 -> 30625 | R7: 890 | S7: =R7*C7-R7*B7 -> 21805 | T7: =SUM(P7,N7,L7,J7,H7,F7) -> 5107 | U7: 1 | V7: 91 | W7: =A7*F7 -> 4725
A8: 55 | B8: =A8*2.8 -> 154 | C8: 530 | D8: =C8-B8 -> 376 | E8: =(CleanedDataset!$F33-CleanedDataset!$E33)/CleanedDataset!$F33 -> 0.6 | F8: 58 | G8: =F8*C8-F8*B8 -> 21808 | H8: 75 | I8: =H8*C8-F8*B8 -> 30818 | J8: 39 | K8: =J8*C8-J8*B8 -> 14664 | L8: 16 | M8: =L8*C8-L8*B8 -> 6016 | N8: 21 | O8: =N8*C8-N8*B8 -> 7896 | P8: 60 | Q8: =P8*C8-P8*B8 -> 22560 | R8: 64 | S8: =R8*C8-R8*B8 -> 24064 | T8: =SUM(P8,N8,L8,J8,H8,F8) -> 269 | U8: 1 | V8: 100 | W8: =A8*F8 -> 3190
A9: 55 | B9: =A9*3.2 -> 176 | C9: 615 | D9: =C9-B9 -> 439 | E9: =(CleanedDataset!$F82-CleanedDataset!$E82)/CleanedDataset!$F82 -> 0.58588235 | F9: 57 | G9: =F9*C9-F9*B9 -> 25023 | H9: 35 | I9: =H9*C9-F9*B9 -> 11493 | J9: 0 | K9: =J9*C9-J9*B9 -> 0 | L9: 0 | M9: =L9*C9-L9*B9 -> 0 | N9: 0 | O9: =N9*C9-N9*B9 -> 0 | P9: 0 | Q9: =P9*C9-P9*B9 -> 0 | R9: 0 | S9: =R9*C9-R9*B9 -> 0 | T9: =SUM(P9,N9,L9,J9,H9,F9) -> 92 | U9: 1 | V9: 93 | W9: =A9*F9 -> 3135
A10: 55 | B10: =A10*3.2 -> 176 | C10: 600 | D10: =C10-B10 -> 424 | E10: =(CleanedDataset!$F117-CleanedDataset!$E117)/CleanedDataset!$F117 -> 0.57333333 | F10: 35 | G10: =F10*C10-F10*B10 -> 14840 | H10: 14 | I10: =H10*C10-F10*B10 -> 2240 | J10: 0 | K10: =J10*C10-J10*B10 -> 0 | L10: 0 | M10: =L10*C10-L10*B10 -> 0 | N10: 0 | O10: =N10*C10-N10*B10 -> 0 | P10: 0 | Q10: =P10*C10-P10*B10 -> 0 | R10: 0 | S10: =R10*C10-R10*B10 -> 0 | T10: =SUM(P10,N10,L10,J10,H10,F10) -> 49 | U10: 1 | V10: 90 | W10: =A10*F10 -> 1925
A11: 55 | B11: =A11*3 -> 165 | C11: 600 | D11: =C11-B11 -> 435 | E11: =(CleanedDataset!$F148-CleanedDataset!$E148)/CleanedDataset!$F148 -> 0.59351351 | F11: 66 | G11: =F11*C11-F11*B11 -> 28710 | H11: 35 | I11: =H11*C11-F11*B11 -> 10110 | J11: 12 | K11: =J11*C11-J11*B11 -> 5220 | L11: 15 | M11: =L11*C11-L11*B11 -> 6525 | N11: 33 | O11: =N11*C11-N11*B11 -> 14355 | P11: 50 | Q11: =P11*C11-P11*B11 -> 21750 | R11: 45 | S11: =R11*C11-R11*B11 -> 19575 | T11: =SUM(P11,N11,L11,J11,H11,F11) -> 211 | U11: 1 | V11: 94 | W11: =A11*F11 -> 3630
A12: 65 | B12: =A12*2.8 -> 182 | C12: 584 | D12: =C12-B12 -> 402 | E12: =(CleanedDataset!$F32-CleanedDataset!$E32)/CleanedDataset!$F32 -> 0.66666667 | F12: 51 | G12: =F12*C12-F12*B12 -> 20502 | H12: 78 | I12: =H12*C12-F12*B12 -> 36270 | J12: 193 | K12: =J12*C12-J12*B12 -> 77586 | L12: 0 | M12: =L12*C12-L12*B12 -> 0 | N12: 0 | O12: =N12*C12-N12*B12 -> 0 | P12: 0 | Q12: =P12*C12-P12*B12 -> 0 | R12: 0 | S12: =R12*C12-R12*B12 -> 0 | T12: =SUM(P12,N12,L12,J12,H12,F12) -> 322 | U12: 1 | V12: 94 | W12: =A12*F12 -> 3315
A13: 65 | B13: =A13*3.2 -> 208 | C13: 700 | D13: =C13-B13 -> 492 | E13: =(CleanedDataset!$F78-CleanedDataset!$E78)/CleanedDataset!$F78 -> -0.275 | F13: 5 | G13: =F13*C13-F13*B13 -> 2460 | H13: 0 | I13: =H13*C13-F13*B13 -> -1040 | J13: 0 | K13: =J13*C13-J13*B13 -> 0 | L13: 0 | M13: =L13*C13-L13*B13 -> 0 | N13: 0 | O13: =N13*C13-N13*B13 -> 0 | P13: 0 | Q13: =P13*C13-P13*B13 -> 0 | R13: 0 | S13: =R13*C13-R13*B13 -> 0 | T13: =SUM(P13,N13,L13,J13,H13,F13) -> 5 | U13: 1 | V13: 99 | W13: =A13*F13 -> 325
A14: 65 | B14: =A14*3 -> 195 | C14: 650 | D14: =C14-B14 -> 455 | E14: =(CleanedDataset!$F84-CleanedDataset!$E84)/CleanedDataset!$F84 -> 0.25 | F14: 3 | G14: =F14*C14-F14*B14 -> 1365 | H14: 0 | I14: =H14*C14-F14*B14 -> -585 | J14: 0 | K14: =J14*C14-J14*B14 -> 0 | L14: 0 | M14: =L14*C14-L14*B14 -> 0 | N14: 0 | O14: =N14*C14-N14*B14 -> 0 | P14: 0 | Q14: =P14*C14-P14*B14 -> 0 | R14: 0 | S14: =R14*C14-R14*B14 -> 0 | T14: =SUM(P14,N14,L14,J14,H14,F14) -> 3 | U14: 1 | V14: 98 | W14: =A14*F14 -> 195
A15: 65 | B15: =A15*3.2 -> 208 | C15: 700 | D15: =C15-B15 -> 492 | E15: =(CleanedDataset!$F99-CleanedDataset!$E99)/CleanedDataset!$F99 -> 0.0625 | F15: 0 | G15: =F15*C15-F15*B15 -> 0 | H15: 5 | I15: =H15*C15-F15*B15 -> 3500 | J15: 0 | K15: =J15*C15-J15*B15 -> 0 | L15: 0 | M15: =L15*C15-L15*B15 -> 0 | N15: 0 | O15: =N15*C15-N15*B15 -> 0 | P15: 0 | Q15: =P15*C15-P15*B15 -> 0 | R15: 0 | S15: =R15*C15-R15*B15 -> 0 | T15: =SUM(P15,N15,L15,J15,H15,F15) -> 5 | U15: 1 | V15: 98 | W15: =A15*F15 -> 0
A16: 65 | B16: =A16*3.2 -> 208 | C16: 700 | D16: =C16-B16 -> 492 | E16: =(CleanedDataset!$F122-CleanedDataset!$E122)/CleanedDataset!$F122 -> 0.49090909 | F16: 53 | G16: =F16*C16-F16*B16 -> 26076 | H16: 28 | I16: =H16*C16-F16*B16 -> 8576 | J16: 0 | K16: =J16*C16-J16*B16 -> 0 | L16: 0 | M16: =L16*C16-L16*B16 -> 0 | N16: 0 | O16: =N16*C16-N16*B16 -> 0 | P16: 0 | Q16: =P16*C16-P16*B16 -> 0 | R16: 0 | S16: =R16*C16-R16*B16 -> 0 | T16: =SUM(P16,N16,L16,J16,H16,F16) -> 81 | U16: 1 | V16: 93 | W16: =A16*F16 -> 3445
A17: 65 | B17: =A17*3 -> 195 | C17: 650 | D17: =C17-B17 -> 455 | E17: =(CleanedDataset!$F152-CleanedDataset!$E152)/CleanedDataset!$F152 -> 0.648 | F17: 158 | G17: =F17*C17-F17*B17 -> 71890 | H17: 113 | I17: =H17*C17-F17*B17 -> 42640 | J17: 250 | K17: =J17*C17-J17*B17 -> 113750 | L17: 0 | M17: =L17*C17-L17*B17 -> 0 | N17: 0 | O17: =N17*C17-N17*B17 -> 0 | P17: 0 | Q17: =P17*C17-P17*B17 -> 0 | R17: 0 | S17: =R17*C17-R17*B17 -> 0 | T17: =SUM(P17,N17,L17,J17,H17,F17) -> 521 | U17: 1 | V17: 97 | W17: =A17*F17 -> 10270
A18: 5 | B18: =A18*2.8 -> 14 | C18: 56 | D18: =C18-B18 -> 42 | E18: =(CleanedDataset!$F35-CleanedDataset!$E35)/CleanedDataset!$F35 -> 0.77272727 | F18: 61 | G18: =F18*C18-F18*B18 -> 2562 | H18: 97 | I18: =H18*C18-F18*B18 -> 4578 | J18: 29 | K18: =J18*C18-J18*B18 -> 1218 | L18: 91 | M18: =L18*C18-L18*B18 -> 3822 | N18: 62 | O18: =N18*C18-N18*B18 -> 2604 | P18: 419 | Q18: =P18*C18-P18*B18 -> 17598 | R18: 37 | S18: =R18*C18-R18*B18 -> 1554 | T18: =SUM(P18,N18,L18,J18,H18,F18) -> 759 | U18: 1 | V18: 96 | W18: =A18*F18 -> 305
A19: 5 | B19: =A19*2.8 -> 14 | C19: 35 | D19: =C19-B19 -> 21 | E19: =(CleanedDataset!$F55-CleanedDataset!$E55)/CleanedDataset!$F55 -> 0.67919799 | F19: 527 | G19: =F19*C19-F19*B19 -> 11067 | H19: 203 | I19: =H19*C19-F19*B19 -> -273 | J19: 395 | K19: =J19*C19-J19*B19 -> 8295 | L19: 499 | M19: =L19*C19-L19*B19 -> 10479 | N19: 915 | O19: =N19*C19-N19*B19 -> 19215 | P19: 230 | Q19: =P19*C19-P19*B19 -> 4830 | R19: 532 | S19: =R19*C19-R19*B19 -> 11172 | T19: =SUM(P19,N19,L19,J19,H19,F19) -> 2769 | U19: 1 | V19: 91 | W19: =A19*F19 -> 2635
A20: 5 | B20: =A20*3 -> 15 | C20: 66 | D20: =C20-B20 -> 51 | E20: =(CleanedDataset!$F65-CleanedDataset!$E65)/CleanedDataset!$F65 -> 0.77846154 | F20: 0 | G20: =F20*C20-F20*B20 -> 0 | H20: 5 | I20: =H20*C20-F20*B20 -> 330 | J20: 0 | K20: =J20*C20-J20*B20 -> 0 | L20: 0 | M20: =L20*C20-L20*B20 -> 0 | N20: 0 | O20: =N20*C20-N20*B20 -> 0 | P20: 0 | Q20: =P20*C20-P20*B20 -> 0 | R20: 0 | S20: =R20*C20-R20*B20 -> 0 | T20: =SUM(P20,N20,L20,J20,H20,F20) -> 5 | U20: 1 | V20: 91 | W20: =A20*F20 -> 0
A21: 5 | B21: =A21*3 -> 15 | C21: 45 | D21: =C21-B21 -> 30 | E21: =(CleanedDataset!$F75-CleanedDataset!$E75)/CleanedDataset!$F75 -> 0.79466667 | F21: 28 | G21: =F21*C21-F21*B21 -> 840 | H21: 5 | I21: =H21*C21-F21*B21 -> -195 | J21: 0 | K21: =J21*C21-J21*B21 -> 0 | L21: 0 | M21: =L21*C21-L21*B21 -> 0 | N21: 0 | O21: =N21*C21-N21*B21 -> 0 | P21: 0 | Q21: =P21*C21-P21*B21 -> 0 | R21: 0 | S21: =R21*C21-R21*B21 -> 0 | T21: =SUM(P21,N21,L21,J21,H21,F21) -> 33 | U21: 1 | V21: 90 | W21: =A21*F21 -> 140
A22: 5 | B22: =A22*3 -> 15 | C22: 66 | D22: =C22-B22 -> 51 | E22: =(CleanedDataset!$F101-CleanedDataset!$E101)/CleanedDataset!$F101 -> 0.1 | F22: 1 | G22: =F22*C22-F22*B22 -> 51 | H22: 0 | I22: =H22*C22-F22*B22 -> -15 | J22: 0 | K22: =J22*C22-J22*B22 -> 0 | L22: 0 | M22: =L22*C22-L22*B22 -> 0 | N22: 0 | O22: =N22*C22-N22*B22 -> 0 | P22: 0 | Q22: =P22*C22-P22*B22 -> 0 | R22: 0 | S22: =R22*C22-R22*B22 -> 0 | T22: =SUM(P22,N22,L22,J22,H22,F22) -> 1 | U22: 1 | V22: 98 | W22: =A22*F22 -> 5
A23: 5 | B23: =A23*3 -> 15 | C23: 66 | D23: =C23-B23 -> 51 | E23: =(CleanedDataset!$F150-CleanedDataset!$E150)/CleanedDataset!$F150 -> 0.58222222 | F23: 87 | G23: =F23*C23-F23*B23 -> 4437 | H23: 65 | I23: =H23*C23-F23*B23 -> 2985 | J23: 50 | K23: =J23*C23-J23*B23 -> 2550 | L23: 67 | M23: =L23*C23-L23*B23 -> 3417 | N23: 50 | O23: =N23*C23-N23*B23 -> 2550 | P23: 35 | Q23: =P23*C23-P23*B23 -> 1785 | R23: 55 | S23: =R23*C23-R23*B23 -> 2805 | T23: =SUM(P23,N23,L23,J23,H23,F23) -> 354 | U23: 1 | V23: 91 | W23: =A23*F23 -> 435
A24: 5 | B24: =A24*3 -> 15 | C24: 45 | D24: =C24-B24 -> 30 | E24: =(CleanedDataset!$F158-CleanedDataset!$E158)/CleanedDataset!$F158 -> 0.2 | F24: 342 | G24: =F24*C24-F24*B24 -> 10260 | H24: 280 | I24: =H24*C24-F24*B24 -> 7470 | J24: 133 | K24: =J24*C24-J24*B24 -> 3990 | L24: 200 | M24: =L24*C24-L24*B24 -> 6000 | N24: 187 | O24: =N24*C24-N24*B24 -> 5610 | P24: 850 | Q24: =P24*C24-P24*B24 -> 25500 | R24: 345 | S24: =R24*C24-R24*B24 -> 10350 | T24: =SUM(P24,N24,L24,J24,H24,F24) -> 1992 | U24: 1 | V24: 94 | W24: =A24*F24 -> 1710
A25: 7 | B25: =A25*2.8 -> 19.6 | C25: 30 | D25: =C25-B25 -> 10.4 | E25: =(CleanedDataset!$F61-CleanedDataset!$E61)/CleanedDataset!$F61 -> 0.76666667 | F25: 2132 | G25: =F25*C25-F25*B25 -> 22172.8 | H25: 2648 | I25: =H25*C25-F25*B25 -> 37652.8 | J25: 2712 | K25: =J25*C25-J25*B25 -> 28204.8 | L25: 1775 | M25: =L25*C25-L25*B25 -> 18460 | N25: 2302 | O25: =N25*C25-N25*B25 -> 23940.8 | P25: 2250 | Q25: =P25*C25-P25*B25 -> 23400 | R25: 2532 | S25: =R25*C25-R25*B25 -> 26332.8 | T25: =SUM(P25,N25,L25,J25,H25,F25) -> 13819 | U25: 1 | V25: 91 | W25: =A25*F25 -> 14924
A26: 7 | B26: =A26*3 -> 21 | C26: 40 | D26: =C26-B26 -> 19 | E26: =(CleanedDataset!$F102-CleanedDataset!$E102)/CleanedDataset!$F102 -> 0.5890411 | F26: 6 | G26: =F26*C26-F26*B26 -> 114 | H26: 15 | I26: =H26*C26-F26*B26 -> 474 | J26: 0 | K26: =J26*C26-J26*B26 -> 0 | L26: 0 | M26: =L26*C26-L26*B26 -> 0 | N26: 0 | O26: =N26*C26-N26*B26 -> 0 | P26: 0 | Q26: =P26*C26-P26*B26 -> 0 | R26: 0 | S26: =R26*C26-R26*B26 -> 0 | T26: =SUM(P26,N26,L26,J26,H26,F26) -> 21 | U26: 1 | V26: 94 | W26: =A26*F26 -> 42
A27: 7 | B27: =A27*3 -> 21 | C27: 40 | D27: =C27-B27 -> 19 | E27: =(CleanedDataset!$F133-CleanedDataset!$E133)/CleanedDataset!$F133 -> 0.70461538 | F27: 135 | G27: =F27*C27-F27*B27 -> 2565 | H27: 46 | I27: =H27*C27-F27*B27 -> -995 | J27: 0 | K27: =J27*C27-J27*B27 -> 0 | L27: 0 | M27: =L27*C27-L27*B27 -> 0 | N27: 0 | O27: =N27*C27-N27*B27 -> 0 | P27: 0 | Q27: =P27*C27-P27*B27 -> 0 | R27: 0 | S27: =R27*C27-R27*B27 -> 0 | T27: =SUM(P27,N27,L27,J27,H27,F27) -> 181 | U27: 1 | V27: 95 | W27: =A27*F27 -> 945
A28: 7 | B28: =A28*3 -> 21 | C28: 40 | D28: =C28-B28 -> 19 | E28: =(CleanedDataset!$F166-CleanedDataset!$E166)/CleanedDataset!$F166 -> 0.87076923 | F28: 1300 | G28: =F28*C28-F28*B28 -> 24700 | H28: 1250 | I28: =H28*C28-F28*B28 -> 22700 | J28: 800 | K28: =J28*C28-J28*B28 -> 15200 | L28: 750 | M28: =L28*C28-L28*B28 -> 14250 | N28: 1200 | O28: =N28*C28-N28*B28 -> 22800 | P28: 2050 | Q28: =P28*C28-P28*B28 -> 38950 | R28: 1980 | S28: =R28*C28-R28*B28 -> 37620 | T28: =SUM(P28,N28,L28,J28,H28,F28) -> 7350 | U28: 1 | V28: 97 | W28: =A28*F28 -> 9100
A29: 5 | B29: =A29*2.8 -> 14 | C29: 45 | D29: =C29-B29 -> 31 | E29: =(CleanedDataset!$F58-CleanedDataset!$E58)/CleanedDataset!$F58 -> 0.68 | F29: 787 | G29: =F29*C29-F29*B29 -> 24397 | H29: 478 | I29: =H29*C29-F29*B29 -> 10492 | J29: 1235 | K29: =J29*C29-J29*B29 -> 38285 | L29: 1450 | M29: =L29*C29-L29*B29 -> 44950 | N29: 1728 | O29: =N29*C29-N29*B29 -> 53568 | P29: 1182 | Q29: =P29*C29-P29*B29 -> 36642 | R29: 999 | S29: =R29*C29-R29*B29 -> 30969 | T29: =SUM(P29,N29,L29,J29,H29,F29) -> 6860 | U29: 1 | V29: 97 | W29: =A29*F29 -> 3935
A30: 5 | B30: =A30*3.2 -> 16 | C30: 60 | D30: =C30-B30 -> 44 | E30: =(CleanedDataset!$F97-CleanedDataset!$E97)/CleanedDataset!$F97 -> 0.45 | F30: 23 | G30: =F30*C30-F30*B30 -> 1012 | H30: 35 | I30: =H30*C30-F30*B30 -> 1732 | J30: 0 | K30: =J30*C30-J30*B30 -> 0 | L30: 0 | M30: =L30*C30-L30*B30 -> 0 | N30: 0 | O30: =N30*C30-N30*B30 -> 0 | P30: 0 | Q30: =P30*C30-P30*B30 -> 0 | R30: 0 | S30: =R30*C30-R30*B30 -> 0 | T30: =SUM(P30,N30,L30,J30,H30,F30) -> 58 | U30: 1 | V30: 95 | W30: =A30*F30 -> 115
A31: 5 | B31: =A31*3 -> 15 | C31: 50 | D31: =C31-B31 -> 35 | E31: =(CleanedDataset!$F164-CleanedDataset!$E164)/CleanedDataset!$F164 -> 0.664 | F31: 860 | G31: =F31*C31-F31*B31 -> 30100 | H31: 744 | I31: =H31*C31-F31*B31 -> 24300 | J31: 343 | K31: =J31*C31-J31*B31 -> 12005 | L31: 320 | M31: =L31*C31-L31*B31 -> 11200 | N31: 287 | O31: =N31*C31-N31*B31 -> 10045 | P31: 680 | Q31: =P31*C31-P31*B31 -> 23800 | R31: 623 | S31: =R31*C31-R31*B31 -> 21805 | T31: =SUM(P31,N31,L31,J31,H31,F31) -> 3234 | U31: 1 | V31: 96 | W31: =A31*F31 -> 4300
A32: 7 | B32: =A32*2.8 -> 19.6 | C32: 45 | D32: =C32-B32 -> 25.4 | E32: =(CleanedDataset!$F60-CleanedDataset!$E60)/CleanedDataset!$F60 -> 0.81333333 | F32: 1064 | G32: =F32*C32-F32*B32 -> 27025.6 | H32: 1153 | I32: =H32*C32-F32*B32 -> 31030.6 | J32: 1979 | K32: =J32*C32-J32*B32 -> 50266.6 | L32: 2901 | M32: =L32*C32-L32*B32 -> 73685.4 | N32: 2434 | O32: =N32*C32-N32*B32 -> 61823.6 | P32: 1693 | Q32: =P32*C32-P32*B32 -> 43002.2 | R32: 1311 | S32: =R32*C32-R32*B32 -> 33299.4 | T32: =SUM(P32,N32,L32,J32,H32,F32) -> 11224 | U32: 1 | V32: 94 | W32: =A32*F32 -> 7448
A33: 7 | B33: =A33*3 -> 21 | C33: 55 | D33: =C33-B33 -> 34 | E33: =(CleanedDataset!$F87-CleanedDataset!$E87)/CleanedDataset!$F87 -> 0.49152542 | F33: 23 | G33: =F33*C33-F33*B33 -> 782 | H33: 15 | I33: =H33*C33-F33*B33 -> 342 | J33: 0 | K33: =J33*C33-J33*B33 -> 0 | L33: 0 | M33: =L33*C33-L33*B33 -> 0 | N33: 0 | O33: =N33*C33-N33*B33 -> 0 | P33: 0 | Q33: =P33*C33-P33*B33 -> 0 | R33: 0 | S33: =R33*C33-R33*B33 -> 0 | T33: =SUM(P33,N33,L33,J33,H33,F33) -> 38 | U33: 1 | V33: 90 | W33: =A33*F33 -> 161
A34: 7 | B34: =A34*3 -> 21 | C34: 55 | D34: =C34-B34 -> 34 | E34: =(CleanedDataset!$F169-CleanedDataset!$E169)/CleanedDataset!$F169 -> 0.49090909 | F34: 1578 | G34: =F34*C34-F34*B34 -> 53652 | H34: 1450 | I34: =H34*C34-F34*B34 -> 46612 | J34: 1135 | K34: =J34*C34-J34*B34 -> 38590 | L34: 957 | M34: =L34*C34-L34*B34 -> 32538 | N34: 2300 | O34: =N34*C34-N34*B34 -> 78200 | P34: 2780 | Q34: =P34*C34-P34*B34 -> 94520 | R34: 2800 | S34: =R34*C34-R34*B34 -> 95200 | T34: =SUM(P34,N34,L34,J34,H34,F34) -> 10200 | U34: 1 | V34: 95 | W34: =A34*F34 -> 11046
A35: 30 | B35: =A35*3 -> 90 | C35: 120 | D35: =C35-B35 -> 30 | E35: =(CleanedDataset!$F74-CleanedDataset!$E74)/CleanedDataset!$F74 -> 0.80588235 | F35: 8 | G35: =F35*C35-F35*B35 -> 240 | H35: 0 | I35: =H35*C35-F35*B35 -> -720 | J35: 0 | K35: =J35*C35-J35*B35 -> 0 | L35: 0 | M35: =L35*C35-L35*B35 -> 0 | N35: 0 | O35: =N35*C35-N35*B35 -> 0 | P35: 0 | Q35: =P35*C35-P35*B35 -> 0 | R35: 0 | S35: =R35*C35-R35*B35 -> 0 | T35: =SUM(P35,N35,L35,J35,H35,F35) -> 8 | U35: 1 | V35: 97 | W35: =A35*F35 -> 240
A36: 30 | B36: =A36*3.2 -> 96 | C36: 150 | D36: =C36-B36 -> 54 | E36: =(CleanedDataset!$F79-CleanedDataset!$E79)/CleanedDataset!$F79 -> -0.25263158 | F36: 26 | G36: =F36*C36-F36*B36 -> 1404 | H36: 25 | I36: =H36*C36-F36*B36 -> 1254 | J36: 0 | K36: =J36*C36-J36*B36 -> 0 | L36: 0 | M36: =L36*C36-L36*B36 -> 0 | N36: 0 | O36: =N36*C36-N36*B36 -> 0 | P36: 0 | Q36: =P36*C36-P36*B36 -> 0 | R36: 0 | S36: =R36*C36-R36*B36 -> 0 | T36: =SUM(P36,N36,L36,J36,H36,F36) -> 51 | U36: 1 | V36: 100 | W36: =A36*F36 -> 780
A37: 30 | B37: =A37*3.2 -> 96 | C37: 120 | D37: =C37-B37 -> 24 | E37: =(CleanedDataset!$F121-CleanedDataset!$E121)/CleanedDataset!$F121 -> 0.52 | F37: 42 | G37: =F37*C37-F37*B37 -> 1008 | H37: 47 | I37: =H37*C37-F37*B37 -> 1608 | J37: 12 | K37: =J37*C37-J37*B37 -> 288 | L37: 7 | M37: =L37*C37-L37*B37 -> 168 | N37: 71 | O37: =N37*C37-N37*B37 -> 1704 | P37: 29 | Q37: =P37*C37-P37*B37 -> 696 | R37: 31 | S37: =R37*C37-R37*B37 -> 744 | T37: =SUM(P37,N37,L37,J37,H37,F37) -> 208 | U37: 1 | V37: 96 | W37: =A37*F37 -> 1260
A38: 30 | B38: =A38*3 -> 90 | C38: 120 | D38: =C38-B38 -> 30 | E38: =(CleanedDataset!$F131-CleanedDataset!$E131)/CleanedDataset!$F131 -> 0.58933333 | F38: 5 | G38: =F38*C38-F38*B38 -> 150 | H38: 0 | I38: =H38*C38-F38*B38 -> -450 | J38: 0 | K38: =J38*C38-J38*B38 -> 0 | L38: 0 | M38: =L38*C38-L38*B38 -> 0 | N38: 0 | O38: =N38*C38-N38*B38 -> 0 | P38: 0 | Q38: =P38*C38-P38*B38 -> 0 | R38: 0 | S38: =R38*C38-R38*B38 -> 0 | T38: =SUM(P38,N38,L38,J38,H38,F38) -> 5 | U38: 1 | V38: 96 | W38: =A38*F38 -> 150
A39: 40 | B39: =A39*2.8 -> 112 | C39: 359 | D39: =C39-B39 -> 247 | E39: =(CleanedDataset!$F28-CleanedDataset!$E28)/CleanedDataset!$F28 -> 0.73333333 | F39: 41 | G39: =F39*C39-F39*B39 -> 10127 | H39: 106 | I39: =H39*C39-F39*B39 -> 33462 | J39: 81 | K39: =J39*C39-J39*B39 -> 20007 | L39: 215 | M39: =L39*C39-L39*B39 -> 53105 | N39: 255 | O39: =N39*C39-N39*B39 -> 62985 | P39: 72 | Q39: =P39*C39-P39*B39 -> 17784 | R39: 21 | S39: =R39*C39-R39*B39 -> 5187 | T39: =SUM(P39,N39,L39,J39,H39,F39) -> 770 | U39: 1 | V39: 93 | W39: =A39*F39 -> 1640
A40: 40 | B40: =A40*3.2 -> 128 | C40: 399 | D40: =C40-B40 -> 271 | E40: =(CleanedDataset!$F80-CleanedDataset!$E80)/CleanedDataset!$F80 -> -0.20888889 | F40: 30 | G40: =F40*C40-F40*B40 -> 8130 | H40: 0 | I40: =H40*C40-F40*B40 -> -3840 | J40: 0 | K40: =J40*C40-J40*B40 -> 0 | L40: 0 | M40: =L40*C40-L40*B40 -> 0 | N40: 0 | O40: =N40*C40-N40*B40 -> 0 | P40: 0 | Q40: =P40*C40-P40*B40 -> 0 | R40: 0 | S40: =R40*C40-R40*B40 -> 0 | T40: =SUM(P40,N40,L40,J40,H40,F40) -> 30 | U40: 1 | V40: 99 | W40: =A40*F40 -> 1200
A41: 40 | B41: =A41*3.2 -> 128 | C41: 399 | D41: =C41-B41 -> 271 | E41: =(CleanedDataset!$F123-CleanedDataset!$E123)/CleanedDataset!$F123 -> 0.624 | F41: 55 | G41: =F41*C41-F41*B41 -> 14905 | H41: 45 | I41: =H41*C41-F41*B41 -> 10915 | J41: 0 | K41: =J41*C41-J41*B41 -> 0 | L41: 0 | M41: =L41*C41-L41*B41 -> 0 | N41: 0 | O41: =N41*C41-N41*B41 -> 0 | P41: 0 | Q41: =P41*C41-P41*B41 -> 0 | R41: 0 | S41: =R41*C41-R41*B41 -> 0 | T41: =SUM(P41,N41,L41,J41,H41,F41) -> 100 | U41: 1 | V41: 98 | W41: =A41*F41 -> 2200
A42: 7.5 | B42: =A42*2.8 -> 21 | C42: 58 | D42: =C42-B42 -> 37 | E42: =(CleanedDataset!$F41-CleanedDataset!$E41)/CleanedDataset!$F41 -> 0.56444444 | F42: 94 | G42: =F42*C42-F42*B42 -> 3478 | H42: 138 | I42: =H42*C42-F42*B42 -> 6030 | J42: 124 | K42: =J42*C42-J42*B42 -> 4588 | L42: 72 | M42: =L42*C42-L42*B42 -> 2664 | N42: 10 | O42: =N42*C42-N42*B42 -> 370 | P42: 0 | Q42: =P42*C42-P42*B42 -> 0 | R42: 0 | S42: =R42*C42-R42*B42 -> 0 | T42: =SUM(P42,N42,L42,J42,H42,F42) -> 438 | U42: 1 | V42: 99 | W42: =A42*F42 -> 705
A43: 7.5 | B43: =A43*3 -> 22.5 | C43: 70 | D43: =C43-B43 -> 47.5 | E43: =(CleanedDataset!$F73-CleanedDataset!$E73)/CleanedDataset!$F73 -> 0.82222222 | F43: 5 | G43: =F43*C43-F43*B43 -> 237.5 | H43: 0 | I43: =H43*C43-F43*B43 -> -112.5 | J43: 0 | K43: =J43*C43-J43*B43 -> 0 | L43: 0 | M43: =L43*C43-L43*B43 -> 0 | N43: 0 | O43: =N43*C43-N43*B43 -> 0 | P43: 0 | Q43: =P43*C43-P43*B43 -> 0 | R43: 0 | S43: =R43*C43-R43*B43 -> 0 | T43: =SUM(P43,N43,L43,J43,H43,F43) -> 5 | U43: 1 | V43: 96 | W43: =A43*F43 -> 37.5
A44: 7.5 | B44: =A44*3 -> 22.5 | C44: 70 | D44: =C44-B44 -> 47.5 | E44: =(CleanedDataset!$F159-CleanedDataset!$E159)/CleanedDataset!$F159 -> 0.25 | F44: 360 | G44: =F44*C44-F44*B44 -> 17100 | H44: 245 | I44: =H44*C44-F44*B44 -> 9050 | J44: 133 | K44: =J44*C44-J44*B44 -> 6317.5 | L44: 88 | M44: =L44*C44-L44*B44 -> 4180 | N44: 10 | O44: =N44*C44-N44*B44 -> 475 | P44: 0 | Q44: =P44*C44-P44*B44 -> 0 | R44: 0 | S44: =R44*C44-R44*B44 -> 0 | T44: =SUM(P44,N44,L44,J44,H44,F44) -> 836 | U44: 1 | V44: 99 | W44: =A44*F44 -> 2700
A45: 10 | B45: =A45*2.8 -> 28 | C45: 130 | D45: =C45-B45 -> 102 | E45: =(CleanedDataset!$F14-CleanedDataset!$E14)/CleanedDataset!$F14 -> 0.70666667 | F45: 15 | G45: =F45*C45-F45*B45 -> 1530 | H45: 15 | I45: =H45*C45-F45*B45 -> 1530 | J45: 0 | K45: =J45*C45-J45*B45 -> 0 | L45: 0 | M45: =L45*C45-L45*B45 -> 0 | N45: 0 | O45: =N45*C45-N45*B45 -> 0 | P45: 0 | Q45: =P45*C45-P45*B45 -> 0 | R45: 0 | S45: =R45*C45-R45*B45 -> 0 | T45: =SUM(P45,N45,L45,J45,H45,F45) -> 30 | U45: 1 | V45: 94 | W45: =A45*F45 -> 150
A46: 4.5 | B46: =A46*2.8 -> 12.6 | C46: 40 | D46: =C46-B46 -> 27.4 | E46: =(CleanedDataset!$F29-CleanedDataset!$E29)/CleanedDataset!$F29 -> 0.7 | F46: 41 | G46: =F46*C46-F46*B46 -> 1123.4 | H46: 68 | I46: =H46*C46-F46*B46 -> 2203.4 | J46: 183 | K46: =J46*C46-J46*B46 -> 5014.2 | L46: 73 | M46: =L46*C46-L46*B46 -> 2000.2 | N46: 79 | O46: =N46*C46-N46*B46 -> 2164.6 | P46: 314 | Q46: =P46*C46-P46*B46 -> 8603.6 | R46: 156 | S46: =R46*C46-R46*B46 -> 4274.4 | T46: =SUM(P46,N46,L46,J46,H46,F46) -> 758 | U46: 1 | V46: 97 | W46: =A46*F46 -> 184.5
A47: 8 | B47: =A47*2.8 -> 22.4 | C47: 65 | D47: =C47-B47 -> 42.6 | E47: =(CleanedDataset!$F34-CleanedDataset!$E34)/CleanedDataset!$F34 -> 0.77272727 | F47: 60 | G47: =F47*C47-F47*B47 -> 2556 | H47: 68 | I47: =H47*C47-F47*B47 -> 3076 | J47: 315 | K47: =J47*C47-J47*B47 -> 13419 | L47: 56 | M47: =L47*C47-L47*B47 -> 2385.6 | N47: 132 | O47: =N47*C47-N47*B47 -> 5623.2 | P47: 160 | Q47: =P47*C47-P47*B47 -> 6816 | R47: 168 | S47: =R47*C47-R47*B47 -> 7156.8 | T47: =SUM(P47,N47,L47,J47,H47,F47) -> 791 | U47: 1 | V47: 99 | W47: =A47*F47 -> 480
A48: 9 | B48: =A48*2.8 -> 25.2 | C48: 45 | D48: =C48-B48 -> 19.8 | E48: =(CleanedDataset!$F39-CleanedDataset!$E39)/CleanedDataset!$F39 -> 0.61818182 | F48: 80 | G48: =F48*C48-F48*B48 -> 1584 | H48: 71 | I48: =H48*C48-F48*B48 -> 1179 | J48: 200 | K48: =J48*C48-J48*B48 -> 3960 | L48: 114 | M48: =L48*C48-L48*B48 -> 2257.2 | N48: 210 | O48: =N48*C48-N48*B48 -> 4158 | P48: 116 | Q48: =P48*C48-P48*B48 -> 2296.8 | R48: 408 | S48: =R48*C48-R48*B48 -> 8078.4 | T48: =SUM(P48,N48,L48,J48,H48,F48) -> 791 | U48: 1 | V48: 97 | W48: =A48*F48 -> 720
A49: 3.5 | B49: =A49*2.8 -> 9.8 | C49: 35 | D49: =C49-B49 -> 25.2 | E49: =(CleanedDataset!$F44-CleanedDataset!$E44)/CleanedDataset!$F44 -> 0.69387755 | F49: 124 | G49: =F49*C49-F49*B49 -> 3124.8 | H49: 4 | I49: =H49*C49-F49*B49 -> -1075.2 | J49: 127 | K49: =J49*C49-J49*B49 -> 3200.4 | L49: 35 | M49: =L49*C49-L49*B49 -> 882 | N49: 38 | O49: =N49*C49-N49*B49 -> 957.6 | P49: 12 | Q49: =P49*C49-P49*B49 -> 302.4 | R49: 0 | S49: =R49*C49-R49*B49 -> 0 | T49: =SUM(P49,N49,L49,J49,H49,F49) -> 340 | U49: 1 | V49: 97 | W49: =A49*F49 -> 434
A50: 10 | B50: =A50*3 -> 30 | C50: 145 | D50: =C50-B50 -> 115 | E50: =(CleanedDataset!$F70-CleanedDataset!$E70)/CleanedDataset!$F70 -> 0.79310345 | F50: 2 | G50: =F50*C50-F50*B50 -> 230 | H50: 0 | I50: =H50*C50-F50*B50 -> -60 | J50: 0 | K50: =J50*C50-J50*B50 -> 0 | L50: 0 | M50: =L50*C50-L50*B50 -> 0 | N50: 0 | O50: =N50*C50-N50*B50 -> 0 | P50: 0 | Q50: =P50*C50-P50*B50 -> 0 | R50: 0 | S50: =R50*C50-R50*B50 -> 0 | T50: =SUM(P50,N50,L50,J50,H50,F50) -> 2 | U50: 1 | V50: 100 | W50: =A50*F50 -> 20
A51: 3.5 | B51: =A51*3.2 -> 11.2 | C51: 60 | D51: =C51-B51 -> 48.8 | E51: =(CleanedDataset!$F107-CleanedDataset!$E107)/CleanedDataset!$F107 -> 0.4 | F51: 3 | G51: =F51*C51-F51*B51 -> 146.4 | H51: 0 | I51: =H51*C51-F51*B51 -> -33.6 | J51: 0 | K51: =J51*C51-J51*B51 -> 0 | L51: 0 | M51: =L51*C51-L51*B51 -> 0 | N51: 0 | O51: =N51*C51-N51*B51 -> 0 | P51: 0 | Q51: =P51*C51-P51*B51 -> 0 | R51: 0 | S51: =R51*C51-R51*B51 -> 0 | T51: =SUM(P51,N51,L51,J51,H51,F51) -> 3 | U51: 1 | V51: 94 | W51: =A51*F51 -> 10.5
A52: 4.5 | B52: =A52*3.2 -> 14.4 | C52: 65 | D52: =C52-B52 -> 50.6 | E52: =(CleanedDataset!$F109-CleanedDataset!$E109)/CleanedDataset!$F109 -> 0.44615385 | F52: 5 | G52: =F52*C52-F52*B52 -> 253 | H52: 0 | I52: =H52*C52-F52*B52 -> -72 | J52: 0 | K52: =J52*C52-J52*B52 -> 0 | L52: 0 | M52: =L52*C52-L52*B52 -> 0 | N52: 0 | O52: =N52*C52-N52*B52 -> 0 | P52: 0 | Q52: =P52*C52-P52*B52 -> 0 | R52: 0 | S52: =R52*C52-R52*B52 -> 0 | T52: =SUM(P52,N52,L52,J52,H52,F52) -> 5 | U52: 1 | V52: 94 | W52: =A52*F52 -> 22.5
A53: 8 | B53: =A53*3.2 -> 25.6 | C53: 85 | D53: =C53-B53 -> 59.4 | E53: =(CleanedDataset!$F110-CleanedDataset!$E110)/CleanedDataset!$F110 -> 0.48 | F53: 5 | G53: =F53*C53-F53*B53 -> 297 | H53: 0 | I53: =H53*C53-F53*B53 -> -128 | J53: 0 | K53: =J53*C53-J53*B53 -> 0 | L53: 0 | M53: =L53*C53-L53*B53 -> 0 | N53: 0 | O53: =N53*C53-N53*B53 -> 0 | P53: 0 | Q53: =P53*C53-P53*B53 -> 0 | R53: 0 | S53: =R53*C53-R53*B53 -> 0 | T53: =SUM(P53,N53,L53,J53,H53,F53) -> 5 | U53: 1 | V53: 97 | W53: =A53*F53 -> 40
A54: 10 | B54: =A54*3.2 -> 32 | C54: 145 | D54: =C54-B54 -> 113 | E54: =(CleanedDataset!$F113-CleanedDataset!$E113)/CleanedDataset!$F113 -> 0.37777778 | F54: 13 | G54: =F54*C54-F54*B54 -> 1469 | H54: 10 | I54: =H54*C54-F54*B54 -> 1034 | J54: 0 | K54: =J54*C54-J54*B54 -> 0 | L54: 0 | M54: =L54*C54-L54*B54 -> 0 | N54: 0 | O54: =N54*C54-N54*B54 -> 0 | P54: 0 | Q54: =P54*C54-P54*B54 -> 0 | R54: 0 | S54: =R54*C54-R54*B54 -> 0 | T54: =SUM(P54,N54,L54,J54,H54,F54) -> 23 | U54: 1 | V54: 96 | W54: =A54*F54 -> 130
A55: 10 | B55: =A55*3 -> 30 | C55: 145 | D55: =C55-B55 -> 115 | E55: =(CleanedDataset!$F140-CleanedDataset!$E140)/CleanedDataset!$F140 -> 0.58 | F55: 10 | G55: =F55*C55-F55*B55 -> 1150 | H55: 0 | I55: =H55*C55-F55*B55 -> -300 | J55: 0 | K55: =J55*C55-J55*B55 -> 0 | L55: 0 | M55: =L55*C55-L55*B55 -> 0 | N55: 0 | O55: =N55*C55-N55*B55 -> 0 | P55: 0 | Q55: =P55*C55-P55*B55 -> 0 | R55: 0 | S55: =R55*C55-R55*B55 -> 0 | T55: =SUM(P55,N55,L55,J55,H55,F55) -> 10 | U55: 1 | V55: 94 | W55: =A55*F55 -> 100
A56: 3.5 | B56: =A56*3 -> 10.5 | C56: 45 | D56: =C56-B56 -> 34.5 | E56: =(CleanedDataset!$F143-CleanedDataset!$E143)/CleanedDataset!$F143 -> 0.55862069 | F56: 24 | G56: =F56*C56-F56*B56 -> 828 | H56: 0 | I56: =H56*C56-F56*B56 -> -252 | J56: 0 | K56: =J56*C56-J56*B56 -> 0 | L56: 0 | M56: =L56*C56-L56*B56 -> 0 | N56: 0 | O56: =N56*C56-N56*B56 -> 0 | P56: 0 | Q56: =P56*C56-P56*B56 -> 0 | R56: 0 | S56: =R56*C56-R56*B56 -> 0 | T56: =SUM(P56,N56,L56,J56,H56,F56) -> 24 | U56: 1 | V56: 91 | W56: =A56*F56 -> 84
A57: 4.5 | B57: =A57*3 -> 13.5 | C57: 50 | D57: =C57-B57 -> 36.5 | E57: =(CleanedDataset!$F145-CleanedDataset!$E145)/CleanedDataset!$F145 -> 0.53846154 | F57: 40 | G57: =F57*C57-F57*B57 -> 1460 | H57: 33 | I57: =H57*C57-F57*B57 -> 1110 | J57: 45 | K57: =J57*C57-J57*B57 -> 1642.5 | L57: 20 | M57: =L57*C57-L57*B57 -> 730 | N57: 15 | O57: =N57*C57-N57*B57 -> 547.5 | P57: 55 | Q57: =P57*C57-P57*B57 -> 2007.5 | R57: 46 | S57: =R57*C57-R57*B57 -> 1679 | T57: =SUM(P57,N57,L57,J57,H57,F57) -> 208 | U57: 1 | V57: 100 | W57: =A57*F57 -> 180
A58: 8 | B58: =A58*3 -> 24 | C58: 75 | D58: =C58-B58 -> 51 | E58: =(CleanedDataset!$F151-CleanedDataset!$E151)/CleanedDataset!$F151 -> 0.648 | F58: 135 | G58: =F58*C58-F58*B58 -> 6885 | H58: 100 | I58: =H58*C58-F58*B58 -> 4260 | J58: 87 | K58: =J58*C58-J58*B58 -> 4437 | L58: 15 | M58: =L58*C58-L58*B58 -> 765 | N58: 57 | O58: =N58*C58-N58*B58 -> 2907 | P58: 180 | Q58: =P58*C58-P58*B58 -> 9180 | R58: 167 | S58: =R58*C58-R58*B58 -> 8517 | T58: =SUM(P58,N58,L58,J58,H58,F58) -> 574 | U58: 1 | V58: 100 | W58: =A58*F58 -> 1080
A59: 9 | B59: =A59*3 -> 27 | C59: 55 | D59: =C59-B59 -> 28 | E59: =(CleanedDataset!$F157-CleanedDataset!$E157)/CleanedDataset!$F157 -> 0.25 | F59: 230 | G59: =F59*C59-F59*B59 -> 6440 | H59: 185 | I59: =H59*C59-F59*B59 -> 3965 | J59: 74 | K59: =J59*C59-J59*B59 -> 2072 | L59: 67 | M59: =L59*C59-L59*B59 -> 1876 | N59: 55 | O59: =N59*C59-N59*B59 -> 1540 | P59: 80 | Q59: =P59*C59-P59*B59 -> 2240 | R59: 250 | S59: =R59*C59-R59*B59 -> 7000 | T59: =SUM(P59,N59,L59,J59,H59,F59) -> 691 | U59: 1 | V59: 90 | W59: =A59*F59 -> 2070
A60: 5.5 | B60: =A60*2.8 -> 15.4 | C60: 75 | D60: =C60-B60 -> 59.6 | E60: =(CleanedDataset!$F15-CleanedDataset!$E15)/CleanedDataset!$F15 -> 0.725 | F60: 15 | G60: =F60*C60-F60*B60 -> 894 | H60: 15 | I60: =H60*C60-F60*B60 -> 894 | J60: 7 | K60: =J60*C60-J60*B60 -> 417.2 | L60: 8 | M60: =L60*C60-L60*B60 -> 476.8 | N60: 27 | O60: =N60*C60-N60*B60 -> 1609.2 | P60: 12 | Q60: =P60*C60-P60*B60 -> 715.2 | R60: 177 | S60: =R60*C60-R60*B60 -> 10549.2 | T60: =SUM(P60,N60,L60,J60,H60,F60) -> 84 | U60: 1 | V60: 97 | W60: =A60*F60 -> 82.5
A61: 5.5 | B61: =A61*3 -> 16.5 | C61: 99 | D61: =C61-B61 -> 82.5 | E61: =(CleanedDataset!$F71-CleanedDataset!$E71)/CleanedDataset!$F71 -> 0.78461538 | F61: 2 | G61: =F61*C61-F61*B61 -> 165 | H61: 0 | I61: =H61*C61-F61*B61 -> -33 | J61: 0 | K61: =J61*C61-J61*B61 -> 0 | L61: 0 | M61: =L61*C61-L61*B61 -> 0 | N61: 0 | O61: =N61*C61-N61*B61 -> 0 | P61: 0 | Q61: =P61*C61-P61*B61 -> 0 | R61: 0 | S61: =R61*C61-R61*B61 -> 0 | T61: =SUM(P61,N61,L61,J61,H61,F61) -> 2 | U61: 1 | V61: 90 | W61: =A61*F61 -> 11
A62: 5.5 | B62: =A62*3.2 -> 17.6 | C62: 99 | D62: =C62-B62 -> 81.4 | E62: =(CleanedDataset!$F114-CleanedDataset!$E114)/CleanedDataset!$F114 -> 0.37777778 | F62: 13 | G62: =F62*C62-F62*B62 -> 1058.2 | H62: 10 | I62: =H62*C62-F62*B62 -> 761.2 | J62: 0 | K62: =J62*C62-J62*B62 -> 0 | L62: 0 | M62: =L62*C62-L62*B62 -> 0 | N62: 0 | O62: =N62*C62-N62*B62 -> 0 | P62: 0 | Q62: =P62*C62-P62*B62 -> 0 | R62: 0 | S62: =R62*C62-R62*B62 -> 0 | T62: =SUM(P62,N62,L62,J62,H62,F62) -> 23 | U62: 1 | V62: 93 | W62: =A62*F62 -> 71.5
A63: 5.5 | B63: =A63*3 -> 16.5 | C63: 85 | D63: =C63-B63 -> 68.5 | E63: =(CleanedDataset!$F141-CleanedDataset!$E141)/CleanedDataset!$F141 -> 0.47027027 | F63: 10 | G63: =F63*C63-F63*B63 -> 685 | H63: 0 | I63: =H63*C63-F63*B63 -> -165 | J63: 0 | K63: =J63*C63-J63*B63 -> 0 | L63: 0 | M63: =L63*C63-L63*B63 -> 0 | N63: 0 | O63: =N63*C63-N63*B63 -> 0 | P63: 0 | Q63: =P63*C63-P63*B63 -> 0 | R63: 0 | S63: =R63*C63-R63*B63 -> 0 | T63: =SUM(P63,N63,L63,J63,H63,F63) -> 10 | U63: 1 | V63: 100 | W63: =A63*F63 -> 55
A64: 5 | B64: =A64*2.8 -> 14 | C64: 65 | D64: =C64-B64 -> 51 | E64: =(CleanedDataset!$F57-CleanedDataset!$E57)/CleanedDataset!$F57 -> 0.69882353 | F64: 728 | G64: =F64*C64-F64*B64 -> 37128 | H64: 871 | I64: =H64*C64-F64*B64 -> 46423 | J64: 913 | K64: =J64*C64-J64*B64 -> 46563 | L64: 1800 | M64: =L64*C64-L64*B64 -> 91800 | N64: 1315 | O64: =N64*C64-N64*B64 -> 67065 | P64: 577 | Q64: =P64*C64-P64*B64 -> 29427 | R64: 573 | S64: =R64*C64-R64*B64 -> 29223 | T64: =SUM(P64,N64,L64,J64,H64,F64) -> 6204 | U64: 1 | V64: 93 | W64: =A64*F64 -> 3640
A65: 4 | B65: =A65*2.8 -> 11.2 | C65: 45 | D65: =C65-B65 -> 33.8 | E65: =(CleanedDataset!$F59-CleanedDataset!$E59)/CleanedDataset!$F59 -> 0.65538462 | F65: 962 | G65: =F65*C65-F65*B65 -> 32515.6 | H65: 1465 | I65: =H65*C65-F65*B65 -> 55150.6 | J65: 1334 | K65: =J65*C65-J65*B65 -> 45089.2 | L65: 2383 | M65: =L65*C65-L65*B65 -> 80545.4 | N65: 1525 | O65: =N65*C65-N65*B65 -> 51545 | P65: 1582 | Q65: =P65*C65-P65*B65 -> 53471.6 | R65: 1539 | S65: =R65*C65-R65*B65 -> 52018.2 | T65: =SUM(P65,N65,L65,J65,H65,F65) -> 9251 | U65: 1 | V65: 100 | W65: =A65*F65 -> 3848
A66: 4 | B66: =A66*3 -> 12 | C66: 55 | D66: =C66-B66 -> 43 | E66: =(CleanedDataset!$F63-CleanedDataset!$E63)/CleanedDataset!$F63 -> 0.50909091 | F66: 0 | G66: =F66*C66-F66*B66 -> 0 | H66: 5 | I66: =H66*C66-F66*B66 -> 275 | J66: 0 | K66: =J66*C66-J66*B66 -> 0 | L66: 0 | M66: =L66*C66-L66*B66 -> 0 | N66: 0 | O66: =N66*C66-N66*B66 -> 0 | P66: 0 | Q66: =P66*C66-P66*B66 -> 0 | R66: 0 | S66: =R66*C66-R66*B66 -> 0 | T66: =SUM(P66,N66,L66,J66,H66,F66) -> 5 | U66: 1 | V66: 100 | W66: =A66*F66 -> 0
A67: 5 | B67: =A67*3 -> 15 | C67: 70 | D67: =C67-B67 -> 55 | E67: =(CleanedDataset!$F86-CleanedDataset!$E86)/CleanedDataset!$F86 -> 0.66666667 | F67: 15 | G67: =F67*C67-F67*B67 -> 825 | H67: 0 | I67: =H67*C67-F67*B67 -> -225 | J67: 0 | K67: =J67*C67-J67*B67 -> 0 | L67: 0 | M67: =L67*C67-L67*B67 -> 0 | N67: 0 | O67: =N67*C67-N67*B67 -> 0 | P67: 0 | Q67: =P67*C67-P67*B67 -> 0 | R67: 0 | S67: =R67*C67-R67*B67 -> 0 | T67: =SUM(P67,N67,L67,J67,H67,F67) -> 15 | U67: 1 | V67: 99 | W67: =A67*F67 -> 75
A68: 4 | B68: =A68*3 -> 12 | C68: 55 | D68: =C68-B68 -> 43 | E68: =(CleanedDataset!$F100-CleanedDataset!$E100)/CleanedDataset!$F100 -> 0.1 | F68: 0 | G68: =F68*C68-F68*B68 -> 0 | H68: 5 | I68: =H68*C68-F68*B68 -> 275 | J68: 0 | K68: =J68*C68-J68*B68 -> 0 | L68: 0 | M68: =L68*C68-L68*B68 -> 0 | N68: 0 | O68: =N68*C68-N68*B68 -> 0 | P68: 0 | Q68: =P68*C68-P68*B68 -> 0 | R68: 0 | S68: =R68*C68-R68*B68 -> 0 | T68: =SUM(P68,N68,L68,J68,H68,F68) -> 5 | U68: 1 | V68: 100 | W68: =A68*F68 -> 0
A69: 4 | B69: =A69*3 -> 12 | C69: 55 | D69: =C69-B69 -> 43 | E69: =(CleanedDataset!$F130-CleanedDataset!$E130)/CleanedDataset!$F130 -> 0.5875 | F69: 5 | G69: =F69*C69-F69*B69 -> 215 | H69: 0 | I69: =H69*C69-F69*B69 -> -60 | J69: 0 | K69: =J69*C69-J69*B69 -> 0 | L69: 0 | M69: =L69*C69-L69*B69 -> 0 | N69: 0 | O69: =N69*C69-N69*B69 -> 0 | P69: 0 | Q69: =P69*C69-P69*B69 -> 0 | R69: 0 | S69: =R69*C69-R69*B69 -> 0 | T69: =SUM(P69,N69,L69,J69,H69,F69) -> 5 | U69: 1 | V69: 95 | W69: =A69*F69 -> 20
A70: 5 | B70: =A70*3 -> 15 | C70: 70 | D70: =C70-B70 -> 55 | E70: =(CleanedDataset!$F132-CleanedDataset!$E132)/CleanedDataset!$F132 -> 0.70461538 | F70: 23 | G70: =F70*C70-F70*B70 -> 1265 | H70: 5 | I70: =H70*C70-F70*B70 -> 5 | J70: 0 | K70: =J70*C70-J70*B70 -> 0 | L70: 0 | M70: =L70*C70-L70*B70 -> 0 | N70: 0 | O70: =N70*C70-N70*B70 -> 0 | P70: 0 | Q70: =P70*C70-P70*B70 -> 0 | R70: 0 | S70: =R70*C70-R70*B70 -> 0 | T70: =SUM(P70,N70,L70,J70,H70,F70) -> 28 | U70: 1 | V70: 93 | W70: =A70*F70 -> 115
A71: 5 | B71: =A71*3 -> 15 | C71: 70 | D71: =C71-B71 -> 55 | E71: =(CleanedDataset!$F165-CleanedDataset!$E165)/CleanedDataset!$F165 -> 0.86 | F71: 890 | G71: =F71*C71-F71*B71 -> 48950 | H71: 765 | I71: =H71*C71-F71*B71 -> 40200 | J71: 521 | K71: =J71*C71-J71*B71 -> 28655 | L71: 220 | M71: =L71*C71-L71*B71 -> 12100 | N71: 349 | O71: =N71*C71-N71*B71 -> 19195 | P71: 1385 | Q71: =P71*C71-P71*B71 -> 76175 | R71: 1290 | S71: =R71*C71-R71*B71 -> 70950 | T71: =SUM(P71,N71,L71,J71,H71,F71) -> 4130 | U71: 1 | V71: 93 | W71: =A71*F71 -> 4450
A72: 4 | B72: =A72*3 -> 12 | C72: 55 | D72: =C72-B72 -> 43 | E72: =(CleanedDataset!$F168-CleanedDataset!$E168)/CleanedDataset!$F168 -> 0.61111111 | F72: 1450 | G72: =F72*C72-F72*B72 -> 62350 | H72: 834 | I72: =H72*C72-F72*B72 -> 28470 | J72: 620 | K72: =J72*C72-J72*B72 -> 26660 | L72: 348 | M72: =L72*C72-L72*B72 -> 14964 | N72: 930 | O72: =N72*C72-N72*B72 -> 39990 | P72: 870 | Q72: =P72*C72-P72*B72 -> 37410 | R72: 850 | S72: =R72*C72-R72*B72 -> 36550 | T72: =SUM(P72,N72,L72,J72,H72,F72) -> 5052 | U72: 1 | V72: 96 | W72: =A72*F72 -> 5800
A73: 5 | B73: =A73*2.8 -> 14 | C73: 85 | D73: =C73-B73 -> 71 | E73: =(CleanedDataset!$F48-CleanedDataset!$E48)/CleanedDataset!$F48 -> 0.75111111 | F73: 268 | G73: =F73*C73-F73*B73 -> 19028 | H73: 253 | I73: =H73*C73-F73*B73 -> 17753 | J73: 178 | K73: =J73*C73-J73*B73 -> 12638 | L73: 360 | M73: =L73*C73-L73*B73 -> 25560 | N73: 816 | O73: =N73*C73-N73*B73 -> 57936 | P73: 410 | Q73: =P73*C73-P73*B73 -> 29110 | R73: 301 | S73: =R73*C73-R73*B73 -> 21371 | T73: =SUM(P73,N73,L73,J73,H73,F73) -> 2285 | U73: 1 | V73: 93 | W73: =A73*F73 -> 1340
A74: 5 | B74: =A74*3 -> 15 | C74: 85 | D74: =C74-B74 -> 70 | E74: =(CleanedDataset!$F153-CleanedDataset!$E153)/CleanedDataset!$F153 -> 0.64893617 | F74: 180 | G74: =F74*C74-F74*B74 -> 12600 | H74: 0 | I74: =H74*C74-F74*B74 -> -2700 | J74: 0 | K74: =J74*C74-J74*B74 -> 0 | L74: 0 | M74: =L74*C74-L74*B74 -> 0 | N74: 0 | O74: =N74*C74-N74*B74 -> 0 | P74: 0 | Q74: =P74*C74-P74*B74 -> 0 | R74: 0 | S74: =R74*C74-R74*B74 -> 0 | T74: =SUM(P74,N74,L74,J74,H74,F74) -> 180 | U74: 1 | V74: 98 | W74: =A74*F74 -> 900
A75: 3.5 | B75: =A75*2.8 -> 9.8 | C75: 28 | D75: =C75-B75 -> 18.2 | E75: =(CleanedDataset!$F49-CleanedDataset!$E49)/CleanedDataset!$F49 -> 0.73417722 | F75: 299 | G75: =F75*C75-F75*B75 -> 5441.8 | H75: 83 | I75: =H75*C75-F75*B75 -> -606.2 | J75: 176 | K75: =J75*C75-J75*B75 -> 3203.2 | L75: 400 | M75: =L75*C75-L75*B75 -> 7280 | N75: 427 | O75: =N75*C75-N75*B75 -> 7771.4 | P75: 459 | Q75: =P75*C75-P75*B75 -> 8353.8 | R75: 369 | S75: =R75*C75-R75*B75 -> 6715.8 | T75: =SUM(P75,N75,L75,J75,H75,F75) -> 1844 | U75: 1 | V75: 99 | W75: =A75*F75 -> 1046.5
A76: 3.5 | B76: =A76*2.8 -> 9.8 | C76: 25 | D76: =C76-B76 -> 15.2 | E76: =(CleanedDataset!$F52-CleanedDataset!$E52)/CleanedDataset!$F52 -> 0.58 | F76: 382 | G76: =F76*C76-F76*B76 -> 5806.4 | H76: 425 | I76: =H76*C76-F76*B76 -> 6881.4 | J76: 323 | K76: =J76*C76-J76*B76 -> 4909.6 | L76: 238 | M76: =L76*C76-L76*B76 -> 3617.6 | N76: 484 | O76: =N76*C76-N76*B76 -> 7356.8 | P76: 394 | Q76: =P76*C76-P76*B76 -> 5988.8 | R76: 213 | S76: =R76*C76-R76*B76 -> 3237.6 | T76: =SUM(P76,N76,L76,J76,H76,F76) -> 2246 | U76: 1 | V76: 97 | W76: =A76*F76 -> 1337
A77: 3.5 | B77: =A77*3 -> 10.5 | C77: 35 | D77: =C77-B77 -> 24.5 | E77: =(CleanedDataset!$F64-CleanedDataset!$E64)/CleanedDataset!$F64 -> 0.44 | F77: 0 | G77: =F77*C77-F77*B77 -> 0 | H77: 13 | I77: =H77*C77-F77*B77 -> 455 | J77: 0 | K77: =J77*C77-J77*B77 -> 0 | L77: 0 | M77: =L77*C77-L77*B77 -> 0 | N77: 0 | O77: =N77*C77-N77*B77 -> 0 | P77: 0 | Q77: =P77*C77-P77*B77 -> 0 | R77: 0 | S77: =R77*C77-R77*B77 -> 0 | T77: =SUM(P77,N77,L77,J77,H77,F77) -> 13 | U77: 1 | V77: 100 | W77: =A77*F77 -> 0
A78: 3.5 | B78: =A78*3 -> 10.5 | C78: 35 | D78: =C78-B78 -> 24.5 | E78: =(CleanedDataset!$F160-CleanedDataset!$E160)/CleanedDataset!$F160 -> 0.7 | F78: 433 | G78: =F78*C78-F78*B78 -> 10608.5 | H78: 350 | I78: =H78*C78-F78*B78 -> 7703.5 | J78: 235 | K78: =J78*C78-J78*B78 -> 5757.5 | L78: 170 | M78: =L78*C78-L78*B78 -> 4165 | N78: 55 | O78: =N78*C78-N78*B78 -> 1347.5 | P78: 135 | Q78: =P78*C78-P78*B78 -> 3307.5 | R78: 120 | S78: =R78*C78-R78*B78 -> 2940 | T78: =SUM(P78,N78,L78,J78,H78,F78) -> 1378 | U78: 1 | V78: 99 | W78: =A78*F78 -> 1515.5
A79: 3.5 | B79: =A79*3 -> 10.5 | C79: 35 | D79: =C79-B79 -> 24.5 | E79: =(CleanedDataset!$F163-CleanedDataset!$E163)/CleanedDataset!$F163 -> 0.72 | F79: 530 | G79: =F79*C79-F79*B79 -> 12985 | H79: 480 | I79: =H79*C79-F79*B79 -> 11235 | J79: 257 | K79: =J79*C79-J79*B79 -> 6296.5 | L79: 200 | M79: =L79*C79-L79*B79 -> 4900 | N79: 230 | O79: =N79*C79-N79*B79 -> 5635 | P79: 580 | Q79: =P79*C79-P79*B79 -> 14210 | R79: 578 | S79: =R79*C79-R79*B79 -> 14161 | T79: =SUM(P79,N79,L79,J79,H79,F79) -> 2277 | U79: 1 | V79: 95 | W79: =A79*F79 -> 1855
A80: 35 | B80: =A80*2.8 -> 98 | C80: 135 | D80: =C80-B80 -> 37 | E80: =(CleanedDataset!$F43-CleanedDataset!$E43)/CleanedDataset!$F43 -> 0.82352941 | F80: 116 | G80: =F80*C80-F80*B80 -> 4292 | H80: 164 | I80: =H80*C80-F80*B80 -> 10772 | J80: 319 | K80: =J80*C80-J80*B80 -> 11803 | L80: 251 | M80: =L80*C80-L80*B80 -> 9287 | N80: 207 | O80: =N80*C80-N80*B80 -> 7659 | P80: 182 | Q80: =P80*C80-P80*B80 -> 6734 | R80: 54 | S80: =R80*C80-R80*B80 -> 1998 | T80: =SUM(P80,N80,L80,J80,H80,F80) -> 1239 | U80: 1 | V80: 96 | W80: =A80*F80 -> 4060
A81: 35 | B81: =A81*3.2 -> 112 | C81: 180 | D81: =C81-B81 -> 68 | E81: =(CleanedDataset!$F94-CleanedDataset!$E94)/CleanedDataset!$F94 -> 0.53125 | F81: 5 | G81: =F81*C81-F81*B81 -> 340 | H81: 0 | I81: =H81*C81-F81*B81 -> -560 | J81: 0 | K81: =J81*C81-J81*B81 -> 0 | L81: 0 | M81: =L81*C81-L81*B81 -> 0 | N81: 0 | O81: =N81*C81-N81*B81 -> 0 | P81: 0 | Q81: =P81*C81-P81*B81 -> 0 | R81: 0 | S81: =R81*C81-R81*B81 -> 0 | T81: =SUM(P81,N81,L81,J81,H81,F81) -> 5 | U81: 1 | V81: 98 | W81: =A81*F81 -> 175
A82: 35 | B82: =A82*3.2 -> 112 | C82: 180 | D82: =C82-B82 -> 68 | E82: =(CleanedDataset!$F103-CleanedDataset!$E103)/CleanedDataset!$F103 -> 0.5443038 | F82: 0 | G82: =F82*C82-F82*B82 -> 0 | H82: 89 | I82: =H82*C82-F82*B82 -> 16020 | J82: 0 | K82: =J82*C82-J82*B82 -> 0 | L82: 0 | M82: =L82*C82-L82*B82 -> 0 | N82: 0 | O82: =N82*C82-N82*B82 -> 0 | P82: 0 | Q82: =P82*C82-P82*B82 -> 0 | R82: 0 | S82: =R82*C82-R82*B82 -> 0 | T82: =SUM(P82,N82,L82,J82,H82,F82) -> 89 | U82: 1 | V82: 92 | W82: =A82*F82 -> 0
A83: 35 | B83: =A83*3.2 -> 112 | C83: 180 | D83: =C83-B83 -> 68 | E83: =(CleanedDataset!$F203-CleanedDataset!$E203)/CleanedDataset!$F203 -> 0.776 | F83: 5 | G83: =F83*C83-F83*B83 -> 340 | H83: 0 | I83: =H83*C83-F83*B83 -> -560 | J83: 0 | K83: =J83*C83-J83*B83 -> 0 | L83: 0 | M83: =L83*C83-L83*B83 -> 0 | N83: 0 | O83: =N83*C83-N83*B83 -> 0 | P83: 0 | Q83: =P83*C83-P83*B83 -> 0 | R83: 0 | S83: =R83*C83-R83*B83 -> 0 | T83: =SUM(P83,N83,L83,J83,H83,F83) -> 5 | U83: 1 | V83: 97 | W83: =A83*F83 -> 175
A84: 40 | B84: =A84*2.8 -> 112 | C84: 220 | D84: =C84-B84 -> 108 | E84: =(CleanedDataset!$F2-CleanedDataset!$E2)/CleanedDataset!$F2 -> 0.8208 | F84: 0 | G84: =F84*C84-F84*B84 -> 0 | H84: 1 | I84: =H84*C84-F84*B84 -> 220 | J84: 0 | K84: =J84*C84-J84*B84 -> 0 | L84: 1 | M84: =L84*C84-L84*B84 -> 108 | N84: 38 | O84: =N84*C84-N84*B84 -> 4104 | P84: 0 | Q84: =P84*C84-P84*B84 -> 0 | R84: 0 | S84: =R84*C84-R84*B84 -> 0 | T84: =SUM(P84,N84,L84,J84,H84,F84) -> 40 | U84: 1 | V84: 98 | W84: =A84*F84 -> 0
